Workbook

Sheet Registro_Actividades
A1: ID_Actividad | B1: Folio | C1: Fecha_Captura | D1: Clave_Proceso | E1: Clave_Proceso_Txt | F1: Meta | G1: Nombre_Meta | H1: Area | I1: Direccion | J1: Unidad_Medida | K1: Meta_Anual | L1: Enfoque_Actividad | M1: Nombre_Actividad | N1: Descripcion_Breve | O1: Temporalidad | P1: Fecha_Inicio | Q1: Fecha_Fin | R1: Total_Sesiones | S1: Disciplina | T1: Subdisciplina | U1: Tipo_Actividad | V1: Proceso_Institucional | W1: Formato | X1: Tipo_Espacio | Y1: Nombre_Espacio | Z1: Especifique_Espacio | AA1: Foto_Evidencia | AB1: Genera_Ingresos | AC1: Monto_Ingreso | AD1: Agentes_Con_Contrato | AE1: Cantidad_Agentes | AF1: Registros_INDAUTOR | AG1: Folio_INDAUTOR | AH1: Costo | AI1: Costo_Minimo | AJ1: Costo_Maximo | AK1: Detalle_Tarifas | AL1: Usuario_Registra | AM1: Promesa_NC | AN1: Eje_PG | AO1: Objetivo_PG | AP1: Estrategia_PG | AQ1: Acciones_PG | AR1: Eje_Tranversal_PEC | AS1: Enfoque_Accion | AT1: Linea_PEC | AU1: Estrategia_PEC | AV1: Acciones_PEC | AW1: Metas_PEC | AX1: Actividad | AY1: Categoria_Helper | AZ1: Tipo_Proceso_Formacion | BA1: Tipo_Oferta_Formacion | BB1: Tipo_Agente_Apoyado | BC1: Cantidad_Agente_Apoyado | BD1: Condicion_Agente | BE1: Nombre_Agente | BF1: Con_Apoyo | BG1: Tipo_Apoyo | BH1: Monto_Total_Contratado | BI1: Tipo_Proyecto_Artistico | BJ1: Tipo_Circulacion | BK1: Tipo_Patrimonio | BL1: Tipo_Convenio | BM1: Vinculacion_Actores | BN1: Tipo_Vinculacion | BO1: Detalle_Calendario | BP1: Ubicacion_GPS | BQ1: Estado_Actividad | BR1: Indicador_Oficial | BS1: Nombre_Indicador | BT1: Instrumento
A2: ACT00031 | B2: SC-260604-111329 | C2: 46177.468 | D2: 94 | E2: PB3572 | F2: Gestión de programas de exposiciones, actividades formativas y académicas en los Museos de la Secretaría de Cultura y actividades extramuros | G2: Creación de actividades para poblaciones especificas como mujeres, niños y niñas, adultos mayores y discapacidad en los Museos adscritos a la Secretaria de Cultura | H2: SUBSECRETARÍA DE DESARROLLO Y PROMOCIÓN ARTÍSTICA Y CULTURAL | I2: DIRECCIÓN GENERAL DE MUSEOS, ARTES VISUALES Y EXPOSICIONES | J2: Número de Actividades realizadas | K2: 12 | L2: Cultural | M2: Juguetes tipicos en estampa alternativa | N2: Fomento del sentido crítico sobre la importancia de las artes visuales en el desarrollo cognitivo, social, humano y artístico. | O2: Única | P2: 46120 | Q2: 46120 | R2: 1 | S2: Cultura comunitaria | T2: Procesos de memoria | U2: Taller | V2: Ninguna | W2: Presencial | X2: Espacio Público | Z2: Centro Nuevo Comienzo Balcones de las Joyas | AB2: FALSE | AD2: FALSE | AF2: FALSE | AH2: Sin costo | AL2: ccardonav@guanajuato.gob.mx | AM2: Arraigo y empoderamiento cultural de comunidades. | AN2: 2 Igualdad | AO2: 2.2 Fortalecer cohesión social | AP2: 2.2 Fortalecer cohesión social | AQ2: 2.2.3.2 Promover la participación de grupos prioritarios en actividades culturales | AR2: Inclusión | AS2: Ninguno (Población General) | AT2: Fortalecimiento de la participación ciudadana y la mediación cultural | AU2: Impulso a la ampliación de la oferta cultural en los territorios. | AV2: Fortalecer la programación cultural en espacios públicos, espacios alternativos y otros espacios culturales. | AW2: Incrementar en 25% la oferta cultural realizada en los municipios. | AX2: Taller | AY2: Mediación | BC2: 0 | BF2: TRUE | BG2: Especie | BL2: Convenio de colaboración entre la DGMAE y la Secretaría del Nuevo Comienzo | BM2: Sí | BN2: Acompañamiento Técnico | BP2: Abierta | BR2: =VLOOKUP(BQ2, Cat_Indicadores!B:C, 2, FALSE) -> #N/A
A3: ACT00032 | B3: SC-260604-160740 | C3: 46177.672 | D3: 94 | E3: PB3572 | F3: Gestión de programas de exposiciones, actividades formativas y académicas en los Museos de la Secretaría de Cultura y actividades extramuros | G3: Creación de actividades para poblaciones especificas como mujeres, niños y niñas, adultos mayores y discapacidad en los Museos adscritos a la Secretaria de Cultura | H3: SUBSECRETARÍA DE DESARROLLO Y PROMOCIÓN ARTÍSTICA Y CULTURAL | I3: DIRECCIÓN GENERAL DE MUSEOS, ARTES VISUALES Y EXPOSICIONES | J3: Número de Actividades realizadas | K3: 12 | L3: Cultural | M3: Juguetes tipicos en estampa alternativa | N3: Fomento del sentido crítico sobre la importancia de las artes visuales en el desarrollo cognitivo, social, humano y artístico. | O3: Única | P3: 46129 | Q3: 46129 | R3: 1 | S3: Cultura comunitaria | T3: Procesos de memoria | U3: Taller | V3: Ninguna | W3: Presencial | X3: Espacio Público | Z3: Centro Nuevo Comienzo Nuevo Amanecer | AB3: FALSE | AD3: FALSE | AF3: FALSE | AH3: Sin costo | AL3: ccardonav@guanajuato.gob.mx | AM3: Arraigo y empoderamiento cultural de comunidades. | AN3: 2 Igualdad | AO3: 2.2 Fortalecer cohesión social | AP3: 2.2 Fortalecer cohesión social | AQ3: 2.2.3.2 Promover la participación de grupos prioritarios en actividades culturales | AR3: Inclusión | AS3: NNA (Niñas, Niños y Adolescentes) | AT3: Fortalecimiento de la participación ciudadana y la mediación cultural | AU3: Impulso a la ampliación de la oferta cultural en los territorios. | AV3: Fortalecer la programación cultural en espacios públicos, espacios alternativos y otros espacios culturales. | AW3: Incrementar en 25% la oferta cultural realizada en los municipios. | AX3: Taller | AY3: Mediación | BC3: 0 | BF3: TRUE | BG3: Especie | BL3: Convenio de colaboración entre la DGMAVE y la Secretaría del Nuevo Comienzo | BM3: Sí | BN3: Acompañamiento Técnico | BP3: Abierta | BR3: =VLOOKUP(BQ3, Cat_Indicadores!B:C, 2, FALSE) -> #N/A
A4: ACT00033 | B4: SC-260605-100441 | C4: 46178.42 | D4: 94 | E4: PB3572 | F4: Gestión de programas de exposiciones, actividades formativas y académicas en los Museos de la Secretaría de Cultura y actividades extramuros | G4: Creación de actividades para poblaciones especificas como mujeres, niños y niñas, adultos mayores y discapacidad en los Museos adscritos a la Secretaria de Cultura | H4: SUBSECRETARÍA DE DESARROLLO Y PROMOCIÓN ARTÍSTICA Y CULTURAL | I4: DIRECCIÓN GENERAL DE MUSEOS, ARTES VISUALES Y EXPOSICIONES | J4: Número de Actividades realizadas | K4: 12 | L4: Cultural | M4: Derechos de los niños y niñas | N4: Fomento del sentido crítico sobre la importancia de las artes visuales en el desarrollo cognitivo, social, humano y artístico. | O4: Única | P4: 46127 | Q4: 46127 | R4: 1 | S4: Cultura comunitaria | T4: Mediación cultural | U4: Taller | V4: Ninguna | W4: Presencial | X4: Espacio Público | Z4: Escuela Primaria Vespertina “Francisco Javier Mina” | AB4: FALSE | AD4: FALSE | AF4: FALSE | AH4: Sin costo | AL4: ccardonav@guanajuato.gob.mx | AM4: Arraigo y empoderamiento cultural de comunidades. | AN4: 2 Igualdad | AO4: 2.2 Fortalecer cohesión social | AP4: 2.2 Fortalecer cohesión social | AQ4: 2.2.3.2 Promover la participación de grupos prioritarios en actividades culturales | AR4: Inclusión | AS4: NNA (Niñas, Niños y Adolescentes) | AT4: Fortalecimiento de la participación ciudadana y la mediación cultural | AU4: Impulso a la ampliación de la oferta cultural en los territorios. | AV4: Fortalecer la programación cultural en espacios públicos, espacios alternativos y otros espacios culturales. | AW4: Incrementar en 25% la oferta cultural realizada en los municipios. | AX4: Taller | AY4: Mediación | BC4: 0 | BF4: TRUE | BG4: Especie | BH4: 0 | BL4: Convenio de colaboración entre la DGMAVE y la Secretaría del Nuevo Comienzo | BM4: Sí | BN4: Acompañamiento Técnico | BP4: Abierta | BR4: =VLOOKUP(BQ4, Cat_Indicadores!B:C, 2, FALSE) -> #N/A
A5: ACT00034 | B5: SC-260605-103419 | C5: 46178.44 | D5: 94 | E5: PB3572 | F5: Gestión de programas de exposiciones, actividades formativas y académicas en los Museos de la Secretaría de Cultura y actividades extramuros | G5: Creación de actividades para poblaciones especificas como mujeres, niños y niñas, adultos mayores y discapacidad en los Museos adscritos a la Secretaria de Cultura | H5: SUBSECRETARÍA DE DESARROLLO Y PROMOCIÓN ARTÍSTICA Y CULTURAL | I5: DIRECCIÓN GENERAL DE MUSEOS, ARTES VISUALES Y EXPOSICIONES | J5: Número de Actividades realizadas | K5: 12 | L5: Cultural | M5: Acoso Escolar | N5: Incentivar y fomentar un sentido crítico sobre la importancia de los derechos de los niños, niñas y adolescentes, en el desarrollo cognitivo, social, humano y artístico en la Escuela Primaria Vespertina Francisco Javier Mina, a través del programa “El Museo a la vuelta de tu casa”. | O5: Única | P5: 46134 | Q5: 46134 | R5: 1 | S5: Cultura comunitaria | T5: Mediación cultural | U5: Taller | V5: Ninguna | W5: Presencial | X5: Espacio Público | Z5: Escuela Primaria Vespertina “Francisco Javier Mina” | AB5: FALSE | AD5: FALSE | AF5: FALSE | AH5: Sin costo | AL5: ccardonav@guanajuato.gob.mx | AM5: Arraigo y empoderamiento cultural de comunidades. | AN5: 2 Igualdad | AO5: 2.2 Fortalecer cohesión social | AP5: 2.2 Fortalecer cohesión social | AQ5: 2.2.3.2 Promover la participación de grupos prioritarios en actividades culturales | AR5: Inclusión | AS5: NNA (Niñas, Niños y Adolescentes) | AT5: Fortalecimiento de la participación ciudadana y la mediación cultural | AU5: Impulso a la ampliación de la oferta cultural en los territorios. | AV5: Fortalecer la programación cultural en espacios públicos, espacios alternativos y otros espacios culturales. | AW5: Incrementar en 25% la oferta cultural realizada en los municipios. | AX5: Taller | AY5: Mediación | BC5: 0 | BF5: TRUE | BG5: Especie | BL5: Convenio de colaboración entre la DGMAVE y la Secretaría del Nuevo Comienzo | BM5: Sí | BN5: Acompañamiento Técnico | BP5: Abierta | BR5: =VLOOKUP(BQ5, Cat_Indicadores!B:C, 2, FALSE) -> #N/A
A6: ACT00035 | B6: SC-260605-110629 | C6: 46178.463 | D6: 94 | E6: PB3572 | F6: Gestión de programas de exposiciones, actividades formativas y académicas en los Museos de la Secretaría de Cultura y actividades extramuros | G6: Creación de actividades para poblaciones especificas como mujeres, niños y niñas, adultos mayores y discapacidad en los Museos adscritos a la Secretaria de Cultura | H6: SUBSECRETARÍA DE DESARROLLO Y PROMOCIÓN ARTÍSTICA Y CULTURAL | I6: DIRECCIÓN GENERAL DE MUSEOS, ARTES VISUALES Y EXPOSICIONES | J6: Número de Actividades realizadas | K6: 12 | L6: Cultural | M6: Sana Convivencia | N6: Incentivar y fomentar un sentido crítico sobre la importancia de los derechos de los niños, niñas y adolescentes, en el desarrollo cognitivo, social, humano y artístico en la Escuela Primaria Vespertina Francisco Javier Mina, a través del programa “El Museo a la vuelta de tu casa”. | O6: Única | P6: 46141 | Q6: 46141 | R6: 1 | S6: Cultura comunitaria | T6: Mediación cultural | U6: Taller | V6: Ninguna | W6: Presencial | X6: Espacio Público | Z6: Escuela Primaria Vespertina “Francisco Javier Mina” | AB6: FALSE | AD6: FALSE | AF6: FALSE | AH6: Sin costo | AL6: ccardonav@guanajuato.gob.mx | AM6: Arraigo y empoderamiento cultural de comunidades. | AN6: 2 Igualdad | AO6: 2.2 Fortalecer cohesión social | AP6: 2.2 Fortalecer cohesión social | AQ6: 2.2.3.2 Promover la participación de grupos prioritarios en actividades culturales | AR6: Inclusión | AS6: NNA (Niñas, Niños y Adolescentes) | AT6: Fortalecimiento de la participación ciudadana y la mediación cultural | AU6: Impulso a la ampliación de la oferta cultural en los territorios. | AV6: Fortalecer la programación cultural en espacios públicos, espacios alternativos y otros espacios culturales. | AW6: Incrementar en 25% la oferta cultural realizada en los municipios. | AX6: Taller | AY6: Mediación | BC6: 0 | BF6: TRUE | BG6: Especie | BH6: 0 | BL6: Convenio de colaboración entre la DGMAVE y la Secretaría del Nuevo Comienzo | BM6: Sí | BN6: Acompañamiento Técnico | BP6: Abierta | BR6: =VLOOKUP(BQ6, Cat_Indicadores!B:C, 2, FALSE) -> #N/A
A7: ACT00036 | B7: SC-260610-105550 | C7: 46183.455 | D7: 94 | E7: PB3572 | F7: Gestión de programas de exposiciones, actividades formativas y académicas en los Museos de la Secretaría de Cultura y actividades extramuros | G7: Creación de actividades para poblaciones especificas como mujeres, niños y niñas, adultos mayores y discapacidad en los Museos adscritos a la Secretaria de Cultura | H7: SUBSECRETARÍA DE DESARROLLO Y PROMOCIÓN ARTÍSTICA Y CULTURAL | I7: DIRECCIÓN GENERAL DE MUSEOS, ARTES VISUALES Y EXPOSICIONES | J7: Número de Actividades realizadas | K7: 12 | L7: Cultural | M7: Tarjeta Española para Mamá | N7: Incentivar y fomentar un sentido crítico sobre la importancia de los derechos de los niños, niñas y adolescentes, en el desarrollo cognitivo, social, humano y artístico en la Escuela Primaria Vespertina Francisco Javier Mina, a través del programa “El Museo a la vuelta de tu casa”. | O7: Única | P7: 46150 | Q7: 46150 | R7: 1 | S7: Cultura comunitaria | T7: Mediación cultural | U7: Taller | V7: Ninguna | W7: Presencial | X7: Espacio Público | Z7: Centro Nuevo Comienzo Nuevo Amanecer | AB7: FALSE | AD7: FALSE | AF7: FALSE | AH7: Sin costo | AL7: ccardonav@guanajuato.gob.mx | AM7: Arraigo y empoderamiento cultural de comunidades. | AN7: 2 Igualdad | AO7: 2.2 Fortalecer cohesión social | AP7: 2.2 Fortalecer cohesión social | AQ7: 2.2.3.2 Promover la participación de grupos prioritarios en actividades culturales | AR7: Inclusión | AS7: NNA (Niñas, Niños y Adolescentes) | AT7: Fortalecimiento de la participación ciudadana y la mediación cultural | AU7: Impulso a la ampliación de la oferta cultural en los territorios. | AV7: Fortalecer la programación cultural en espacios públicos, espacios alternativos y otros espacios culturales. | AW7: Incrementar en 25% la oferta cultural realizada en los municipios. | AX7: Taller | AY7: Mediación | BC7: 0 | BF7: TRUE | BG7: Especie | BL7: Convenio de colaboración entre la DGMAVE y la Secretaría del Nuevo Comienzo | BM7: Sí | BN7: Acompañamiento Técnico | BP7: Abierta | BR7: =VLOOKUP(BQ7, Cat_Indicadores!B:C, 2, FALSE) -> #N/A
A8: ACT00037 | B8: SC-260610-114106 | C8: 46183.487 | D8: 94 | E8: PB3572 | F8: Gestión de programas de exposiciones, actividades formativas y académicas en los Museos de la Secretaría de Cultura y actividades extramuros | G8: Creación de actividades para poblaciones especificas como mujeres, niños y niñas, adultos mayores y discapacidad en los Museos adscritos a la Secretaria de Cultura | H8: SUBSECRETARÍA DE DESARROLLO Y PROMOCIÓN ARTÍSTICA Y CULTURAL | I8: DIRECCIÓN GENERAL DE MUSEOS, ARTES VISUALES Y EXPOSICIONES | J8: Número de Actividades realizadas | K8: 12 | L8: Cultural | M8: Tarjeta Española para Mamá | N8: Incentivar y fomentar un sentido crítico sobre la importancia de los derechos de los niños, niñas y adolescentes, en el desarrollo cognitivo, social, humano y artístico en la Escuela Primaria Vespertina Francisco Javier Mina, a través del programa “El Museo a la vuelta de tu casa”. | O8: Única | P8: 46186 | Q8: 46186 | R8: 1 | S8: Cultura comunitaria | T8: Mediación cultural | U8: Taller | V8: Ninguna | W8: Presencial | X8: Espacio Público | Z8: Centro Nuevo Comienzo Balcones de las Joyas | AB8: FALSE | AD8: FALSE | AF8: FALSE | AH8: Sin costo | AL8: ccardonav@guanajuato.gob.mx | AM8: Arraigo y empoderamiento cultural de comunidades. | AN8: 2 Igualdad | AO8: 2.2 Fortalecer cohesión social | AP8: 2.2 Fortalecer cohesión social | AQ8: 2.2.3.2 Promover la participación de grupos prioritarios en actividades culturales | AR8: Inclusión | AS8: Ninguno (Población General) | AT8: Fortalecimiento de la participación ciudadana y la mediación cultural | AU8: Impulso a la ampliación de la oferta cultural en los territorios. | AV8: Fortalecer la programación cultural en espacios públicos, espacios alternativos y otros espacios culturales. | AW8: Incrementar en 25% la oferta cultural realizada en los municipios. | AX8: Taller | AY8: Mediación | BC8: 0 | BF8: TRUE | BG8: Especie | BL8: Convenio de colaboración entre la DGMAVE y la Secretaría del Nuevo Comienzo | BM8: Sí | BN8: Acompañamiento Técnico | BP8: Abierta | BR8: =VLOOKUP(BQ8, Cat_Indicadores!B:C, 2, FALSE) -> #N/A
A9: ACT00038 | B9: SC-260611-102905 | C9: 46184.437 | D9: 92 | E9: PB3572 | F9: Gestión de programas de exposiciones, actividades formativas y académicas en los Museos de la Secretaría de Cultura y actividades extramuros | G9: Creación y participación en actividades formativas y académicas de los museos adscritos a la Secretaria de Cultura | H9: SUBSECRETARÍA DE DESARROLLO Y PROMOCIÓN ARTÍSTICA Y CULTURAL | I9: DIRECCIÓN GENERAL DE MUSEOS, ARTES VISUALES Y EXPOSICIONES | J9: Número de Actividades realizadas | K9: 800 | L9: Cultural | M9: 1EEM "Diálogos de Museos y política pública" | N9: El I Encuentro Estatal de Museos de Guanajuato es un espacio de reunión y diálogo que convoca a representantes de museos, gestores culturales y profesionales del sector de los 46 municipios del estado, con el propósito de compartir experiencias, reflexionar sobre los retos actuales y visibilizar la diversidad del patrimonio cultural guanajuatense. Este encuentro impulsa la colaboración intermunicipal y el trabajo en red como ejes para fortalecer el papel social, educativo y cultural de los museos. | O9: Única | P9: 46169 | Q9: 46169 | R9: 1 | S9: Cultura comunitaria | T9: Gestión cultural | U9: Encuentro cultural | V9: Evaluación | W9: Presencial | X9: Espacio Privado | Z9: Hotel Hotsson | AB9: FALSE | AD9: TRUE | AE9: 1 | AF9: FALSE | AH9: Sin costo | AL9: ccardonav@guanajuato.gob.mx | AM9: Formación de formadores artísticos y culturales: Cursos y talleres de capacitación artística para docentes. Encuentros entre formadores de casas de cultura. Plataforma de colaboración entre instituciones culturales. | AN9: 2 Igualdad | AO9: 2.4 Reducir brechas de desigualdad | AP9: 2.4.3 Descentralización de la oferta cultural | AQ9: 2.4.3.3 Incidir en el involucramiento de las personas con el ecosistema cultural | AR9: Cooperación | AT9: Fortalecimiento de la participación ciudadana y la mediación cultural | AU9: Fortalecimiento del diálogo, la mediación y las capacidades de las redes comunitarias. | AV9: Fortalecer las capacidades de autoridades locales y estatales | AW9: Incrementar en 25% la oferta cultural realizada en los municipios. | AX9: Asesoría especializada | AY9: Formación | AZ9: Formación | BC9: 0 | BF9: TRUE | BG9: Asesoría | BL9: Contrato de Prestación de Servicios | BM9: Sí | BN9: Acompañamiento Técnico | BP9: Abierta | BR9: =VLOOKUP(BQ9, Cat_Indicadores!B:C, 2, FALSE) -> #N/A
A10: ACT00039 | B10: SC-260611-111846 | C10: 46184.471 | D10: 92 | E10: PB3572 | F10: Gestión de programas de exposiciones, actividades formativas y académicas en los Museos de la Secretaría de Cultura y actividades extramuros | G10: Creación y participación en actividades formativas y académicas de los museos adscritos a la Secretaria de Cultura | H10: SUBSECRETARÍA DE DESARROLLO Y PROMOCIÓN ARTÍSTICA Y CULTURAL | I10: DIRECCIÓN GENERAL DE MUSEOS, ARTES VISUALES Y EXPOSICIONES | J10: Número de Actividades realizadas | K10: 800 | L10: Cultural | M10: 1EEM "Vámonos conociendo" | N10: Sesión de taller a cargo del Laboratorio Creativo Luciérnaga | O10: Única | P10: 46169 | Q10: 46169 | R10: 1 | S10: Cultura comunitaria | T10: Mediación cultural | U10: Taller | V10: Evaluación | W10: Presencial | X10: Espacio Privado | Z10: Hotel Hotsson | AB10: FALSE | AD10: TRUE | AE10: 1 | AF10: FALSE | AH10: Sin costo | AL10: ccardonav@guanajuato.gob.mx | AM10: Formación de formadores artísticos y culturales: Cursos y talleres de capacitación artística para docentes. Encuentros entre formadores de casas de cultura. Plataforma de colaboración entre instituciones culturales. | AN10: 2 Igualdad | AO10: 2.4 Reducir brechas de desigualdad | AP10: 2.4.3 Descentralización de la oferta cultural | AQ10: 2.4.3.3 Incidir en el involucramiento de las personas con el ecosistema cultural | AR10: Cooperación | AT10: Fortalecimiento de la participación ciudadana y la mediación cultural | AU10: Fortalecimiento del diálogo, la mediación y las capacidades de las redes comunitarias. | AV10: Fortalecer las capacidades de autoridades locales y estatales | AW10: Incrementar en 25% la oferta cultural realizada en los municipios. | AX10: Taller | AY10: Mediación | BC10: 0 | BF10: TRUE | BG10: Asesoría | BL10: Contrato de Prestación de Servicios | BM10: Sí | BN10: Acompañamiento Técnico | BP10: Abierta | BR10: =VLOOKUP(BQ10, Cat_Indicadores!B:C, 2, FALSE) -> #N/A
A11: ACT00040 | B11: SC-260611-140443 | C11: 46184.587 | D11: 92 | E11: PB3572 | F11: Gestión de programas de exposiciones, actividades formativas y académicas en los Museos de la Secretaría de Cultura y actividades extramuros | G11: Creación y participación en actividades formativas y académicas de los museos adscritos a la Secretaria de Cultura | H11: SUBSECRETARÍA DE DESARROLLO Y PROMOCIÓN ARTÍSTICA Y CULTURAL | I11: DIRECCIÓN GENERAL DE MUSEOS, ARTES VISUALES Y EXPOSICIONES | J11: Número de Actividades realizadas | K11: 800 | L11: Cultural | M11: 1 EEM "Conferencia comunidades y museos" | N11: En conversación Álvaro Octavio Lara Huerta, Subsecretario deDesarrollo y Promoción Artística y Cultural de Guanajuato | O11: Única | P11: 46170 | Q11: 46170 | R11: 1 | S11: Cultura comunitaria | T11: Gestión cultural | U11: Conferencia | V11: Ninguna | W11: Presencial | X11: Espacio Privado | Z11: Hotel Hotsson | AB11: FALSE | AD11: TRUE | AE11: 1 | AF11: FALSE | AH11: Sin costo | AL11: ccardonav@guanajuato.gob.mx | AM11: Formación de formadores artísticos y culturales: Cursos y talleres de capacitación artística para docentes. Encuentros entre formadores de casas de cultura. Plataforma de colaboración entre instituciones culturales. | AN11: 2 Igualdad | AO11: 2.4 Reducir brechas de desigualdad | AP11: 2.4.3 Descentralización de la oferta cultural | AQ11: 2.4.3.3 Incidir en el involucramiento de las personas con el ecosistema cultural | AR11: Cooperación | AT11: Fortalecimiento de la participación ciudadana y la mediación cultural | AU11: Fortalecimiento del diálogo, la mediación y las capacidades de las redes comunitarias. | AV11: Fortalecer las capacidades de autoridades locales y estatales | AW11: Incrementar en 25% la oferta cultural realizada en los municipios. | AX11: Asesoría especializada | AY11: Formación | BC11: 0 | BF11: TRUE | BG11: Asesoría | BL11: Contrato de Prestacion de Servicios | BM11: Sí | BN11: Acompañamiento Técnico | BP11: Abierta | BR11: =VLOOKUP(BQ11, Cat_Indicadores!B:C, 2, FALSE) -> #N/A
A12: ACT00041 | B12: SC-260611-143318 | C12: 46184.606 | D12: 92 | E12: PB3572 | F12: Gestión de programas de exposiciones, actividades formativas y académicas en los Museos de la Secretaría de Cultura y actividades extramuros | G12: Creación y participación en actividades formativas y académicas de los museos adscritos a la Secretaria de Cultura | H12: SUBSECRETARÍA DE DESARROLLO Y PROMOCIÓN ARTÍSTICA Y CULTURAL | I12: DIRECCIÓN GENERAL DE MUSEOS, ARTES VISUALES Y EXPOSICIONES | J12: Número de Actividades realizadas | K12: 800 | L12: Cultural | M12: 1 EEM "Conociendo los museos de Guanajuato. Sesion de PechaKucha" | N12: Presentación de los museos con la dinámica PechaKucha. | O12: Única | P12: 46170 | Q12: 46170 | R12: 1 | S12: Cultura comunitaria | T12: Gestión cultural | U12: Vinculación | V12: Ninguna | W12: Presencial | X12: Espacio Privado | Z12: Hotel Hotsson | AB12: FALSE | AD12: FALSE | AF12: FALSE | AH12: Sin costo | AL12: ccardonav@guanajuato.gob.mx | AM12: Formación de formadores artísticos y culturales: Cursos y talleres de capacitación artística para docentes. Encuentros entre formadores de casas de cultura. Plataforma de colaboración entre instituciones culturales. | AN12: 2 Igualdad | AO12: 2.4 Reducir brechas de desigualdad | AP12: 2.4.3 Descentralización de la oferta cultural | AQ12: 2.4.3.3 Incidir en el involucramiento de las personas con el ecosistema cultural | AR12: Inclusión | AT12: Fortalecimiento de la participación ciudadana y la mediación cultural | AU12: Fortalecimiento del diálogo, la mediación y las capacidades de las redes comunitarias. | AV12: Fortalecer las capacidades de autoridades locales y estatales | AW12: Incrementar en 25% la oferta cultural realizada en los municipios. | AX12: Encuentro cultural | AY12: Circulación / Exhibición | BC12: 0 | BF12: TRUE | BG12: Asesoría | BM12: No | BN12: Acompañamiento Técnico | BP12: Abierta | BR12: =VLOOKUP(BQ12, Cat_Indicadores!B:C, 2, FALSE) -> #N/A
A13: ACT00042 | B13: SC-260611-154851 | C13: 46184.659 | D13: 92 | E13: PB3572 | F13: Gestión de programas de exposiciones, actividades formativas y académicas en los Museos de la Secretaría de Cultura y actividades extramuros | G13: Creación y participación en actividades formativas y académicas de los museos adscritos a la Secretaria de Cultura | H13: SUBSECRETARÍA DE DESARROLLO Y PROMOCIÓN ARTÍSTICA Y CULTURAL | I13: DIRECCIÓN GENERAL DE MUSEOS, ARTES VISUALES Y EXPOSICIONES | J13: Número de Actividades realizadas | K13: 800 | L13: Cultural | M13: 1 EEM " Conferencia el diseño de exhibiciones" | N13: La conferencia se centró en la importancia de mirar a los públicos. Imparte Gabriel Horner en conversación con Óscar Ascencio. | O13: Única | P13: 46170 | Q13: 46170 | R13: 1 | S13: Cultura comunitaria | T13: Gestión cultural | U13: Conferencia | V13: Ninguna | W13: Presencial | X13: Espacio Privado | Z13: Hotel Hotsson | AB13: FALSE | AD13: TRUE | AE13: 1 | AF13: FALSE | AH13: Sin costo | AL13: ccardonav@guanajuato.gob.mx | AM13: Formación de formadores artísticos y culturales: Cursos y talleres de capacitación artística para docentes. Encuentros entre formadores de casas de cultura. Plataforma de colaboración entre instituciones culturales. | AN13: 2 Igualdad | AO13: 2.4 Reducir brechas de desigualdad | AP13: 2.4.3 Descentralización de la oferta cultural | AQ13: 2.4.3.3 Incidir en el involucramiento de las personas con el ecosistema cultural | AR13: Cooperación | AT13: Fortalecimiento de la participación ciudadana y la mediación cultural | AU13: Fortalecimiento del diálogo, la mediación y las capacidades de las redes comunitarias. | AV13: Fortalecer las capacidades de autoridades locales y estatales | AW13: Incrementar en 25% la oferta cultural realizada en los municipios. | AX13: Asesoría especializada | AY13: Mediación | BC13: 0 | BF13: TRUE | BG13: Asesoría | BL13: Contrato de Prestacion de Servicios | BM13: Sí | BP13: Abierta | BR13: =VLOOKUP(BQ13, Cat_Indicadores!B:C, 2, FALSE) -> #N/A
A14: ACT00043 | B14: SC-260612-103524 | C14: 46185.441 | D14: 92 | E14: PB3572 | F14: Gestión de programas de exposiciones, actividades formativas y académicas en los Museos de la Secretaría de Cultura y actividades extramuros | G14: Creación y participación en actividades formativas y académicas de los museos adscritos a la Secretaria de Cultura | H14: SUBSECRETARÍA DE DESARROLLO Y PROMOCIÓN ARTÍSTICA Y CULTURAL | I14: DIRECCIÓN GENERAL DE MUSEOS, ARTES VISUALES Y EXPOSICIONES | J14: Número de Actividades realizadas | K14: 800 | L14: Cultural | M14: 1 EEM " ¿Qué somos Y qué tenemos en común? | N14: Sesión de taller a cargo del Laboratorio Creativo Luciérnaga | O14: Única | P14: 46170 | Q14: 46170 | R14: 1 | S14: Cultura comunitaria | T14: Mediación cultural | U14: Taller | V14: Evaluación | W14: Presencial | X14: Espacio Privado | Z14: Hotel Hotsson | AB14: FALSE | AD14: TRUE | AE14: 1 | AF14: FALSE | AH14: Sin costo | AL14: ccardonav@guanajuato.gob.mx | AM14: Formación de formadores artísticos y culturales: Cursos y talleres de capacitación artística para docentes. Encuentros entre formadores de casas de cultura. Plataforma de colaboración entre instituciones culturales. | AN14: 2 Igualdad | AO14: 2.4 Reducir brechas de desigualdad | AP14: 2.4.3 Descentralización de la oferta cultural | AQ14: 2.4.3.3 Incidir en el involucramiento de las personas con el ecosistema cultural | AR14: Cooperación | AT14: Fortalecimiento de la participación ciudadana y la mediación cultural | AU14: Fortalecimiento del diálogo, la mediación y las capacidades de las redes comunitarias. | AV14: Fortalecer las capacidades de autoridades locales y estatales | AW14: Incrementar en 25% la oferta cultural realizada en los municipios. | AX14: Taller | AY14: Mediación | BC14: 0 | BF14: TRUE | BG14: Asesoría | BH14: 23200 | BL14: Contrato de Prestación de Servicios | BM14: Sí | BN14: Acompañamiento Técnico | BP14: Abierta | BR14: =VLOOKUP(BQ14, Cat_Indicadores!B:C, 2, FALSE) -> #N/A
A15: ACT00044 | B15: SC-260612-110853 | C15: 46185.465 | D15: 92 | E15: PB3572 | F15: Gestión de programas de exposiciones, actividades formativas y académicas en los Museos de la Secretaría de Cultura y actividades extramuros | G15: Creación y participación en actividades formativas y académicas de los museos adscritos a la Secretaria de Cultura | H15: SUBSECRETARÍA DE DESARROLLO Y PROMOCIÓN ARTÍSTICA Y CULTURAL | I15: DIRECCIÓN GENERAL DE MUSEOS, ARTES VISUALES Y EXPOSICIONES | J15: Número de Actividades realizadas | K15: 800 | L15: Cultural | M15: 1 EEM " Conferencia Las redes sociales, un campo abierto a la comunicación e los emprendimientos culturales" | N15: La conferencia la impartió Melania Chavarría. | O15: Única | P15: 46171 | Q15: 46171 | R15: 1 | S15: Cultura comunitaria | T15: Gestión cultural | U15: Conferencia | V15: Ninguna | W15: Presencial | X15: Espacio Privado | Z15: Hotel Hotsson | AB15: FALSE | AD15: FALSE | AF15: FALSE | AH15: Sin costo | AL15: ccardonav@guanajuato.gob.mx | AM15: Formación de formadores artísticos y culturales: Cursos y talleres de capacitación artística para docentes. Encuentros entre formadores de casas de cultura. Plataforma de colaboración entre instituciones culturales. | AN15: 2 Igualdad | AO15: 2.4 Reducir brechas de desigualdad | AP15: 2.4.3 Descentralización de la oferta cultural | AQ15: 2.4.3.3 Incidir en el involucramiento de las personas con el ecosistema cultural | AR15: Cooperación | AT15: Fortalecimiento de la participación ciudadana y la mediación cultural | AU15: Fortalecimiento del diálogo, la mediación y las capacidades de las redes comunitarias. | AV15: Fortalecer las capacidades de autoridades locales y estatales | AW15: Incrementar en 25% la oferta cultural realizada en los municipios. | AX15: Asesoría especializada | AY15: Formación | AZ15: Formación | BC15: 0 | BF15: TRUE | BG15: Asesoría | BM15: No | BP15: Abierta | BR15: =VLOOKUP(BQ15, Cat_Indicadores!B:C, 2, FALSE) -> #N/A
A16: ACT00045 | B16: SC-260612-113026 | C16: 46185.479 | D16: 92 | E16: PB3572 | F16: Gestión de programas de exposiciones, actividades formativas y académicas en los Museos de la Secretaría de Cultura y actividades extramuros | G16: Creación y participación en actividades formativas y académicas de los museos adscritos a la Secretaria de Cultura | H16: SUBSECRETARÍA DE DESARROLLO Y PROMOCIÓN ARTÍSTICA Y CULTURAL | I16: DIRECCIÓN GENERAL DE MUSEOS, ARTES VISUALES Y EXPOSICIONES | J16: Número de Actividades realizadas | K16: 800 | L16: Cultural | M16: 1 EEM " Conversatorio los retos de la comunicación y la mediación de los museos" | N16: Participan Brenda Galvan, Museo de las identidades leonesas/ICL, Rafael Soldara, Museo de Celaya de Historia Regional, Míriam de los Ángeles | O16: Única | P16: 46171 | Q16: 46171 | R16: 1 | S16: Cultura comunitaria | T16: Mediación cultural | U16: Conversatorio | V16: Ninguna | W16: Presencial | X16: Espacio Privado | Z16: Hotel Hotsson | AB16: FALSE | AD16: FALSE | AF16: FALSE | AH16: Sin costo | AL16: ccardonav@guanajuato.gob.mx | AM16: Formación de formadores artísticos y culturales: Cursos y talleres de capacitación artística para docentes. Encuentros entre formadores de casas de cultura. Plataforma de colaboración entre instituciones culturales. | AN16: 2 Igualdad | AO16: 2.4 Reducir brechas de desigualdad | AP16: 2.4.3 Descentralización de la oferta cultural | AQ16: 2.4.3.3 Incidir en el involucramiento de las personas con el ecosistema cultural | AR16: Inclusión | AS16: Ninguno (Población General) | AT16: Fortalecimiento de la participación ciudadana y la mediación cultural | AU16: Fortalecimiento del diálogo, la mediación y las capacidades de las redes comunitarias. | AV16: Fortalecer las capacidades de autoridades locales y estatales | AW16: Incrementar en 25% la oferta cultural realizada en los municipios. | AX16: Asesoría especializada | AY16: Mediación | BC16: 5 | BD16: Nuevo | BF16: TRUE | BG16: Asesoría | BM16: No | BP16: Abierta | BR16: =VLOOKUP(BQ16, Cat_Indicadores!B:C, 2, FALSE) -> #N/A
A17: ACT00046 | B17: SC-260612-122622 | C17: 46185.518 | D17: 92 | E17: PB3572 | F17: Gestión de programas de exposiciones, actividades formativas y académicas en los Museos de la Secretaría de Cultura y actividades extramuros | G17: Creación y participación en actividades formativas y académicas de los museos adscritos a la Secretaria de Cultura | H17: SUBSECRETARÍA DE DESARROLLO Y PROMOCIÓN ARTÍSTICA Y CULTURAL | I17: DIRECCIÓN GENERAL DE MUSEOS, ARTES VISUALES Y EXPOSICIONES | J17: Número de Actividades realizadas | K17: 800 | L17: Cultural | M17: 1 EEM "Conferencia reflexiones sobre la educación en museos" | N17: Conferencia Impartida por la Mtr. Ariadna Vargas Trejo | O17: Única | P17: 46171 | Q17: 46171 | R17: 1 | S17: Cultura comunitaria | T17: Gestión cultural | U17: Conferencia | V17: Ninguna | W17: Presencial | X17: Espacio Privado | Z17: Hotel Hotsson | AB17: FALSE | AD17: TRUE | AE17: 1 | AF17: FALSE | AH17: Sin costo | AL17: ccardonav@guanajuato.gob.mx | AM17: Formación de formadores artísticos y culturales: Cursos y talleres de capacitación artística para docentes. Encuentros entre formadores de casas de cultura. Plataforma de colaboración entre instituciones culturales. | AN17: 2 Igualdad | AO17: 2.4 Reducir brechas de desigualdad | AP17: 2.4.3 Descentralización de la oferta cultural | AQ17: 2.4.3.3 Incidir en el involucramiento de las personas con el ecosistema cultural | AR17: Cooperación | AT17: Fortalecimiento de la participación ciudadana y la mediación cultural | AU17: Fortalecimiento del diálogo, la mediación y las capacidades de las redes comunitarias. | AV17: Fortalecer las capacidades de autoridades locales y estatales | AW17: Incrementar en 25% la oferta cultural realizada en los municipios. | AX17: Asesoría especializada | AY17: Formación | AZ17: Formación | BC17: 0 | BF17: TRUE | BG17: Asesoría | BH17: 7656.25 | BL17: Contrato de Prestacion de Servicios | BM17: Sí | BN17: Acompañamiento Técnico | BP17: Abierta | BR17: =VLOOKUP(BQ17, Cat_Indicadores!B:C, 2, FALSE) -> #N/A
A18: ACT00017 | B18: SC-260615-100445 | C18: 46188.42 | D18: 92 | E18: PB3572 | F18: Gestión de programas de exposiciones, actividades formativas y académicas en los Museos de la Secretaría de Cultura y actividades extramuros | G18: Creación y participación en actividades formativas y académicas de los museos adscritos a la Secretaria de Cultura | H18: SUBSECRETARÍA DE DESARROLLO Y PROMOCIÓN ARTÍSTICA Y CULTURAL | I18: DIRECCIÓN GENERAL DE MUSEOS, ARTES VISUALES Y EXPOSICIONES | J18: Número de Actividades realizadas | K18: 800 | L18: Cultural | M18: "Museos para la niñez: Torneo de Rubik " | N18: La Asociación Mundial del Cubo (WCA) te invita a participar o presenciar el Torneo de Rubik. Una competencia en la que chicos y grandes pueden demostrar sus habilidades con este popular juego que ha dado la vuelta por todo el mundo. | O18: Única | P18: 46124 | Q18: 46124 | R18: 1 | S18: Multidisciplinario | T18: Interdisciplinario | U18: Activación cultural comunitaria | V18: Ninguna | W18: Presencial | X18: Espacio a Cargo de la Secretaría | Y18: 8 | AB18: FALSE | AD18: FALSE | AF18: FALSE | AH18: Sin costo | AL18: ccardonav@guanajuato.gob.mx | AM18: Juventudes: Apropiación de espacios públicos: revitalizar espacios subutilizados para actividades comunitarias y culturales, con jóvenes en su diseño y gestión. | AN18: 1 Tranquilidad | AO18: 1.2 Fortalecer prevención del delito | AP18: 1.2.2 Fortalecimiento del tejido social | AQ18: 1.2.3.4 Promover una cultura de paz desde las expresiones artísticas y culturales | AR18: Cooperación | AT18: Protección y dinamización del patrimonio, la memoria y los espacios culturales | AU18: Consolidación de los mecanismos de gobernanza para el uso de los espacios cultuales y zonas patrimoniales. | AV18: Promover mecanismos de gobernanza para el aprovechamiento de espacios patrimoniales del estado de Guanajuato (ferias, festivales, encuentros comunitarios, etc.). | AW18: Incrementar un 30% la participación de grupos, colectivos y comunidades en procesos de memoria, investigación, divulgación y difusión del patrimonio material e inmaterial | AX18: Programación cultural en espacio público | AY18: Formación | BC18: 0 | BF18: FALSE | BL18: N/A | BM18: Sí | BP18: Abierta | BR18: =VLOOKUP(BQ18, Cat_Indicadores!B:C, 2, FALSE) -> #N/A
A19: ACT00018 | B19: SC-260615-103418 | C19: 46188.44 | D19: 92 | E19: PB3572 | F19: Gestión de programas de exposiciones, actividades formativas y académicas en los Museos de la Secretaría de Cultura y actividades extramuros | G19: Creación y participación en actividades formativas y académicas de los museos adscritos a la Secretaria de Cultura | H19: SUBSECRETARÍA DE DESARROLLO Y PROMOCIÓN ARTÍSTICA Y CULTURAL | I19: DIRECCIÓN GENERAL DE MUSEOS, ARTES VISUALES Y EXPOSICIONES | J19: Número de Actividades realizadas | K19: 800 | L19: Artística | M19: Museos para la niñez: Proyectos Kamalio y Orquesta Ensamble Da Capo | N19: Orquesta Ensamble Da Capo está compuesta por alumnos de clases de música Amadeus Mozart, a cargo del maestro Eduardo Véjar. Con instrumentos de cuerda y percusión, son una orquesta que promueve la formación artística a través de la música en infancias y juventudes. | O19: Única | P19: 46130 | Q19: 46130 | R19: 1 | S19: Música | T19: Música tradicional | U19: Muestra artística | V19: Ninguna | W19: Presencial | X19: Espacio a Cargo de la Secretaría | Y19: 8 | AB19: FALSE | AD19: FALSE | AF19: FALSE | AH19: Sin costo | AL19: ccardonav@guanajuato.gob.mx | AM19: Juventudes: Apropiación de espacios públicos: revitalizar espacios subutilizados para actividades comunitarias y culturales, con jóvenes en su diseño y gestión. | AN19: 1 Tranquilidad | AO19: 1.2 Fortalecer prevención del delito | AP19: 1.2.2 Fortalecimiento del tejido social | AQ19: 1.2.3.4 Promover una cultura de paz desde las expresiones artísticas y culturales | AR19: Cooperación | AT19: Fomento a la creación y circulación cultural. | AU19: Impulso a redes colaborativas y plataformas de visibilidad | AV19: Celebrar esquemas de colaboración para facilitar la presencia de artistas locales en ferias, festivales y redes culturales nacionales e internacionales. | AW19: Lograr un incremento anual del 10% en la circulación de obras fuera del territorio estatal. | AX19: Presentación artística | AY19: Formación | BC19: 0 | BF19: FALSE | BL19: N/A | BM19: Sí | BP19: Abierta | BR19: =VLOOKUP(BQ19, Cat_Indicadores!B:C, 2, FALSE) -> #N/A
A20: ACT00019 | B20: SC-260615-104331 | C20: 46188.447 | D20: 92 | E20: PB3572 | F20: Gestión de programas de exposiciones, actividades formativas y académicas en los Museos de la Secretaría de Cultura y actividades extramuros | G20: Creación y participación en actividades formativas y académicas de los museos adscritos a la Secretaria de Cultura | H20: SUBSECRETARÍA DE DESARROLLO Y PROMOCIÓN ARTÍSTICA Y CULTURAL | I20: DIRECCIÓN GENERAL DE MUSEOS, ARTES VISUALES Y EXPOSICIONES | J20: Número de Actividades realizadas | K20: 800 | L20: Cultural | M20: Museos para la niñez: Magic Mind para la niñez. Meditación | N20: Meditación, yoga y aromaterapia en Terraza del Jardín de las esculturas. Imparte: Ana Gabriela Barajas Hernández de Magic Mind. | O20: Única | P20: 46131 | Q20: 46131 | R20: 1 | S20: Multidisciplinario | T20: Interdisciplinario | U20: Taller | V20: Ninguna | W20: Presencial | X20: Espacio a Cargo de la Secretaría | Y20: 8 | AB20: FALSE | AD20: FALSE | AF20: FALSE | AH20: Sin costo | AL20: ccardonav@guanajuato.gob.mx | AM20: Juventudes: Apropiación de espacios públicos: revitalizar espacios subutilizados para actividades comunitarias y culturales, con jóvenes en su diseño y gestión. | AN20: 1 Tranquilidad | AO20: 1.2 Fortalecer prevención del delito | AP20: 1.2.2 Fortalecimiento del tejido social | AQ20: 1.2.3.4 Promover una cultura de paz desde las expresiones artísticas y culturales | AR20: Cooperación | AT20: Sostenibilidad del trabajo cultural y la economía creativa. | AU20: Consolidación de los mecanismos de gobernanza para el uso de los espacios cultuales y zonas patrimoniales. | AV20: Diseñar programas de formación y gestión cultural de base comunitaria. | AW20: Incrementar un 30% la participación de grupos, colectivos y comunidades en procesos de memoria, investigación, divulgación y difusión del patrimonio material e inmaterial | AX20: Taller | AY20: Formación | BC20: 0 | BF20: FALSE | BL20: N/A | BM20: Sí | BP20: Abierta | BR20: =VLOOKUP(BQ20, Cat_Indicadores!B:C, 2, FALSE) -> #N/A
A21: ACT00020 | B21: SC-260615-112323 | C21: 46188.475 | D21: 92 | E21: PB3572 | F21: Gestión de programas de exposiciones, actividades formativas y académicas en los Museos de la Secretaría de Cultura y actividades extramuros | G21: Creación y participación en actividades formativas y académicas de los museos adscritos a la Secretaria de Cultura | H21: SUBSECRETARÍA DE DESARROLLO Y PROMOCIÓN ARTÍSTICA Y CULTURAL | I21: DIRECCIÓN GENERAL DE MUSEOS, ARTES VISUALES Y EXPOSICIONES | J21: Número de Actividades realizadas | K21: 800 | L21: Cultural | M21: Museos para la niñez: Cómo visitar un museo para niños | N21: La Plataforma de Arte emergente del Bajío LANZA te invita a participar en este divertido taller en el que podrás aprender cómo conocer y disfrutar de los museos. | O21: Única | P21: 46131 | Q21: 46131 | R21: 1 | S21: Cultura comunitaria | T21: Mediación cultural | U21: Taller | V21: Ninguna | W21: Presencial | X21: Espacio a Cargo de la Secretaría | Y21: 8 | AB21: FALSE | AD21: FALSE | AF21: FALSE | AH21: Sin costo | AL21: ccardonav@guanajuato.gob.mx | AM21: Juventudes: Apropiación de espacios públicos: revitalizar espacios subutilizados para actividades comunitarias y culturales, con jóvenes en su diseño y gestión. | AN21: 2 Igualdad | AO21: 2.4 Reducir brechas de desigualdad | AP21: 2.4.3 Descentralización de la oferta cultural | AQ21: 2.4.3.1 Impulsar el desarrollo artístico y cultural entre infancias y juventudes | AR21: Cooperación | AT21: Fortalecimiento de la participación ciudadana y la mediación cultural | AU21: Fortalecimiento del diálogo, la mediación y las capacidades de las redes comunitarias. | AV21: Diseñar e impartir talleres de formación en derechos culturales | AW21: Incrementar en 25% la oferta cultural realizada en los municipios. | AX21: Taller | AY21: Formación | BC21: 0 | BF21: FALSE | BL21: N/A | BM21: Sí | BP21: Abierta | BR21: =VLOOKUP(BQ21, Cat_Indicadores!B:C, 2, FALSE) -> #N/A
A22: ACT00021 | B22: SC-260615-113141 | C22: 46188.48 | D22: 92 | E22: PB3572 | F22: Gestión de programas de exposiciones, actividades formativas y académicas en los Museos de la Secretaría de Cultura y actividades extramuros | G22: Creación y participación en actividades formativas y académicas de los museos adscritos a la Secretaria de Cultura | H22: SUBSECRETARÍA DE DESARROLLO Y PROMOCIÓN ARTÍSTICA Y CULTURAL | I22: DIRECCIÓN GENERAL DE MUSEOS, ARTES VISUALES Y EXPOSICIONES | J22: Número de Actividades realizadas | K22: 800 | L22: Artística | M22: Museos para la niñez: Ensamble Sinfónico Oviedo | N22: Déjate sorprender por las maravillosas piezas musicales que las niñas, niños y adolescentes del Instituto Oviedo nos traerán en este mes de las infancias. Acompáñanos en este recital integrado de pequeñas piezas camerísticas y concertantes de los períodos Barroco, Clásico y Romántico; yendo desde Vivaldi y Corelli hasta Busoni. | O22: Única | P22: 46188 | Q22: 46188 | R22: 1 | S22: Música | T22: Orquestas | U22: Muestra artística | V22: Ninguna | W22: Presencial | X22: Espacio a Cargo de la Secretaría | Y22: 8 | AB22: FALSE | AD22: FALSE | AF22: FALSE | AH22: Sin costo | AL22: ccardonav@guanajuato.gob.mx | AM22: Juventudes: Apropiación de espacios públicos: revitalizar espacios subutilizados para actividades comunitarias y culturales, con jóvenes en su diseño y gestión. | AN22: 1 Tranquilidad | AO22: 1.2 Fortalecer prevención del delito | AP22: 1.2.2 Fortalecimiento del tejido social | AQ22: 1.2.3.4 Promover una cultura de paz desde las expresiones artísticas y culturales | AR22: Cooperación | AT22: Fortalecimiento de la participación ciudadana y la mediación cultural | AU22: Fortalecimiento del diálogo, la mediación y las capacidades de las redes comunitarias. | AV22: Diseñar e impartir talleres de formación en derechos culturales | AW22: Incrementar en 25% la oferta cultural realizada en los municipios. | AX22: Presentación artística | AY22: Formación | BC22: 0 | BF22: FALSE | BL22: N/A | BM22: Sí | BP22: Abierta | BR22: =VLOOKUP(BQ22, Cat_Indicadores!B:C, 2, FALSE) -> #N/A
A23: ACT00022 | B23: SC-260615-114225 | C23: 46188.488 | D23: 92 | E23: PB3572 | F23: Gestión de programas de exposiciones, actividades formativas y académicas en los Museos de la Secretaría de Cultura y actividades extramuros | G23: Creación y participación en actividades formativas y académicas de los museos adscritos a la Secretaria de Cultura | H23: SUBSECRETARÍA DE DESARROLLO Y PROMOCIÓN ARTÍSTICA Y CULTURAL | I23: DIRECCIÓN GENERAL DE MUSEOS, ARTES VISUALES Y EXPOSICIONES | J23: Número de Actividades realizadas | K23: 800 | L23: Cultural | M23: Musos para la niñez: Misión Olimpo y un poco de IA | N23: ICONMUNITY invita a participar a las niñas a que exploten su creatividad al máximo utilizando la IA para entrenar un modelo basado en imágenes y videos de la instalación ubicada en el museo. | O23: Única | P23: 46137 | Q23: 46137 | R23: 1 | S23: Artes visuales | T23: Arte digital | U23: Taller | V23: Ninguna | W23: Presencial | X23: Espacio a Cargo de la Secretaría | Y23: 8 | AB23: FALSE | AD23: FALSE | AF23: FALSE | AH23: Sin costo | AL23: ccardonav@guanajuato.gob.mx | AM23: Juventudes: Apropiación de espacios públicos: revitalizar espacios subutilizados para actividades comunitarias y culturales, con jóvenes en su diseño y gestión. | AN23: 2 Igualdad | AO23: 2.4 Reducir brechas de desigualdad | AP23: 2.4.3 Descentralización de la oferta cultural | AQ23: 2.4.3.1 Impulsar el desarrollo artístico y cultural entre infancias y juventudes | AR23: Cooperación | AT23: Fortalecimiento de la participación ciudadana y la mediación cultural | AU23: Fortalecimiento del diálogo, la mediación y las capacidades de las redes comunitarias. | AV23: Diseñar e impartir talleres de formación en derechos culturales | AW23: Incrementar en 25% la oferta cultural realizada en los municipios. | AX23: Taller | AY23: Formación | BC23: 0 | BF23: FALSE | BL23: N/A | BM23: Sí | BP23: Abierta | BR23: =VLOOKUP(BQ23, Cat_Indicadores!B:C, 2, FALSE) -> #N/A
A24: ACT00023 | B24: SC-260615-115027 | C24: 46188.493 | D24: 92 | E24: PB3572 | F24: Gestión de programas de exposiciones, actividades formativas y académicas en los Museos de la Secretaría de Cultura y actividades extramuros | G24: Creación y participación en actividades formativas y académicas de los museos adscritos a la Secretaria de Cultura | H24: SUBSECRETARÍA DE DESARROLLO Y PROMOCIÓN ARTÍSTICA Y CULTURAL | I24: DIRECCIÓN GENERAL DE MUSEOS, ARTES VISUALES Y EXPOSICIONES | J24: Número de Actividades realizadas | K24: 800 | L24: Artística | M24: Encuentro de Danza Guanajuato | N24: En el marco del Dïa de la Danza habitemos los espacios del museo desde los diferentes estilos de danza y encontramos las posibilidades de expresión a través del cuerpo con la participación de 15 academias y colectivos guanajuatenses. En colaboración con Vaivén. Cuerpos en Escena. | O24: Única | P24: 46138 | Q24: 46138 | R24: 1 | S24: Artes escénicas | T24: Danza contemporánea | U24: Presentación artística | V24: Ninguna | W24: Presencial | X24: Espacio a Cargo de la Secretaría | Y24: 8 | AB24: FALSE | AD24: FALSE | AF24: FALSE | AH24: Sin costo | AL24: ccardonav@guanajuato.gob.mx | AM24: Leer para crecer. | AN24: 2 Igualdad | AO24: 2.4 Reducir brechas de desigualdad | AP24: 2.4.3 Descentralización de la oferta cultural | AQ24: 2.4.3.1 Impulsar el desarrollo artístico y cultural entre infancias y juventudes | AR24: Cooperación | AT24: Fomento a la creación y circulación cultural. | AU24: Incentivar la creación y producción artística y cultural de agentes locales. | AV24: Diseñar e implementar un sistema de reconocimiento público a las comunidades culturales. | AW24: Incrementar nuevas producciones, obras y proyectos culturales en un 15% anual. | AX24: Taller | AY24: Formación | BC24: 0 | BF24: FALSE | BL24: N/A | BM24: Sí | BP24: Abierta | BR24: =VLOOKUP(BQ24, Cat_Indicadores!B:C, 2, FALSE) -> #N/A
A25: ACT00024 | B25: SC-260615-120517 | C25: 46188.504 | D25: 92 | E25: PB3572 | F25: Gestión de programas de exposiciones, actividades formativas y académicas en los Museos de la Secretaría de Cultura y actividades extramuros | G25: Creación y participación en actividades formativas y académicas de los museos adscritos a la Secretaria de Cultura | H25: SUBSECRETARÍA DE DESARROLLO Y PROMOCIÓN ARTÍSTICA Y CULTURAL | I25: DIRECCIÓN GENERAL DE MUSEOS, ARTES VISUALES Y EXPOSICIONES | J25: Número de Actividades realizadas | K25: 800 | L25: Artística | M25: Museos para la niñez: "Donde nacen los sueños" Ballet infantil | N25: Disfruta del poder del ballet infantil como un lenguaje universal que acompaña el desarrollo, fortalece la disciplina y celebra la imaginación. Presenta: Rallye Studio Dirección: Ana Guillermina Oropeza y Mariah José Paloma Hurtado Martínez. | O25: Única | P25: 46138 | Q25: 46138 | R25: 1 | S25: Artes escénicas | T25: Danza tradicional | U25: Presentación artística | V25: Ninguna | W25: Presencial | X25: Espacio a Cargo de la Secretaría | Y25: 8 | AB25: FALSE | AD25: FALSE | AF25: FALSE | AH25: Sin costo | AL25: ccardonav@guanajuato.gob.mx | AM25: Juventudes: Apropiación de espacios públicos: revitalizar espacios subutilizados para actividades comunitarias y culturales, con jóvenes en su diseño y gestión. | AN25: 2 Igualdad | AO25: 2.4 Reducir brechas de desigualdad | AP25: 2.4.3 Descentralización de la oferta cultural | AQ25: 2.4.3.1 Impulsar el desarrollo artístico y cultural entre infancias y juventudes | AR25: Cooperación | AT25: Fomento a la creación y circulación cultural. | AU25: Incentivar la creación y producción artística y cultural de agentes locales. | AV25: Diseñar e implementar un sistema de reconocimiento público a las comunidades culturales. | AW25: Incrementar nuevas producciones, obras y proyectos culturales en un 15% anual. | AX25: Presentación artística | AY25: Formación | BC25: 0 | BF25: FALSE | BL25: N/A | BM25: Sí | BP25: Abierta | BR25: =VLOOKUP(BQ25, Cat_Indicadores!B:C, 2, FALSE) -> #N/A
A26: ACT00025 | B26: SC-260615-122541 | C26: 46188.518 | D26: 92 | E26: PB3572 | F26: Gestión de programas de exposiciones, actividades formativas y académicas en los Museos de la Secretaría de Cultura y actividades extramuros | G26: Creación y participación en actividades formativas y académicas de los museos adscritos a la Secretaria de Cultura | H26: SUBSECRETARÍA DE DESARROLLO Y PROMOCIÓN ARTÍSTICA Y CULTURAL | I26: DIRECCIÓN GENERAL DE MUSEOS, ARTES VISUALES Y EXPOSICIONES | J26: Número de Actividades realizadas | K26: 800 | L26: Cultural | M26: Palabras Umbral, Palabrasfilo. Hilandera: Flor Bosco. | N26: Un tejido verbal hecho con fibras extraídas de diversos poetas. Hilandera: Flor Bosco. | O26: Única | P26: 46150 | Q26: 46150 | R26: 1 | S26: Literatura | T26: Fomento a la lectura | U26: Muestra artística | V26: Ninguna | W26: Presencial | X26: Espacio a Cargo de la Secretaría | Y26: 8 | AB26: FALSE | AD26: FALSE | AF26: FALSE | AH26: Sin costo | AL26: ccardonav@guanajuato.gob.mx | AM26: Leer para crecer. | AN26: 4 Vocación | AO26: 4.4 Reforzar competencias lectoras y lógico matemáticas | AP26: 4.4.2 Competencias lectoras | AQ26: 4.4.2 Fomentar el hábito lector | AR26: Cooperación | AT26: Fomento a la creación y circulación cultural. | AU26: Incentivar la creación y producción artística y cultural de agentes locales. | AV26: Diseñar e implementar un sistema de reconocimiento público a las comunidades culturales. | AW26: Incrementar nuevas producciones, obras y proyectos culturales en un 15% anual. | AX26: Presentación artística | AY26: Formación | BC26: 0 | BF26: FALSE | BL26: N/A | BM26: Sí | BP26: Abierta | BR26: =VLOOKUP(BQ26, Cat_Indicadores!B:C, 2, FALSE) -> #N/A
A27: ACT00026 | B27: SC-260615-125555 | C27: 46188.539 | D27: 92 | E27: PB3572 | F27: Gestión de programas de exposiciones, actividades formativas y académicas en los Museos de la Secretaría de Cultura y actividades extramuros | G27: Creación y participación en actividades formativas y académicas de los museos adscritos a la Secretaria de Cultura | H27: SUBSECRETARÍA DE DESARROLLO Y PROMOCIÓN ARTÍSTICA Y CULTURAL | I27: DIRECCIÓN GENERAL DE MUSEOS, ARTES VISUALES Y EXPOSICIONES | J27: Número de Actividades realizadas | K27: 800 | L27: Cultural | M27: Entre medios y a través de. Diálogos con Miguel Mesa."Habitar ése bosque. Camila Apaez y Miguel Mesa" | N27: De forma teórica y práctica se dialogarán posibilidades para la gestación y desarrollo de proyectos artísticos, considerando los cruces entre medios, ideas, tecnología y disciplinas; tomando en cuenta la importancia de las decisiones estéticas, técnicas y políticas. El punto de partida será la exposición “Habitar ese bosque” que se encuentra expuesta en la sala CoLab del Museo de Arte e Historia de Guanajuato. | O27: Única | P27: 46157 | Q27: 46157 | R27: 1 | S27: Artes visuales | T27: Escultura | U27: Taller | V27: Ninguna | W27: Presencial | X27: Espacio a Cargo de la Secretaría | Y27: 8 | AB27: FALSE | AD27: FALSE | AF27: FALSE | AH27: Sin costo | AL27: ccardonav@guanajuato.gob.mx | AM27: Formación de formadores artísticos y culturales: Cursos y talleres de capacitación artística para docentes. Encuentros entre formadores de casas de cultura. Plataforma de colaboración entre instituciones culturales. | AN27: 1 Tranquilidad | AO27: 1.2 Fortalecer prevención del delito | AP27: 1.2.2 Fortalecimiento del tejido social | AQ27: 1.2.3.4 Promover una cultura de paz desde las expresiones artísticas y culturales | AR27: Cooperación | AT27: Impulso a la educación artística y a la profesionalización del sector cultural | AU27: Impulso a programas de formación y profesionalización para agentes culturales. | AV27: Diseñar programas de formación y profesionalización modulares y flexibles. | AW27: Incrementar un 30% la oferta de formación y profesionalización para agentes culturales. | AX27: Taller | AY27: Creación | BC27: 0 | BF27: FALSE | BL27: N/A | BM27: Sí | BP27: Abierta | BR27: =VLOOKUP(BQ27, Cat_Indicadores!B:C, 2, FALSE) -> #N/A
A28: ACT00027 | B28: SC-260615-142412 | C28: 46188.6 | D28: 92 | E28: PB3572 | F28: Gestión de programas de exposiciones, actividades formativas y académicas en los Museos de la Secretaría de Cultura y actividades extramuros | G28: Creación y participación en actividades formativas y académicas de los museos adscritos a la Secretaria de Cultura | H28: SUBSECRETARÍA DE DESARROLLO Y PROMOCIÓN ARTÍSTICA Y CULTURAL | I28: DIRECCIÓN GENERAL DE MUSEOS, ARTES VISUALES Y EXPOSICIONES | J28: Número de Actividades realizadas | K28: 800 | L28: Artística | M28: Museo en Escena. Encuentro Arte Guanajuato | N28: Presentación de performance de danza y música (saxofón) en diferentes espacios del museo como parte del programa del Dia Internacional de los Museos. | O28: Única | P28: 46159 | Q28: 46159 | R28: 1 | S28: Artes escénicas | T28: Danza tradicional | U28: Muestra artística | V28: Ninguna | W28: Presencial | X28: Espacio a Cargo de la Secretaría | Y28: 8 | AB28: FALSE | AD28: FALSE | AF28: FALSE | AH28: Sin costo | AL28: ccardonav@guanajuato.gob.mx | AM28: Juventudes: Apropiación de espacios públicos: revitalizar espacios subutilizados para actividades comunitarias y culturales, con jóvenes en su diseño y gestión. | AN28: 1 Tranquilidad | AO28: 1.2 Fortalecer prevención del delito | AP28: 1.2.2 Fortalecimiento del tejido social | AQ28: 1.2.3.4 Promover una cultura de paz desde las expresiones artísticas y culturales | AR28: Cooperación | AT28: Impulso a la educación artística y a la profesionalización del sector cultural | AU28: Impulso a programas de formación y profesionalización para agentes culturales. | AV28: Diseñar programas de formación y profesionalización modulares y flexibles. | AW28: Incrementar un 30% la oferta de formación y profesionalización para agentes culturales. | AX28: Presentación artística | AY28: Formación | BC28: 0 | BF28: FALSE | BL28: N/A | BM28: Sí | BP28: Abierta | BR28: =VLOOKUP(BQ28, Cat_Indicadores!B:C, 2, FALSE) -> #N/A
A29: ACT00028 | B29: SC-260615-143235 | C29: 46188.606 | D29: 92 | E29: PB3572 | F29: Gestión de programas de exposiciones, actividades formativas y académicas en los Museos de la Secretaría de Cultura y actividades extramuros | G29: Creación y participación en actividades formativas y académicas de los museos adscritos a la Secretaria de Cultura | H29: SUBSECRETARÍA DE DESARROLLO Y PROMOCIÓN ARTÍSTICA Y CULTURAL | I29: DIRECCIÓN GENERAL DE MUSEOS, ARTES VISUALES Y EXPOSICIONES | J29: Número de Actividades realizadas | K29: 800 | L29: Cultural | M29: Libro de Zona 102. Festival FELIZ. Región III, sector 03 y Zona 102. | N29: Cultivemos un mundo mejor a partir del arte y la literatura, abramos juntos las puertas del arte y la imaginación de las infancias. Descubre el poder de un libro. Abre una puerta al aprendizaje y la imaginación para tus hijos. ¡Ven a FELIZ y cultivemos juntos el amor a la lectura | O29: Única | P29: 46163 | Q29: 46163 | R29: 1 | S29: Literatura | T29: Fomento a la lectura | U29: Feria del libro | V29: Ninguna | W29: Presencial | X29: Espacio a Cargo de la Secretaría | Y29: 8 | AB29: FALSE | AD29: FALSE | AF29: FALSE | AH29: Sin costo | AL29: ccardonav@guanajuato.gob.mx | AM29: Leer para crecer. | AN29: 4 Vocación | AO29: 4.4 Reforzar competencias lectoras y lógico matemáticas | AP29: 4.4.2 Competencias lectoras | AQ29: 4.4.2 Fomentar el hábito lector | AR29: Cooperación | AT29: Fortalecimiento de la participación ciudadana y la mediación cultural | AU29: Fortalecimiento del diálogo, la mediación y las capacidades de las redes comunitarias. | AV29: Diseñar e impartir talleres de formación en derechos culturales | AW29: Incrementar en 25% la oferta cultural realizada en los municipios. | AX29: Feria del libro | AY29: Formación | BC29: 0 | BF29: FALSE | BL29: N/A | BM29: Sí | BP29: Abierta | BR29: =VLOOKUP(BQ29, Cat_Indicadores!B:C, 2, FALSE) -> #N/A
A30: ACT00029 | B30: SC-260615-143913 | C30: 46188.611 | D30: 92 | E30: PB3572 | F30: Gestión de programas de exposiciones, actividades formativas y académicas en los Museos de la Secretaría de Cultura y actividades extramuros | G30: Creación y participación en actividades formativas y académicas de los museos adscritos a la Secretaria de Cultura | H30: SUBSECRETARÍA DE DESARROLLO Y PROMOCIÓN ARTÍSTICA Y CULTURAL | I30: DIRECCIÓN GENERAL DE MUSEOS, ARTES VISUALES Y EXPOSICIONES | J30: Número de Actividades realizadas | K30: 800 | L30: Cultural | M30: Conferencia: Hipnosis y Estados Alterados de Consciencia. Presenta: Ramón Iturbide."Bajo el signo de Saturno. Adivinación en el arte" | N30: Descubre qué es la hipnosis y su relación con la conciencia a partir de su análisis desde la psicología. | O30: Única | P30: 46164 | Q30: 46164 | R30: 1 | S30: Artes visuales | T30: Performance visual | U30: Conferencia | V30: Ninguna | W30: Presencial | X30: Espacio a Cargo de la Secretaría | Y30: 8 | AB30: FALSE | AD30: FALSE | AF30: FALSE | AH30: Sin costo | AL30: ccardonav@guanajuato.gob.mx | AM30: Creación de la Secretaría de Cultura, con una visión social de la política cultural. | AN30: 4 Vocación | AO30: 4.4 Reforzar competencias lectoras y lógico matemáticas | AP30: 4.4.1 Competencias y habilidades | AQ30: 4.4.1 Competencias y habilidades | AR30: Cooperación | AT30: Fomento a la creación y circulación cultural. | AU30: Incentivar la creación y producción artística y cultural de agentes locales. | AV30: Diseñar e implementar un sistema de reconocimiento público a las comunidades culturales. | AW30: Incrementar nuevas producciones, obras y proyectos culturales en un 15% anual. | AX30: Conferencia | AY30: Formación | BC30: 0 | BF30: FALSE | BL30: N/A | BM30: Sí | BP30: Abierta | BR30: =VLOOKUP(BQ30, Cat_Indicadores!B:C, 2, FALSE) -> #N/A
A31: ACT00030 | B31: SC-260615-144427 | C31: 46188.614 | D31: 92 | E31: PB3572 | F31: Gestión de programas de exposiciones, actividades formativas y académicas en los Museos de la Secretaría de Cultura y actividades extramuros | G31: Creación y participación en actividades formativas y académicas de los museos adscritos a la Secretaria de Cultura | H31: SUBSECRETARÍA DE DESARROLLO Y PROMOCIÓN ARTÍSTICA Y CULTURAL | I31: DIRECCIÓN GENERAL DE MUSEOS, ARTES VISUALES Y EXPOSICIONES | J31: Número de Actividades realizadas | K31: 800 | L31: Cultural | M31: Conferencia: Tarot como camino del autoconocimiento. Presenta: Alejandra del Castillo Negrete. "Bajo el signo de Saturno. Adivinación en el arte" | N31: Charla en la que nos introduciremos en el mundo del tarot como una posible herramienta del análisis del comportamiento humano. | O31: Única | P31: 46165 | Q31: 46165 | R31: 1 | S31: Literatura | T31: Narrativa | U31: Conferencia | V31: Ninguna | W31: Presencial | X31: Espacio a Cargo de la Secretaría | Y31: 8 | AB31: FALSE | AD31: FALSE | AF31: FALSE | AH31: Sin costo | AL31: ccardonav@guanajuato.gob.mx | AM31: Juventudes: Apropiación de espacios públicos: revitalizar espacios subutilizados para actividades comunitarias y culturales, con jóvenes en su diseño y gestión. | AN31: 5 Prosperidad | AO31: 5.4 Fortalecer presencia turística | AP31: 5.4 Fortalecer presencia turística | AQ31: 5.4 Fortalecer presencia turística | AR31: Cooperación | AT31: Sostenibilidad del trabajo cultural y la economía creativa. | AU31: Consolidación de los mecanismos de gobernanza para el uso de los espacios cultuales y zonas patrimoniales. | AV31: Diseñar programas de formación y gestión cultural de base comunitaria. | AW31: Incrementar un 30% la participación de grupos, colectivos y comunidades en procesos de memoria, investigación, divulgación y difusión del patrimonio material e inmaterial | AX31: Conferencia | AY31: Formación | AZ31: Formación | BC31: 0 | BF31: FALSE | BL31: N/A | BM31: Sí | BP31: Abierta | BR31: =VLOOKUP(BQ31, Cat_Indicadores!B:C, 2, FALSE) -> #N/A
A32: ACT-SCYJ01916 | B32: SC-260617-135837 | C32: 46190.582 | D32: 92 | E32: PB3572 | F32: Gestión de programas de exposiciones, actividades formativas y académicas en los Museos de la Secretaría de Cultura y actividades extramuros | G32: Creación y participación en actividades formativas y académicas de los museos adscritos a la Secretaria de Cultura | H32: SUBSECRETARÍA DE DESARROLLO Y PROMOCIÓN ARTÍSTICA Y CULTURAL | I32: DIRECCIÓN GENERAL DE MUSEOS, ARTES VISUALES Y EXPOSICIONES | J32: Número de Actividades realizadas | K32: 800 | L32: Cultural | M32: Compilación Viernes de Dolores en Guanajuato | N32: Presentación editorial a cargo del autor sobre la tradición del Viernes de Dolores en la ciudad de Guanajuato. | O32: Única | P32: 46120 | Q32: 46120 | R32: 1 | S32: Multidisciplinario | T32: Investigación cultural | U32: Conferencia | V32: Ninguna | W32: Presencial | X32: Espacio a Cargo de la Secretaría | Y32: 3 | AB32: FALSE | AD32: FALSE | AF32: FALSE | AH32: Sin costo | AL32: ccardonav@guanajuato.gob.mx | AM32: Arraigo y empoderamiento cultural de comunidades. | AN32: 1 Tranquilidad | AO32: 1.2 Fortalecer prevención del delito | AP32: 1.2.2 Fortalecimiento del tejido social | AQ32: 1.2.3.4 Promover una cultura de paz desde las expresiones artísticas y culturales | AR32: Cooperación | AT32: Fortalecimiento de la participación ciudadana y la mediación cultural | AU32: Impulso a la ampliación de la oferta cultural en los territorios. | AV32: Fortalecer la programación cultural en espacios públicos, espacios alternativos y otros espacios culturales. | AW32: Incrementar en 25% la oferta cultural realizada en los municipios. | AX32: Presentación editorial | AY32: Formación | AZ32: Formación | BC32: 0 | BF32: FALSE | BM32: No | BQ32: Abierta | BR32: =VLOOKUP(BQ32, Cat_Indicadores!B:C, 2, FALSE) -> #N/A | BS32: #ERROR!
A33: ACT-SCHP41657 | B33: SC-260617-140546 | C33: 46190.587 | D33: 92 | E33: PB3572 | F33: Gestión de programas de exposiciones, actividades formativas y académicas en los Museos de la Secretaría de Cultura y actividades extramuros | G33: Creación y participación en actividades formativas y académicas de los museos adscritos a la Secretaria de Cultura | H33: SUBSECRETARÍA DE DESARROLLO Y PROMOCIÓN ARTÍSTICA Y CULTURAL | I33: DIRECCIÓN GENERAL DE MUSEOS, ARTES VISUALES Y EXPOSICIONES | J33: Número de Actividades realizadas | K33: 800 | L33: Artística | M33: Cuentacuentos: Luis Long, el arquitecto del tiempo | N33: Luis Long el relojero, viajero, constructor de palacios, arquitecto londinense y leones nos cuenta su historia iMil aventuras vivirán y muchos títeres verán!, actividad en torno al 99° Aniversario luctuoso de Louis Long. | O33: Única | P33: 46123 | Q33: 46123 | R33: 1 | S33: Artes escénicas | T33: Teatro | U33: Muestra artística | V33: Ninguna | W33: Presencial | X33: Espacio a Cargo de la Secretaría | Y33: 5 | AB33: FALSE | AD33: TRUE | AE33: 1 | AF33: FALSE | AH33: Sin costo | AL33: ccardonav@guanajuato.gob.mx | AM33: Arraigo y empoderamiento cultural de comunidades. | AN33: 1 Tranquilidad | AO33: 1.2 Fortalecer prevención del delito | AP33: 1.2.2 Fortalecimiento del tejido social | AQ33: 1.2.3.4 Promover una cultura de paz desde las expresiones artísticas y culturales | AR33: Cooperación | AT33: Fortalecimiento de la participación ciudadana y la mediación cultural | AU33: Impulso a la ampliación de la oferta cultural en los territorios. | AV33: Fortalecer la programación cultural en espacios públicos, espacios alternativos y otros espacios culturales. | AW33: Incrementar en 25% la oferta cultural realizada en los municipios. | AX33: Presentación artística | AY33: Formación | AZ33: Formación | BC33: 0 | BF33: FALSE | BM33: No | BQ33: Abierta | BR33: =VLOOKUP(BQ33, Cat_Indicadores!B:C, 2, FALSE) -> #N/A | BS33: #ERROR!
A34: ACT-SCXD05649 | B34: SC-260617-141205 | C34: 46190.592 | D34: 92 | E34: PB3572 | F34: Gestión de programas de exposiciones, actividades formativas y académicas en los Museos de la Secretaría de Cultura y actividades extramuros | G34: Creación y participación en actividades formativas y académicas de los museos adscritos a la Secretaria de Cultura | H34: SUBSECRETARÍA DE DESARROLLO Y PROMOCIÓN ARTÍSTICA Y CULTURAL | I34: DIRECCIÓN GENERAL DE MUSEOS, ARTES VISUALES Y EXPOSICIONES | J34: Número de Actividades realizadas | K34: 800 | L34: Artística | M34: Taller familiar de barro | N34: Un espacio de encuentro y difusión en torno al cierre de las exposiciones La mayólica de Gorky González. Una tradición que vive, Dolores Porras. Taller de Cerámica y Diálogo entre los Grandes Maestros del Arte Popular de Guanajuato y Veracruz. | O34: Única | P34: 46124 | Q34: 46124 | R34: 1 | S34: Artes visuales | T34: Escultura | U34: Taller | V34: Ninguna | W34: Presencial | X34: Espacio a Cargo de la Secretaría | Y34: 2 | AB34: FALSE | AD34: FALSE | AF34: FALSE | AH34: Sin costo | AL34: ccardonav@guanajuato.gob.mx | AM34: Arraigo y empoderamiento cultural de comunidades. | AN34: 1 Tranquilidad | AO34: 1.2 Fortalecer prevención del delito | AP34: 1.2.2 Fortalecimiento del tejido social | AQ34: 1.2.3.4 Promover una cultura de paz desde las expresiones artísticas y culturales | AR34: Cooperación | AT34: Fortalecimiento de la participación ciudadana y la mediación cultural | AU34: Impulso a la ampliación de la oferta cultural en los territorios. | AV34: Fortalecer la programación cultural en espacios públicos, espacios alternativos y otros espacios culturales. | AW34: Incrementar en 25% la oferta cultural realizada en los municipios. | AX34: Taller | AY34: Formación | AZ34: Formación | BC34: 0 | BF34: FALSE | BM34: No | BQ34: Abierta | BR34: =VLOOKUP(BQ34, Cat_Indicadores!B:C, 2, FALSE) -> #N/A | BS34: #ERROR!
A35: ACT-SCQF07472 | B35: SC-260617-142030 | C35: 46190.598 | D35: 92 | E35: PB3572 | F35: Gestión de programas de exposiciones, actividades formativas y académicas en los Museos de la Secretaría de Cultura y actividades extramuros | G35: Creación y participación en actividades formativas y académicas de los museos adscritos a la Secretaria de Cultura | H35: SUBSECRETARÍA DE DESARROLLO Y PROMOCIÓN ARTÍSTICA Y CULTURAL | I35: DIRECCIÓN GENERAL DE MUSEOS, ARTES VISUALES Y EXPOSICIONES | J35: Número de Actividades realizadas | K35: 800 | L35: Artística | M35: Tradición cerámica en Guanajuato | N35: conferencia a cargo de Paulina Delgado en torno a esta importante tradición | O35: Única | P35: 46124 | Q35: 46124 | R35: 1 | S35: Artesanías y arte popular | T35: Cerámica | U35: Conferencia | V35: Ninguna | W35: Presencial | X35: Espacio a Cargo de la Secretaría | Y35: 2 | AB35: FALSE | AD35: FALSE | AF35: FALSE | AH35: Sin costo | AL35: ccardonav@guanajuato.gob.mx | AM35: Arraigo y empoderamiento cultural de comunidades. | AN35: 1 Tranquilidad | AO35: 1.2 Fortalecer prevención del delito | AP35: 1.2.2 Fortalecimiento del tejido social | AQ35: 1.2.3.4 Promover una cultura de paz desde las expresiones artísticas y culturales | AR35: Cooperación | AT35: Fortalecimiento de la participación ciudadana y la mediación cultural | AU35: Impulso a la ampliación de la oferta cultural en los territorios. | AV35: Fortalecer la programación cultural en espacios públicos, espacios alternativos y otros espacios culturales. | AW35: Incrementar en 25% la oferta cultural realizada en los municipios. | AX35: Taller | AY35: Formación | AZ35: Formación | BC35: 0 | BF35: FALSE | BM35: No | BQ35: Abierta | BR35: =VLOOKUP(BQ35, Cat_Indicadores!B:C, 2, FALSE) -> #N/A | BS35: #ERROR!
A36: ACT-SCNJ91361 | B36: SC-260617-143326 | C36: 46190.607 | D36: 92 | E36: PB3572 | F36: Gestión de programas de exposiciones, actividades formativas y académicas en los Museos de la Secretaría de Cultura y actividades extramuros | G36: Creación y participación en actividades formativas y académicas de los museos adscritos a la Secretaria de Cultura | H36: SUBSECRETARÍA DE DESARROLLO Y PROMOCIÓN ARTÍSTICA Y CULTURAL | I36: DIRECCIÓN GENERAL DE MUSEOS, ARTES VISUALES Y EXPOSICIONES | J36: Número de Actividades realizadas | K36: 800 | L36: Artística | M36: Talleres en el Día Mundial del Arte | N36: Invitamos a las niñas, niños y sus familias, a celebrar el Día Mundial del Arte con un recorrido lúdico por el Museo Conde Rul y a participar en nuestras mesas de arte: grabado, pintura y barro. Con participación musical Sakura, tema y variaciones, por Gustavo Botello Áviles. | O36: Única | P36: 46127 | Q36: 46127 | R36: 1 | S36: Artes visuales | T36: Pintura | U36: Taller | V36: Ninguna | W36: Presencial | X36: Espacio a Cargo de la Secretaría | Y36: 4 | AB36: FALSE | AD36: FALSE | AF36: FALSE | AH36: Sin costo | AL36: ccardonav@guanajuato.gob.mx | AM36: Arraigo y empoderamiento cultural de comunidades. | AN36: 2 Igualdad | AO36: 2.4 Reducir brechas de desigualdad | AP36: 2.4.3 Descentralización de la oferta cultural | AQ36: 2.4.3.1 Impulsar el desarrollo artístico y cultural entre infancias y juventudes | AR36: Cooperación | AT36: Fortalecimiento de la participación ciudadana y la mediación cultural | AU36: Impulso a la ampliación de la oferta cultural en los territorios. | AV36: Fortalecer la programación cultural en espacios públicos, espacios alternativos y otros espacios culturales. | AW36: Incrementar en 25% la oferta cultural realizada en los municipios. | AX36: Taller | AY36: Formación | AZ36: Formación | BC36: 0 | BF36: FALSE | BM36: No | BQ36: Abierta | BR36: =VLOOKUP(BQ36, Cat_Indicadores!B:C, 2, FALSE) -> #N/A | BS36: #ERROR!
A37: ACT-SCNO77641 | B37: SC-260617-143908 | C37: 46190.611 | D37: 92 | E37: PB3572 | F37: Gestión de programas de exposiciones, actividades formativas y académicas en los Museos de la Secretaría de Cultura y actividades extramuros | G37: Creación y participación en actividades formativas y académicas de los museos adscritos a la Secretaria de Cultura | H37: SUBSECRETARÍA DE DESARROLLO Y PROMOCIÓN ARTÍSTICA Y CULTURAL | I37: DIRECCIÓN GENERAL DE MUSEOS, ARTES VISUALES Y EXPOSICIONES | J37: Número de Actividades realizadas | K37: 800 | L37: Artística | M37: Recital de guitarra en el Día Mundial del arte | N37: Con participación musical Sakura, tema y variaciones, por Gustavo Botello Áviles. | O37: Única | P37: 46127 | Q37: 46127 | R37: 1 | S37: Música | T37: Música académica | U37: Presentación artística | V37: Ninguna | W37: Presencial | X37: Espacio a Cargo de la Secretaría | Y37: 4 | AB37: FALSE | AD37: FALSE | AF37: FALSE | AH37: Sin costo | AL37: ccardonav@guanajuato.gob.mx | AM37: Arraigo y empoderamiento cultural de comunidades. | AN37: 1 Tranquilidad | AO37: 1.2 Fortalecer prevención del delito | AP37: 1.2.2 Fortalecimiento del tejido social | AQ37: 1.2.3.4 Promover una cultura de paz desde las expresiones artísticas y culturales | AR37: Cooperación | AT37: Fortalecimiento de la participación ciudadana y la mediación cultural | AU37: Impulso a la ampliación de la oferta cultural en los territorios. | AV37: Fortalecer la programación cultural en espacios públicos, espacios alternativos y otros espacios culturales. | AW37: Incrementar en 25% la oferta cultural realizada en los municipios. | AX37: Taller | AY37: Formación | AZ37: Formación | BC37: 0 | BF37: FALSE | BL37: Vinculación | BM37: Sí | BQ37: Abierta | BR37: =VLOOKUP(BQ37, Cat_Indicadores!B:C, 2, FALSE) -> #N/A | BS37: #ERROR!
A38: ACT-SCEB55079 | B38: SC-260617-144916 | C38: 46190.618 | D38: 92 | E38: PB3572 | F38: Gestión de programas de exposiciones, actividades formativas y académicas en los Museos de la Secretaría de Cultura y actividades extramuros | G38: Creación y participación en actividades formativas y académicas de los museos adscritos a la Secretaria de Cultura | H38: SUBSECRETARÍA DE DESARROLLO Y PROMOCIÓN ARTÍSTICA Y CULTURAL | I38: DIRECCIÓN GENERAL DE MUSEOS, ARTES VISUALES Y EXPOSICIONES | J38: Número de Actividades realizadas | K38: 800 | L38: Artística | M38: Recorrido guiado en Día Mundial del arte | N38: Invitamos a las niñas, niños y sus familias, a celebrar el Día Mundial del Arte con un recorrido lúdico por el Museo Conde Rul y a participar en nuestras mesas de arte: grabado, pintura y barro. Con participación musical Sakura, tema y variaciones, por Gustavo Botello Áviles. | O38: Única | P38: 46127 | Q38: 46127 | R38: 1 | S38: Cultura comunitaria | T38: Formación comunitaria | U38: Visitas guiadas | V38: Ninguna | W38: Presencial | X38: Espacio a Cargo de la Secretaría | Y38: 4 | AB38: FALSE | AD38: FALSE | AF38: FALSE | AH38: Sin costo | AL38: ccardonav@guanajuato.gob.mx | AM38: Arraigo y empoderamiento cultural de comunidades. | AN38: 2 Igualdad | AO38: 2.4 Reducir brechas de desigualdad | AP38: 2.4.3 Descentralización de la oferta cultural | AQ38: 2.4.3.1 Impulsar el desarrollo artístico y cultural entre infancias y juventudes | AR38: Cooperación | AT38: Fortalecimiento de la participación ciudadana y la mediación cultural | AU38: Impulso a la ampliación de la oferta cultural en los territorios. | AV38: Fortalecer la programación cultural en espacios públicos, espacios alternativos y otros espacios culturales. | AW38: Incrementar en 25% la oferta cultural realizada en los municipios. | AX38: Visitas institucionales | AY38: Formación | AZ38: Formación | BC38: 0 | BF38: FALSE | BM38: No | BQ38: Abierta | BR38: =VLOOKUP(BQ38, Cat_Indicadores!B:C, 2, FALSE) -> #N/A | BS38: #ERROR!
A39: ACT-SCAN56678 | B39: SC-260618-113309 | C39: 46191.481 | D39: 92 | E39: PB3572 | F39: Gestión de programas de exposiciones, actividades formativas y académicas en los Museos de la Secretaría de Cultura y actividades extramuros | G39: Creación y participación en actividades formativas y académicas de los museos adscritos a la Secretaria de Cultura | H39: SUBSECRETARÍA DE DESARROLLO Y PROMOCIÓN ARTÍSTICA Y CULTURAL | I39: DIRECCIÓN GENERAL DE MUSEOS, ARTES VISUALES Y EXPOSICIONES | J39: Número de Actividades realizadas | K39: 800 | L39: Artística | M39: Me conozco y me quiero | N39: Taller que tiene como objetivo fomentar el autoconocimiento, el autoestima y el amor propio en la niñez a través de una actividad artística, en donde las niñas y niños realizarán un autorretrato con diversos materiales, reflexionarán sobre sus cualidades, su valor y la importancia de su autocuidado propio y personal. | O39: Única | P39: 46130 | Q39: 46130 | R39: 1 | S39: Artes visuales | T39: Dibujo | U39: Taller | V39: Ninguna | W39: Presencial | X39: Espacio a Cargo de la Secretaría | Y39: 2 | AB39: FALSE | AD39: FALSE | AF39: FALSE | AH39: Sin costo | AL39: ccardonav@guanajuato.gob.mx | AM39: Arraigo y empoderamiento cultural de comunidades. | AN39: 2 Igualdad | AO39: 2.4 Reducir brechas de desigualdad | AP39: 2.4.3 Descentralización de la oferta cultural | AQ39: 2.4.3.1 Impulsar el desarrollo artístico y cultural entre infancias y juventudes | AR39: Cooperación | AT39: Fortalecimiento de la participación ciudadana y la mediación cultural | AU39: Impulso a la ampliación de la oferta cultural en los territorios. | AV39: Fortalecer la programación cultural en espacios públicos, espacios alternativos y otros espacios culturales. | AW39: Incrementar en 25% la oferta cultural realizada en los municipios. | AX39: Taller | AY39: Formación | AZ39: Formación | BC39: 0 | BF39: FALSE | BM39: No | BQ39: Abierta | BR39: =VLOOKUP(BQ39, Cat_Indicadores!B:C, 2, FALSE) -> #N/A | BS39: #ERROR!
A40: ACT-SCFI49355 | B40: SC-260618-115051 | C40: 46191.494 | D40: 92 | E40: PB3572 | F40: Gestión de programas de exposiciones, actividades formativas y académicas en los Museos de la Secretaría de Cultura y actividades extramuros | G40: Creación y participación en actividades formativas y académicas de los museos adscritos a la Secretaria de Cultura | H40: SUBSECRETARÍA DE DESARROLLO Y PROMOCIÓN ARTÍSTICA Y CULTURAL | I40: DIRECCIÓN GENERAL DE MUSEOS, ARTES VISUALES Y EXPOSICIONES | J40: Número de Actividades realizadas | K40: 800 | L40: Artística | M40: La escuela al Museo | N40: Estudiantes de la Licenciatura en Artes Visuales de la Universidad de Guanajuato acudirán a las distintas sedes de los Museos de la Secretaría de Cultura a participar en talleres artísticos, con la finalidad de que conozcan las valiosas colecciones de los museos y un primer acercamiento a las técnicas con las que fueron elaboradas algunas las obras. | O40: Única | P40: 46133 | Q40: 46133 | R40: 1 | S40: Cultura comunitaria | T40: Formación comunitaria | U40: Taller | V40: Ninguna | W40: Presencial | X40: Espacio a Cargo de la Secretaría | Y40: 9 | AB40: FALSE | AD40: FALSE | AF40: FALSE | AH40: Sin costo | AL40: ccardonav@guanajuato.gob.mx | AM40: Arraigo y empoderamiento cultural de comunidades. | AN40: 2 Igualdad | AO40: 2.4 Reducir brechas de desigualdad | AP40: 2.4.3 Descentralización de la oferta cultural | AQ40: 2.4.3.1 Impulsar el desarrollo artístico y cultural entre infancias y juventudes | AR40: Cooperación | AT40: Fortalecimiento de la participación ciudadana y la mediación cultural | AU40: Impulso a la ampliación de la oferta cultural en los territorios. | AV40: Fortalecer la programación cultural en espacios públicos, espacios alternativos y otros espacios culturales. | AW40: Incrementar en 25% la oferta cultural realizada en los municipios. | AX40: Visitas escolares | AY40: Formación | AZ40: Formación | BC40: 0 | BF40: FALSE | BM40: No | BQ40: Abierta | BR40: =VLOOKUP(BQ40, Cat_Indicadores!B:C, 2, FALSE) -> #N/A | BS40: #ERROR!
A41: ACT-SCJD19095 | B41: SC-260618-115556 | C41: 46191.497 | D41: 92 | E41: PB3572 | F41: Gestión de programas de exposiciones, actividades formativas y académicas en los Museos de la Secretaría de Cultura y actividades extramuros | G41: Creación y participación en actividades formativas y académicas de los museos adscritos a la Secretaria de Cultura | H41: SUBSECRETARÍA DE DESARROLLO Y PROMOCIÓN ARTÍSTICA Y CULTURAL | I41: DIRECCIÓN GENERAL DE MUSEOS, ARTES VISUALES Y EXPOSICIONES | J41: Número de Actividades realizadas | K41: 800 | L41: Artística | M41: Cuentos al piano | N41: Concierto dirigido a niñas y niños a cargo de estudiantes de música de la Universidad | O41: Única | P41: 46133 | Q41: 46133 | R41: 1 | S41: Música | T41: Música académica | U41: Presentación artística | V41: Ninguna | W41: Presencial | X41: Espacio a Cargo de la Secretaría | Y41: 5 | AB41: FALSE | AD41: FALSE | AF41: FALSE | AH41: Sin costo | AL41: ccardonav@guanajuato.gob.mx | AM41: Arraigo y empoderamiento cultural de comunidades. | AN41: 1 Tranquilidad | AO41: 1.2 Fortalecer prevención del delito | AP41: 1.2.2 Fortalecimiento del tejido social | AQ41: 1.2.3.4 Promover una cultura de paz desde las expresiones artísticas y culturales | AR41: Cooperación | AT41: Fortalecimiento de la participación ciudadana y la mediación cultural | AU41: Impulso a la ampliación de la oferta cultural en los territorios. | AV41: Fortalecer la programación cultural en espacios públicos, espacios alternativos y otros espacios culturales. | AW41: Incrementar en 25% la oferta cultural realizada en los municipios. | AX41: Presentación editorial | AY41: Formación | AZ41: Formación | BC41: 0 | BF41: FALSE | BL41: Vinculacion | BM41: Sí | BQ41: Abierta | BR41: =VLOOKUP(BQ41, Cat_Indicadores!B:C, 2, FALSE) -> #N/A | BS41: #ERROR!
A42: ACT-SCZZ10210 | B42: SC-260618-141113 | C42: 46191.591 | D42: 92 | E42: PB3572 | F42: Gestión de programas de exposiciones, actividades formativas y académicas en los Museos de la Secretaría de Cultura y actividades extramuros | G42: Creación y participación en actividades formativas y académicas de los museos adscritos a la Secretaria de Cultura | H42: SUBSECRETARÍA DE DESARROLLO Y PROMOCIÓN ARTÍSTICA Y CULTURAL | I42: DIRECCIÓN GENERAL DE MUSEOS, ARTES VISUALES Y EXPOSICIONES | J42: Número de Actividades realizadas | K42: 800 | L42: Artística | M42: Circulo de lectura escritura para niños, niñas y adolescentes | N42: A partir de la lectura de Cuentos para niños que se atreven a ser diferentes y Cuentos de buenas noches para niñas rebeldes se busca fomentar el respeto y empatía entre niños y niñas con énfasis en la equidad e igualdad. | O42: Única | P42: 46134 | Q42: 46134 | R42: 1 | S42: Literatura | T42: Fomento a la lectura | U42: Taller | V42: Ninguna | W42: Presencial | X42: Espacio a Cargo de la Secretaría | Y42: 1 | AB42: FALSE | AD42: TRUE | AE42: 1 | AF42: FALSE | AH42: Sin costo | AL42: ccardonav@guanajuato.gob.mx | AM42: Leer para crecer. | AN42: 1 Tranquilidad | AO42: 1.2 Fortalecer prevención del delito | AP42: 1.2.2 Fortalecimiento del tejido social | AQ42: 1.2.3.4 Promover una cultura de paz desde las expresiones artísticas y culturales | AR42: Cooperación | AT42: Fortalecimiento de la participación ciudadana y la mediación cultural | AU42: Impulso a la ampliación de la oferta cultural en los territorios. | AV42: Fortalecer la programación cultural en espacios públicos, espacios alternativos y otros espacios culturales. | AW42: Incrementar en 25% la oferta cultural realizada en los municipios. | AX42: Taller | AY42: Formación | AZ42: Formación | BC42: 0 | BF42: FALSE | BM42: No | BQ42: Abierta | BR42: =VLOOKUP(BQ42, Cat_Indicadores!B:C, 2, FALSE) -> #N/A | BS42: #ERROR!
A43: ACT-SCGV04211 | B43: SC-260618-143128 | C43: 46191.605 | D43: 92 | E43: PB3572 | F43: Gestión de programas de exposiciones, actividades formativas y académicas en los Museos de la Secretaría de Cultura y actividades extramuros | G43: Creación y participación en actividades formativas y académicas de los museos adscritos a la Secretaria de Cultura | H43: SUBSECRETARÍA DE DESARROLLO Y PROMOCIÓN ARTÍSTICA Y CULTURAL | I43: DIRECCIÓN GENERAL DE MUSEOS, ARTES VISUALES Y EXPOSICIONES | J43: Número de Actividades realizadas | K43: 800 | L43: Artística | M43: Museos desde la primera infancia | N43: Taller de experiencias artísticas que estimulan la necesidad natural de exploración de las niñas y niños de seis meses a cinco años, los participantes de la mano de su mamá, papá o cuidador participarán activamente en el descubrimiento de materiales, olores, sonidos y otros elementos que estimulen su desarrollo. | O43: Única | P43: 46134 | Q43: 46134 | R43: 1 | S43: Cultura comunitaria | T43: Formación comunitaria | U43: Taller | V43: Ninguna | W43: Presencial | X43: Espacio a Cargo de la Secretaría | Y43: 1 | AB43: FALSE | AD43: FALSE | AF43: FALSE | AH43: Sin costo | AL43: ccardonav@guanajuato.gob.mx | AM43: Arraigo y empoderamiento cultural de comunidades. | AN43: 2 Igualdad | AO43: 2.4 Reducir brechas de desigualdad | AP43: 2.4.3 Descentralización de la oferta cultural | AQ43: 2.4.3.1 Impulsar el desarrollo artístico y cultural entre infancias y juventudes | AR43: Cooperación | AT43: Fortalecimiento de la participación ciudadana y la mediación cultural | AU43: Impulso a la ampliación de la oferta cultural en los territorios. | AV43: Fortalecer la programación cultural en espacios públicos, espacios alternativos y otros espacios culturales. | AW43: Incrementar en 25% la oferta cultural realizada en los municipios. | AX43: Taller | AY43: Formación | AZ43: Formación | BC43: 0 | BF43: FALSE | BM43: No | BQ43: Abierta | BR43: =VLOOKUP(BQ43, Cat_Indicadores!B:C, 2, FALSE) -> #N/A | BS43: #ERROR!
A44: ACT-SCMY03003 | B44: SC-260618-143808 | C44: 46191.61 | D44: 92 | E44: PB3572 | F44: Gestión de programas de exposiciones, actividades formativas y académicas en los Museos de la Secretaría de Cultura y actividades extramuros | G44: Creación y participación en actividades formativas y académicas de los museos adscritos a la Secretaria de Cultura | H44: SUBSECRETARÍA DE DESARROLLO Y PROMOCIÓN ARTÍSTICA Y CULTURAL | I44: DIRECCIÓN GENERAL DE MUSEOS, ARTES VISUALES Y EXPOSICIONES | J44: Número de Actividades realizadas | K44: 800 | L44: Artística | M44: Inauguración de la exposición: Poética del paisaje | N44: Apelando al poema del maestro Carlos Pellicer Cámara, la exposición Poética del Paisaje, vuelve a reunir a los ciudadanos tabasqueños con el acervo que resguarda el Museo Nacional de Arte, perteneciente a la red de museos del Instituto Nacional de Bellas Artes y Literatura. | O44: Única | P44: 46135 | Q44: 46135 | R44: 1 | S44: Artes visuales | T44: Pintura | U44: Exposición | V44: Ninguna | W44: Presencial | X44: Espacio a Cargo de la Secretaría | Y44: 6 | AB44: FALSE | AD44: TRUE | AE44: 1 | AF44: FALSE | AH44: Sin costo | AL44: ccardonav@guanajuato.gob.mx | AM44: Creación de la Secretaría de Cultura, con una visión social de la política cultural. | AN44: 1 Tranquilidad | AO44: 1.2 Fortalecer prevención del delito | AP44: 1.2.2 Fortalecimiento del tejido social | AQ44: 1.2.3.4 Promover una cultura de paz desde las expresiones artísticas y culturales | AR44: Cooperación | AT44: Fortalecimiento de la participación ciudadana y la mediación cultural | AU44: Impulso a la ampliación de la oferta cultural en los territorios. | AV44: Fortalecer la programación cultural en espacios públicos, espacios alternativos y otros espacios culturales. | AW44: Incrementar en 25% la oferta cultural realizada en los municipios. | AX44: Exposición | AY44: Formación | BC44: 0 | BF44: FALSE | BM44: No | BQ44: Abierta | BR44: =VLOOKUP(BQ44, Cat_Indicadores!B:C, 2, FALSE) -> #N/A | BS44: #ERROR!
A45: ACT-SCKO16141 | B45: SC-260618-145323 | C45: 46191.62 | D45: 92 | E45: PB3572 | F45: Gestión de programas de exposiciones, actividades formativas y académicas en los Museos de la Secretaría de Cultura y actividades extramuros | G45: Creación y participación en actividades formativas y académicas de los museos adscritos a la Secretaria de Cultura | H45: SUBSECRETARÍA DE DESARROLLO Y PROMOCIÓN ARTÍSTICA Y CULTURAL | I45: DIRECCIÓN GENERAL DE MUSEOS, ARTES VISUALES Y EXPOSICIONES | J45: Número de Actividades realizadas | K45: 800 | L45: Artística | M45: Noche misteriosa en los museos. | N45: Las niñas y niños participantes podrán visitar el museo en un horario especial, en donde a través de juego, arte y diversión podrán recorrer los espacios y las obras que atesoran este espacio. | O45: Única | P45: 46136 | Q45: 46136 | R45: 1 | S45: Artes visuales | T45: Pintura | U45: Taller | V45: Ninguna | W45: Presencial | X45: Espacio a Cargo de la Secretaría | Y45: 6 | AB45: FALSE | AD45: FALSE | AF45: FALSE | AH45: Sin costo | AL45: ccardonav@guanajuato.gob.mx | AM45: Arraigo y empoderamiento cultural de comunidades. | AN45: 2 Igualdad | AO45: 2.4 Reducir brechas de desigualdad | AP45: 2.4.3 Descentralización de la oferta cultural | AQ45: 2.4.3.1 Impulsar el desarrollo artístico y cultural entre infancias y juventudes | AR45: Cooperación | AT45: Fortalecimiento de la participación ciudadana y la mediación cultural | AU45: Impulso a la ampliación de la oferta cultural en los territorios. | AV45: Fortalecer la programación cultural en espacios públicos, espacios alternativos y otros espacios culturales. | AW45: Incrementar en 25% la oferta cultural realizada en los municipios. | AX45: Taller | AY45: Formación | AZ45: Formación | BC45: 0 | BF45: FALSE | BM45: No | BQ45: Abierta | BR45: =VLOOKUP(BQ45, Cat_Indicadores!B:C, 2, FALSE) -> #N/A | BS45: #ERROR!
A46: ACT-SCJC28810 | B46: SC-260618-151905 | C46: 46191.638 | D46: 92 | E46: PB3572 | F46: Gestión de programas de exposiciones, actividades formativas y académicas en los Museos de la Secretaría de Cultura y actividades extramuros | G46: Creación y participación en actividades formativas y académicas de los museos adscritos a la Secretaria de Cultura | H46: SUBSECRETARÍA DE DESARROLLO Y PROMOCIÓN ARTÍSTICA Y CULTURAL | I46: DIRECCIÓN GENERAL DE MUSEOS, ARTES VISUALES Y EXPOSICIONES | J46: Número de Actividades realizadas | K46: 800 | L46: Artística | M46: Me conozco y me quiero | N46: Taller que tiene como objetivo fomentar el autoconocimiento, el autoestima y el amor propio en la niñez a través de una actividad artística, en donde las niñas y niños realizarán un autorretrato con diversos materiales, reflexionarán sobre sus cualidades, su valor y la importancia de su autocuidado propio y personal. | O46: Única | P46: 46137 | Q46: 46137 | R46: 1 | S46: Artes visuales | T46: Dibujo | U46: Taller | V46: Ninguna | W46: Presencial | X46: Espacio a Cargo de la Secretaría | Y46: 2 | AB46: FALSE | AD46: FALSE | AF46: FALSE | AH46: Sin costo | AL46: ccardonav@guanajuato.gob.mx | AM46: Arraigo y empoderamiento cultural de comunidades. | AN46: 2 Igualdad | AO46: 2.4 Reducir brechas de desigualdad | AP46: 2.4.3 Descentralización de la oferta cultural | AQ46: 2.4.3.1 Impulsar el desarrollo artístico y cultural entre infancias y juventudes | AR46: Cooperación | AT46: Fortalecimiento de la participación ciudadana y la mediación cultural | AU46: Impulso a la ampliación de la oferta cultural en los territorios. | AV46: Fortalecer la programación cultural en espacios públicos, espacios alternativos y otros espacios culturales. | AW46: Incrementar en 25% la oferta cultural realizada en los municipios. | AX46: Taller | AY46: Formación | AZ46: Formación | BC46: 0 | BF46: FALSE | BM46: No | BQ46: Abierta | BR46: =VLOOKUP(BQ46, Cat_Indicadores!B:C, 2, FALSE) -> #N/A | BS46: #ERROR!
A47: ACT-SCWL91147 | B47: SC-260618-153933 | C47: 46191.652 | D47: 92 | E47: PB3572 | F47: Gestión de programas de exposiciones, actividades formativas y académicas en los Museos de la Secretaría de Cultura y actividades extramuros | G47: Creación y participación en actividades formativas y académicas de los museos adscritos a la Secretaria de Cultura | H47: SUBSECRETARÍA DE DESARROLLO Y PROMOCIÓN ARTÍSTICA Y CULTURAL | I47: DIRECCIÓN GENERAL DE MUSEOS, ARTES VISUALES Y EXPOSICIONES | J47: Número de Actividades realizadas | K47: 800 | L47: Artística | M47: Cine para niños y niñas | N47: Presentación de cortometrajes en torno al Día del niño y la niña | O47: Única | P47: 46138 | Q47: 46138 | R47: 1 | S47: Cinematografía y medios audiovisuales | T47: Cine | U47: Muestra artística | V47: Ninguna | W47: Presencial | X47: Espacio a Cargo de la Secretaría | Y47: 6 | AB47: FALSE | AD47: FALSE | AF47: FALSE | AH47: Sin costo | AL47: ccardonav@guanajuato.gob.mx | AM47: Arraigo y empoderamiento cultural de comunidades. | AN47: 2 Igualdad | AO47: 2.4 Reducir brechas de desigualdad | AP47: 2.4.3 Descentralización de la oferta cultural | AQ47: 2.4.3.1 Impulsar el desarrollo artístico y cultural entre infancias y juventudes | AR47: Cooperación | AT47: Fortalecimiento de la participación ciudadana y la mediación cultural | AU47: Impulso a la ampliación de la oferta cultural en los territorios. | AV47: Fortalecer la programación cultural en espacios públicos, espacios alternativos y otros espacios culturales. | AW47: Incrementar en 25% la oferta cultural realizada en los municipios. | AX47: Muestra artística | AY47: Formación | AZ47: Formación | BC47: 0 | BF47: FALSE | BM47: No | BQ47: Abierta | BR47: =VLOOKUP(BQ47, Cat_Indicadores!B:C, 2, FALSE) -> #N/A | BS47: #ERROR!
A48: ACT-SCFA11501 | B48: SC-260618-155005 | C48: 46191.66 | D48: 92 | E48: PB3572 | F48: Gestión de programas de exposiciones, actividades formativas y académicas en los Museos de la Secretaría de Cultura y actividades extramuros | G48: Creación y participación en actividades formativas y académicas de los museos adscritos a la Secretaria de Cultura | H48: SUBSECRETARÍA DE DESARROLLO Y PROMOCIÓN ARTÍSTICA Y CULTURAL | I48: DIRECCIÓN GENERAL DE MUSEOS, ARTES VISUALES Y EXPOSICIONES | J48: Número de Actividades realizadas | K48: 800 | L48: Artística | M48: Recital infantil | N48: Concierto dirigido a niñas y niños a cargo de alumnos de la Sección infantil y Nivel medio básico del Departamento de Música de la Universidad de Guanajuato. | O48: Única | P48: 46140 | Q48: 46140 | R48: 1 | S48: Música | T48: Música académica | U48: Presentación artística | V48: Ninguna | W48: Presencial | X48: Espacio a Cargo de la Secretaría | Y48: 5 | AB48: FALSE | AD48: FALSE | AF48: FALSE | AH48: Sin costo | AL48: ccardonav@guanajuato.gob.mx | AM48: Arraigo y empoderamiento cultural de comunidades. | AN48: 2 Igualdad | AO48: 2.4 Reducir brechas de desigualdad | AP48: 2.4.3 Descentralización de la oferta cultural | AQ48: 2.4.3.1 Impulsar el desarrollo artístico y cultural entre infancias y juventudes | AR48: Cooperación | AT48: Fortalecimiento de la participación ciudadana y la mediación cultural | AU48: Impulso a la ampliación de la oferta cultural en los territorios. | AV48: Fortalecer la programación cultural en espacios públicos, espacios alternativos y otros espacios culturales. | AW48: Incrementar en 25% la oferta cultural realizada en los municipios. | AX48: Presentación artística | AY48: Formación | AZ48: Formación | BC48: 0 | BF48: FALSE | BM48: No | BQ48: Abierta | BR48: =VLOOKUP(BQ48, Cat_Indicadores!B:C, 2, FALSE) -> #N/A | BS48: #ERROR!
A49: ACT-SCSV85618 | B49: SC-260618-161122 | C49: 46191.675 | D49: 92 | E49: PB3572 | F49: Gestión de programas de exposiciones, actividades formativas y académicas en los Museos de la Secretaría de Cultura y actividades extramuros | G49: Creación y participación en actividades formativas y académicas de los museos adscritos a la Secretaria de Cultura | H49: SUBSECRETARÍA DE DESARROLLO Y PROMOCIÓN ARTÍSTICA Y CULTURAL | I49: DIRECCIÓN GENERAL DE MUSEOS, ARTES VISUALES Y EXPOSICIONES | J49: Número de Actividades realizadas | K49: 800 | L49: Artística | M49: Clap, clap, clap, al compás del Museo. Presentación de Danza | N49: Celebración del Día Internacional de la Danza En colaboración con la Licenciatura en Artes Escénicas de la Universidad de Guanajuato se llevará a cabo un recorrido por los Museos de Guanajuato, con presentaciones de danza a cargo de las y los estudiantes, al finalizar se llevará a cabo una conferencia en torno a esta corriente artística. | O49: Única | P49: 46141 | Q49: 46141 | R49: 1 | S49: Artes escénicas | T49: Danza contemporánea | U49: Presentación artística | V49: Ninguna | W49: Presencial | X49: Espacio a Cargo de la Secretaría | Y49: 5 | AB49: FALSE | AD49: FALSE | AF49: FALSE | AH49: Sin costo | AL49: ccardonav@guanajuato.gob.mx | AM49: Arraigo y empoderamiento cultural de comunidades. | AN49: 1 Tranquilidad | AO49: 1.2 Fortalecer prevención del delito | AP49: 1.2.2 Fortalecimiento del tejido social | AQ49: 1.2.3.4 Promover una cultura de paz desde las expresiones artísticas y culturales | AR49: Cooperación | AT49: Fortalecimiento de la participación ciudadana y la mediación cultural | AU49: Impulso a la ampliación de la oferta cultural en los territorios. | AV49: Fortalecer la programación cultural en espacios públicos, espacios alternativos y otros espacios culturales. | AW49: Incrementar en 25% la oferta cultural realizada en los municipios. | AX49: Presentación artística | AY49: Formación | AZ49: Formación | BC49: 0 | BF49: FALSE | BL49: Vinculacion | BM49: Sí | BQ49: Abierta | BR49: =VLOOKUP(BQ49, Cat_Indicadores!B:C, 2, FALSE) -> #N/A | BS49: #ERROR!
A50: ACT-SCQV21814 | B50: SC-260619-101209 | C50: 46192.425 | D50: 92 | E50: PB3572 | F50: Gestión de programas de exposiciones, actividades formativas y académicas en los Museos de la Secretaría de Cultura y actividades extramuros | G50: Creación y participación en actividades formativas y académicas de los museos adscritos a la Secretaria de Cultura | H50: SUBSECRETARÍA DE DESARROLLO Y PROMOCIÓN ARTÍSTICA Y CULTURAL | I50: DIRECCIÓN GENERAL DE MUSEOS, ARTES VISUALES Y EXPOSICIONES | J50: Número de Actividades realizadas | K50: 800 | L50: Artística | M50: Clap, clap, clap, al compás del Museo. Presentación de Danza | N50: Celebración del Día Internacional de la Danza | O50: Única | P50: 46141 | Q50: 46141 | R50: 1 | S50: Artes escénicas | T50: Danza contemporánea | U50: Presentación artística | V50: Ninguna | W50: Presencial | X50: Espacio a Cargo de la Secretaría | Y50: 4 | AB50: FALSE | AD50: FALSE | AF50: FALSE | AH50: Sin costo | AL50: ccardonav@guanajuato.gob.mx | AM50: Arraigo y empoderamiento cultural de comunidades. | AN50: 1 Tranquilidad | AO50: 1.2 Fortalecer prevención del delito | AP50: 1.2.2 Fortalecimiento del tejido social | AQ50: 1.2.3.4 Promover una cultura de paz desde las expresiones artísticas y culturales | AR50: Cooperación | AT50: Fortalecimiento de la participación ciudadana y la mediación cultural | AU50: Impulso a la ampliación de la oferta cultural en los territorios. | AV50: Fortalecer la programación cultural en espacios públicos, espacios alternativos y otros espacios culturales. | AW50: Incrementar en 25% la oferta cultural realizada en los municipios. | AX50: Presentación artística | AY50: Formación | AZ50: Formación | BC50: 0 | BF50: FALSE | BM50: No | BQ50: Abierta | BR50: =VLOOKUP(BQ50, Cat_Indicadores!B:C, 2, FALSE) -> #N/A | BS50: #ERROR!
A51: ACT-SCVO74171 | B51: SC-260619-103127 | C51: 46192.439 | D51: 92 | E51: PB3572 | F51: Gestión de programas de exposiciones, actividades formativas y académicas en los Museos de la Secretaría de Cultura y actividades extramuros | G51: Creación y participación en actividades formativas y académicas de los museos adscritos a la Secretaria de Cultura | H51: SUBSECRETARÍA DE DESARROLLO Y PROMOCIÓN ARTÍSTICA Y CULTURAL | I51: DIRECCIÓN GENERAL DE MUSEOS, ARTES VISUALES Y EXPOSICIONES | J51: Número de Actividades realizadas | K51: 800 | L51: Artística | M51: Clap, clap, clap, al compás del Museo. Conferencia | N51: Celebración del Día Internacional de la Danza En colaboración con la Licenciatura en Artes Escénicas de la Universidad de Guanajuato se llevará a cabo un recorrido por los Museos de Guanajuato, con presentaciones de danza a cargo de las y los estudiantes, al finalizar se llevará a cabo una conferencia en torno a esta corriente artística. | O51: Única | P51: 46141 | Q51: 46141 | R51: 1 | S51: Artes escénicas | T51: Danza contemporánea | U51: Presentación artística | V51: Ninguna | W51: Presencial | X51: Espacio a Cargo de la Secretaría | Y51: 2 | AB51: FALSE | AD51: FALSE | AF51: FALSE | AH51: Sin costo | AL51: ccardonav@guanajuato.gob.mx | AM51: Arraigo y empoderamiento cultural de comunidades. | AN51: 1 Tranquilidad | AO51: 1.2 Fortalecer prevención del delito | AP51: 1.2.2 Fortalecimiento del tejido social | AQ51: 1.2.3.4 Promover una cultura de paz desde las expresiones artísticas y culturales | AR51: Cooperación | AT51: Fortalecimiento de la participación ciudadana y la mediación cultural | AU51: Impulso a la ampliación de la oferta cultural en los territorios. | AV51: Fortalecer la programación cultural en espacios públicos, espacios alternativos y otros espacios culturales. | AW51: Incrementar en 25% la oferta cultural realizada en los municipios. | AX51: Presentación artística | AY51: Formación | AZ51: Formación | BC51: 0 | BF51: FALSE | BL51: Vinculacion | BM51: Sí | BQ51: Abierta | BR51: =VLOOKUP(BQ51, Cat_Indicadores!B:C, 2, FALSE) -> #N/A | BS51: #ERROR!
A52: ACT-SCUZ80082 | B52: SC-260619-103736 | C52: 46192.443 | D52: 92 | E52: PB3572 | F52: Gestión de programas de exposiciones, actividades formativas y académicas en los Museos de la Secretaría de Cultura y actividades extramuros | G52: Creación y participación en actividades formativas y académicas de los museos adscritos a la Secretaria de Cultura | H52: SUBSECRETARÍA DE DESARROLLO Y PROMOCIÓN ARTÍSTICA Y CULTURAL | I52: DIRECCIÓN GENERAL DE MUSEOS, ARTES VISUALES Y EXPOSICIONES | J52: Número de Actividades realizadas | K52: 800 | L52: Artística | M52: Inauguración de la exposición: Manuel Álvarez Bravo, los años decisivos | N52: Manuel Álvarez Bravo (CDMX, 1902-2002), uno de los fundadores de la fotografía moderna mundial, es considerado de los máximos representantes de la fotografía latinoamericana del siglo XX. | O52: Única | P52: 46142 | Q52: 46142 | R52: 1 | S52: Artes visuales | T52: Fotografía | U52: Exposición | V52: Ninguna | W52: Presencial | X52: Espacio a Cargo de la Secretaría | Y52: 6 | AB52: FALSE | AD52: TRUE | AE52: 1 | AF52: FALSE | AH52: Sin costo | AL52: ccardonav@guanajuato.gob.mx | AM52: Creación de la Secretaría de Cultura, con una visión social de la política cultural. | AN52: 1 Tranquilidad | AO52: 1.2 Fortalecer prevención del delito | AP52: 1.2.2 Fortalecimiento del tejido social | AQ52: 1.2.3.4 Promover una cultura de paz desde las expresiones artísticas y culturales | AR52: Cooperación | AT52: Fortalecimiento de la participación ciudadana y la mediación cultural | AU52: Impulso a la ampliación de la oferta cultural en los territorios. | AV52: Fortalecer la programación cultural en espacios públicos, espacios alternativos y otros espacios culturales. | AW52: Incrementar en 25% la oferta cultural realizada en los municipios. | AX52: Exposición | AY52: Formación | AZ52: Formación | BC52: 0 | BF52: FALSE | BM52: No | BQ52: Abierta | BR52: =VLOOKUP(BQ52, Cat_Indicadores!B:C, 2, FALSE) -> #N/A | BS52: #ERROR!
A53: ACT-SCRE54917 | B53: SC-260619-110512 | C53: 46192.462 | D53: 92 | E53: PB3572 | F53: Gestión de programas de exposiciones, actividades formativas y académicas en los Museos de la Secretaría de Cultura y actividades extramuros | G53: Creación y participación en actividades formativas y académicas de los museos adscritos a la Secretaria de Cultura | H53: SUBSECRETARÍA DE DESARROLLO Y PROMOCIÓN ARTÍSTICA Y CULTURAL | I53: DIRECCIÓN GENERAL DE MUSEOS, ARTES VISUALES Y EXPOSICIONES | J53: Número de Actividades realizadas | K53: 800 | L53: Artística | M53: Visita guiada libre | N53: Recorrido guiado por el museo | O53: Única | P53: 46119 | Q53: 46119 | R53: 1 | S53: Cultura comunitaria | T53: Formación comunitaria | U53: Visitas guiadas | V53: Ninguna | W53: Presencial | X53: Espacio a Cargo de la Secretaría | Y53: 1 | AB53: FALSE | AD53: FALSE | AF53: FALSE | AH53: Sin costo | AL53: ccardonav@guanajuato.gob.mx | AM53: Arraigo y empoderamiento cultural de comunidades. | AN53: 1 Tranquilidad | AO53: 1.2 Fortalecer prevención del delito | AP53: 1.2.2 Fortalecimiento del tejido social | AQ53: 1.2.3.4 Promover una cultura de paz desde las expresiones artísticas y culturales | AR53: Cooperación | AT53: Fortalecimiento de la participación ciudadana y la mediación cultural | AU53: Impulso a la ampliación de la oferta cultural en los territorios. | AV53: Fortalecer la programación cultural en espacios públicos, espacios alternativos y otros espacios culturales. | AW53: Incrementar en 25% la oferta cultural realizada en los municipios. | AX53: Visitas guiadas | AY53: Formación | AZ53: Formación | BC53: 0 | BF53: FALSE | BM53: No | BQ53: Abierta | BR53: =VLOOKUP(BQ53, Cat_Indicadores!B:C, 2, FALSE) -> #N/A | BS53: #ERROR!
A54: ACT-SCJS28324 | B54: SC-260619-111135 | C54: 46192.466 | D54: 92 | E54: PB3572 | F54: Gestión de programas de exposiciones, actividades formativas y académicas en los Museos de la Secretaría de Cultura y actividades extramuros | G54: Creación y participación en actividades formativas y académicas de los museos adscritos a la Secretaria de Cultura | H54: SUBSECRETARÍA DE DESARROLLO Y PROMOCIÓN ARTÍSTICA Y CULTURAL | I54: DIRECCIÓN GENERAL DE MUSEOS, ARTES VISUALES Y EXPOSICIONES | J54: Número de Actividades realizadas | K54: 800 | L54: Artística | M54: Visita guiada libre | N54: Recorrido guiado por el museo | O54: Única | P54: 46121 | Q54: 46121 | R54: 1 | S54: Cultura comunitaria | T54: Formación comunitaria | U54: Visitas guiadas | V54: Ninguna | W54: Presencial | X54: Espacio a Cargo de la Secretaría | Y54: 1 | AB54: FALSE | AD54: FALSE | AF54: FALSE | AH54: Sin costo | AL54: ccardonav@guanajuato.gob.mx | AM54: Arraigo y empoderamiento cultural de comunidades. | AN54: 1 Tranquilidad | AO54: 1.2 Fortalecer prevención del delito | AP54: 1.2.2 Fortalecimiento del tejido social | AQ54: 1.2.3.4 Promover una cultura de paz desde las expresiones artísticas y culturales | AR54: Cooperación | AT54: Fortalecimiento de la participación ciudadana y la mediación cultural | AU54: Impulso a la ampliación de la oferta cultural en los territorios. | AV54: Fortalecer la programación cultural en espacios públicos, espacios alternativos y otros espacios culturales. | AW54: Incrementar en 25% la oferta cultural realizada en los municipios. | AX54: Visitas guiadas | AY54: Formación | AZ54: Formación | BC54: 0 | BF54: FALSE | BM54: No | BQ54: Abierta | BR54: =VLOOKUP(BQ54, Cat_Indicadores!B:C, 2, FALSE) -> #N/A | BS54: #ERROR!
A55: ACT-SCQW88822 | B55: SC-260619-114120 | C55: 46192.487 | D55: 92 | E55: PB3572 | F55: Gestión de programas de exposiciones, actividades formativas y académicas en los Museos de la Secretaría de Cultura y actividades extramuros | G55: Creación y participación en actividades formativas y académicas de los museos adscritos a la Secretaria de Cultura | H55: SUBSECRETARÍA DE DESARROLLO Y PROMOCIÓN ARTÍSTICA Y CULTURAL | I55: DIRECCIÓN GENERAL DE MUSEOS, ARTES VISUALES Y EXPOSICIONES | J55: Número de Actividades realizadas | K55: 800 | L55: Artística | M55: Visita guiada libre | N55: Recorrido guiado por el museo | O55: Única | P55: 46122 | Q55: 46122 | R55: 1 | S55: Cultura comunitaria | T55: Formación comunitaria | U55: Visitas guiadas | V55: Ninguna | W55: Presencial | X55: Espacio a Cargo de la Secretaría | Y55: 1 | AB55: FALSE | AD55: FALSE | AF55: FALSE | AH55: Sin costo | AL55: ccardonav@guanajuato.gob.mx | AM55: Arraigo y empoderamiento cultural de comunidades. | AN55: 2 Igualdad | AO55: 2.1 Protección de derechos humanos | AP55: 2.1.3 Inclusión de personas con discapacidad | AQ55: 2.1.3.2 Coordinar la incorporación progresiva de la accesibilidad universal | AR55: Cooperación | AT55: Fortalecimiento de la participación ciudadana y la mediación cultural | AU55: Impulso a la ampliación de la oferta cultural en los territorios. | AV55: Fortalecer la programación cultural en espacios públicos, espacios alternativos y otros espacios culturales. | AW55: Incrementar en 25% la oferta cultural realizada en los municipios. | AX55: Visitas guiadas | AY55: Formación | AZ55: Formación | BC55: 0 | BF55: FALSE | BM55: No | BQ55: Abierta | BR55: =VLOOKUP(BQ55, Cat_Indicadores!B:C, 2, FALSE) -> #N/A | BS55: #ERROR!
A56: ACT-SCGF02574 | B56: SC-260619-114648 | C56: 46192.491 | D56: 92 | E56: PB3572 | F56: Gestión de programas de exposiciones, actividades formativas y académicas en los Museos de la Secretaría de Cultura y actividades extramuros | G56: Creación y participación en actividades formativas y académicas de los museos adscritos a la Secretaria de Cultura | H56: SUBSECRETARÍA DE DESARROLLO Y PROMOCIÓN ARTÍSTICA Y CULTURAL | I56: DIRECCIÓN GENERAL DE MUSEOS, ARTES VISUALES Y EXPOSICIONES | J56: Número de Actividades realizadas | K56: 800 | L56: Artística | M56: Visita guiada libre | N56: Recorrido guiado por el museo | O56: Única | P56: 46134 | Q56: 46134 | R56: 1 | S56: Cultura comunitaria | T56: Formación comunitaria | U56: Visitas guiadas | V56: Ninguna | W56: Presencial | X56: Espacio a Cargo de la Secretaría | Y56: 1 | AB56: FALSE | AD56: FALSE | AF56: FALSE | AH56: Sin costo | AL56: ccardonav@guanajuato.gob.mx | AM56: Arraigo y empoderamiento cultural de comunidades. | AN56: 2 Igualdad | AO56: 2.1 Protección de derechos humanos | AP56: 2.1.3 Inclusión de personas con discapacidad | AQ56: 2.1.3.2 Coordinar la incorporación progresiva de la accesibilidad universal | AR56: Cooperación | AT56: Fortalecimiento de la participación ciudadana y la mediación cultural | AU56: Impulso a la ampliación de la oferta cultural en los territorios. | AV56: Fortalecer la programación cultural en espacios públicos, espacios alternativos y otros espacios culturales. | AW56: Incrementar en 25% la oferta cultural realizada en los municipios. | AX56: Visitas guiadas | AY56: Formación | AZ56: Formación | BC56: 0 | BF56: FALSE | BM56: No | BQ56: Abierta | BR56: =VLOOKUP(BQ56, Cat_Indicadores!B:C, 2, FALSE) -> #N/A | BS56: #ERROR!
A57: ACT-SCDO56831 | B57: SC-260619-115047 | C57: 46192.494 | D57: 92 | E57: PB3572 | F57: Gestión de programas de exposiciones, actividades formativas y académicas en los Museos de la Secretaría de Cultura y actividades extramuros | G57: Creación y participación en actividades formativas y académicas de los museos adscritos a la Secretaria de Cultura | H57: SUBSECRETARÍA DE DESARROLLO Y PROMOCIÓN ARTÍSTICA Y CULTURAL | I57: DIRECCIÓN GENERAL DE MUSEOS, ARTES VISUALES Y EXPOSICIONES | J57: Número de Actividades realizadas | K57: 800 | L57: Artística | M57: Visita guiada libre | N57: Recorrido guiado por el museo | O57: Única | P57: 46134 | Q57: 46134 | R57: 1 | S57: Cultura comunitaria | T57: Formación comunitaria | U57: Visitas guiadas | V57: Ninguna | W57: Presencial | X57: Espacio a Cargo de la Secretaría | Y57: 1 | AB57: FALSE | AD57: FALSE | AF57: FALSE | AH57: Sin costo | AL57: ccardonav@guanajuato.gob.mx | AM57: Arraigo y empoderamiento cultural de comunidades. | AN57: 2 Igualdad | AO57: 2.1 Protección de derechos humanos | AP57: 2.1.3 Inclusión de personas con discapacidad | AQ57: 2.1.3.2 Coordinar la incorporación progresiva de la accesibilidad universal | AR57: Cooperación | AT57: Fortalecimiento de la participación ciudadana y la mediación cultural | AU57: Impulso a la ampliación de la oferta cultural en los territorios. | AV57: Fortalecer la programación cultural en espacios públicos, espacios alternativos y otros espacios culturales. | AW57: Incrementar en 25% la oferta cultural realizada en los municipios. | AX57: Visitas guiadas | AY57: Formación | AZ57: Formación | BC57: 0 | BF57: FALSE | BM57: No | BQ57: Abierta | BR57: =VLOOKUP(BQ57, Cat_Indicadores!B:C, 2, FALSE) -> #N/A | BS57: #ERROR!
A58: ACT-SCID52619 | B58: SC-260619-115439 | C58: 46192.496 | D58: 92 | E58: PB3572 | F58: Gestión de programas de exposiciones, actividades formativas y académicas en los Museos de la Secretaría de Cultura y actividades extramuros | G58: Creación y participación en actividades formativas y académicas de los museos adscritos a la Secretaria de Cultura | H58: SUBSECRETARÍA DE DESARROLLO Y PROMOCIÓN ARTÍSTICA Y CULTURAL | I58: DIRECCIÓN GENERAL DE MUSEOS, ARTES VISUALES Y EXPOSICIONES | J58: Número de Actividades realizadas | K58: 800 | L58: Artística | M58: Visita guiada libre | N58: Recorrido guiado por el museo | O58: Única | P58: 46138 | Q58: 46138 | R58: 1 | S58: Cultura comunitaria | T58: Formación comunitaria | U58: Visitas guiadas | V58: Ninguna | W58: Presencial | X58: Espacio a Cargo de la Secretaría | Y58: 1 | AB58: FALSE | AD58: FALSE | AF58: FALSE | AH58: Sin costo | AL58: ccardonav@guanajuato.gob.mx | AM58: Arraigo y empoderamiento cultural de comunidades. | AN58: 2 Igualdad | AO58: 2.1 Protección de derechos humanos | AP58: 2.1.3 Inclusión de personas con discapacidad | AQ58: 2.1.3.2 Coordinar la incorporación progresiva de la accesibilidad universal | AR58: Cooperación | AT58: Fortalecimiento de la participación ciudadana y la mediación cultural | AU58: Impulso a la ampliación de la oferta cultural en los territorios. | AV58: Fortalecer la programación cultural en espacios públicos, espacios alternativos y otros espacios culturales. | AW58: Incrementar en 25% la oferta cultural realizada en los municipios. | AX58: Visitas guiadas | AY58: Formación | AZ58: Formación | BC58: 0 | BF58: FALSE | BM58: No | BQ58: Abierta | BR58: =VLOOKUP(BQ58, Cat_Indicadores!B:C, 2, FALSE) -> #N/A | BS58: #ERROR!
A59: ACT-SCFY90265 | B59: SC-260619-115815 | C59: 46192.499 | D59: 92 | E59: PB3572 | F59: Gestión de programas de exposiciones, actividades formativas y académicas en los Museos de la Secretaría de Cultura y actividades extramuros | G59: Creación y participación en actividades formativas y académicas de los museos adscritos a la Secretaria de Cultura | H59: SUBSECRETARÍA DE DESARROLLO Y PROMOCIÓN ARTÍSTICA Y CULTURAL | I59: DIRECCIÓN GENERAL DE MUSEOS, ARTES VISUALES Y EXPOSICIONES | J59: Número de Actividades realizadas | K59: 800 | L59: Artística | M59: Visita guiada libre | N59: Recorrido guiado por el museo | O59: Única | P59: 46140 | Q59: 46140 | R59: 1 | S59: Cultura comunitaria | T59: Formación comunitaria | U59: Visitas guiadas | V59: Ninguna | W59: Presencial | X59: Espacio a Cargo de la Secretaría | Y59: 1 | AB59: FALSE | AD59: FALSE | AF59: FALSE | AH59: Sin costo | AL59: ccardonav@guanajuato.gob.mx | AM59: Arraigo y empoderamiento cultural de comunidades. | AN59: 2 Igualdad | AO59: 2.1 Protección de derechos humanos | AP59: 2.1.3 Inclusión de personas con discapacidad | AQ59: 2.1.3.2 Coordinar la incorporación progresiva de la accesibilidad universal | AR59: Cooperación | AT59: Fortalecimiento de la participación ciudadana y la mediación cultural | AU59: Impulso a la ampliación de la oferta cultural en los territorios. | AV59: Fortalecer la programación cultural en espacios públicos, espacios alternativos y otros espacios culturales. | AW59: Incrementar en 25% la oferta cultural realizada en los municipios. | AX59: Visitas guiadas | AY59: Formación | AZ59: Formación | BC59: 0 | BF59: FALSE | BM59: No | BQ59: Abierta | BR59: =VLOOKUP(BQ59, Cat_Indicadores!B:C, 2, FALSE) -> #N/A | BS59: #ERROR!
A60: ACT-SCRR27760 | B60: SC-260619-120149 | C60: 46192.501 | D60: 92 | E60: PB3572 | F60: Gestión de programas de exposiciones, actividades formativas y académicas en los Museos de la Secretaría de Cultura y actividades extramuros | G60: Creación y participación en actividades formativas y académicas de los museos adscritos a la Secretaria de Cultura | H60: SUBSECRETARÍA DE DESARROLLO Y PROMOCIÓN ARTÍSTICA Y CULTURAL | I60: DIRECCIÓN GENERAL DE MUSEOS, ARTES VISUALES Y EXPOSICIONES | J60: Número de Actividades realizadas | K60: 800 | L60: Artística | M60: Visita guiada libre | N60: Recorrido guiado por el museo | O60: Única | P60: 46140 | Q60: 46140 | R60: 1 | S60: Cultura comunitaria | T60: Formación comunitaria | U60: Visitas guiadas | V60: Ninguna | W60: Presencial | X60: Espacio a Cargo de la Secretaría | Y60: 1 | AB60: FALSE | AD60: FALSE | AF60: FALSE | AH60: Sin costo | AL60: ccardonav@guanajuato.gob.mx | AM60: Arraigo y empoderamiento cultural de comunidades. | AN60: 2 Igualdad | AO60: 2.1 Protección de derechos humanos | AP60: 2.1.3 Inclusión de personas con discapacidad | AQ60: 2.1.3.2 Coordinar la incorporación progresiva de la accesibilidad universal | AR60: Cooperación | AT60: Fortalecimiento de la participación ciudadana y la mediación cultural | AU60: Impulso a la ampliación de la oferta cultural en los territorios. | AV60: Fortalecer la programación cultural en espacios públicos, espacios alternativos y otros espacios culturales. | AW60: Incrementar en 25% la oferta cultural realizada en los municipios. | AX60: Visitas guiadas | AY60: Formación | AZ60: Formación | BC60: 0 | BF60: FALSE | BM60: No | BQ60: Abierta | BR60: =VLOOKUP(BQ60, Cat_Indicadores!B:C, 2, FALSE) -> #N/A | BS60: #ERROR!
A61: ACT-SCAF80267 | B61: SC-260619-120509 | C61: 46192.504 | D61: 92 | E61: PB3572 | F61: Gestión de programas de exposiciones, actividades formativas y académicas en los Museos de la Secretaría de Cultura y actividades extramuros | G61: Creación y participación en actividades formativas y académicas de los museos adscritos a la Secretaria de Cultura | H61: SUBSECRETARÍA DE DESARROLLO Y PROMOCIÓN ARTÍSTICA Y CULTURAL | I61: DIRECCIÓN GENERAL DE MUSEOS, ARTES VISUALES Y EXPOSICIONES | J61: Número de Actividades realizadas | K61: 800 | L61: Artística | M61: Visita guiada UVEG Telebachillerato Comunitario León Ramillete | N61: Recorrido guiado por el museo | O61: Única | P61: 46142 | Q61: 46142 | R61: 1 | S61: Cultura comunitaria | T61: Formación comunitaria | U61: Visitas guiadas | V61: Ninguna | W61: Presencial | X61: Espacio a Cargo de la Secretaría | Y61: 5 | AB61: FALSE | AD61: FALSE | AF61: FALSE | AH61: Sin costo | AL61: ccardonav@guanajuato.gob.mx | AM61: Arraigo y empoderamiento cultural de comunidades. | AN61: 2 Igualdad | AO61: 2.1 Protección de derechos humanos | AP61: 2.1.3 Inclusión de personas con discapacidad | AQ61: 2.1.3.2 Coordinar la incorporación progresiva de la accesibilidad universal | AR61: Cooperación | AT61: Fortalecimiento de la participación ciudadana y la mediación cultural | AU61: Impulso a la ampliación de la oferta cultural en los territorios. | AV61: Fortalecer la programación cultural en espacios públicos, espacios alternativos y otros espacios culturales. | AW61: Incrementar en 25% la oferta cultural realizada en los municipios. | AX61: Visitas escolares | AY61: Formación | AZ61: Formación | BC61: 0 | BF61: FALSE | BM61: No | BQ61: Abierta | BR61: =VLOOKUP(BQ61, Cat_Indicadores!B:C, 2, FALSE) -> #N/A | BS61: #ERROR!
A62: ACT-SCCR74811 | B62: SC-260619-122603 | C62: 46192.518 | D62: 92 | E62: PB3572 | F62: Gestión de programas de exposiciones, actividades formativas y académicas en los Museos de la Secretaría de Cultura y actividades extramuros | G62: Creación y participación en actividades formativas y académicas de los museos adscritos a la Secretaria de Cultura | H62: SUBSECRETARÍA DE DESARROLLO Y PROMOCIÓN ARTÍSTICA Y CULTURAL | I62: DIRECCIÓN GENERAL DE MUSEOS, ARTES VISUALES Y EXPOSICIONES | J62: Número de Actividades realizadas | K62: 800 | L62: Artística | M62: Visita guiada Instituto Tecnológico Superior de Irapuato | N62: Recorrido guiado por el museo | O62: Única | P62: 46130 | Q62: 46130 | R62: 1 | S62: Cultura comunitaria | T62: Formación comunitaria | U62: Visitas escolares | V62: Ninguna | W62: Presencial | X62: Espacio a Cargo de la Secretaría | Y62: 5 | AB62: FALSE | AD62: FALSE | AF62: FALSE | AH62: Sin costo | AL62: ccardonav@guanajuato.gob.mx | AM62: Arraigo y empoderamiento cultural de comunidades. | AN62: 2 Igualdad | AO62: 2.1 Protección de derechos humanos | AP62: 2.1.3 Inclusión de personas con discapacidad | AQ62: 2.1.3.2 Coordinar la incorporación progresiva de la accesibilidad universal | AR62: Cooperación | AT62: Fortalecimiento de la participación ciudadana y la mediación cultural | AU62: Impulso a la ampliación de la oferta cultural en los territorios. | AV62: Fortalecer la programación cultural en espacios públicos, espacios alternativos y otros espacios culturales. | AW62: Incrementar en 25% la oferta cultural realizada en los municipios. | AX62: Visitas escolares | AY62: Formación | AZ62: Formación | BC62: 0 | BF62: FALSE | BM62: No | BQ62: Abierta | BR62: =VLOOKUP(BQ62, Cat_Indicadores!B:C, 2, FALSE) -> #N/A | BS62: #ERROR!
A63: ACT-SCFB28687 | B63: SC-260619-124027 | C63: 46192.528 | D63: 92 | E63: PB3572 | F63: Gestión de programas de exposiciones, actividades formativas y académicas en los Museos de la Secretaría de Cultura y actividades extramuros | G63: Creación y participación en actividades formativas y académicas de los museos adscritos a la Secretaria de Cultura | H63: SUBSECRETARÍA DE DESARROLLO Y PROMOCIÓN ARTÍSTICA Y CULTURAL | I63: DIRECCIÓN GENERAL DE MUSEOS, ARTES VISUALES Y EXPOSICIONES | J63: Número de Actividades realizadas | K63: 800 | L63: Artística | M63: Visita guiada Universidad de Guanajuato (Facultad de Arquitectura) | N63: Recorrido guiado por el museo | O63: Única | P63: 46140 | Q63: 46140 | R63: 1 | S63: Cultura comunitaria | T63: Formación comunitaria | U63: Visitas guiadas | V63: Ninguna | W63: Presencial | X63: Espacio a Cargo de la Secretaría | Y63: 5 | AB63: FALSE | AD63: FALSE | AF63: FALSE | AH63: Sin costo | AL63: ccardonav@guanajuato.gob.mx | AM63: Arraigo y empoderamiento cultural de comunidades. | AN63: 2 Igualdad | AO63: 2.1 Protección de derechos humanos | AP63: 2.1.3 Inclusión de personas con discapacidad | AQ63: 2.1.3.2 Coordinar la incorporación progresiva de la accesibilidad universal | AR63: Cooperación | AT63: Fortalecimiento de la participación ciudadana y la mediación cultural | AU63: Impulso a la ampliación de la oferta cultural en los territorios. | AV63: Fortalecer la programación cultural en espacios públicos, espacios alternativos y otros espacios culturales. | AW63: Incrementar en 25% la oferta cultural realizada en los municipios. | AX63: Visitas escolares | AY63: Formación | AZ63: Formación | BC63: 0 | BF63: FALSE | BM63: No | BQ63: Abierta | BR63: =VLOOKUP(BQ63, Cat_Indicadores!B:C, 2, FALSE) -> #N/A | BS63: #ERROR!
A64: ACT-SCEY53656 | B64: SC-260619-124452 | C64: 46192.531 | D64: 92 | E64: PB3572 | F64: Gestión de programas de exposiciones, actividades formativas y académicas en los Museos de la Secretaría de Cultura y actividades extramuros | G64: Creación y participación en actividades formativas y académicas de los museos adscritos a la Secretaria de Cultura | H64: SUBSECRETARÍA DE DESARROLLO Y PROMOCIÓN ARTÍSTICA Y CULTURAL | I64: DIRECCIÓN GENERAL DE MUSEOS, ARTES VISUALES Y EXPOSICIONES | J64: Número de Actividades realizadas | K64: 800 | L64: Artística | M64: Recorrido guiado por el museo | N64: Recorrido guiado por el museo | O64: Única | P64: 46192 | Q64: 46192 | R64: 1 | S64: Cultura comunitaria | T64: Formación comunitaria | U64: Visitas escolares | V64: Ninguna | W64: Presencial | X64: Espacio a Cargo de la Secretaría | Y64: 2 | AB64: FALSE | AD64: FALSE | AF64: FALSE | AH64: Sin costo | AL64: ccardonav@guanajuato.gob.mx | AM64: Arraigo y empoderamiento cultural de comunidades. | AN64: 2 Igualdad | AO64: 2.1 Protección de derechos humanos | AP64: 2.1.3 Inclusión de personas con discapacidad | AQ64: 2.1.3.2 Coordinar la incorporación progresiva de la accesibilidad universal | AR64: Cooperación | AT64: Fortalecimiento de la participación ciudadana y la mediación cultural | AU64: Impulso a la ampliación de la oferta cultural en los territorios. | AV64: Fortalecer la programación cultural en espacios públicos, espacios alternativos y otros espacios culturales. | AW64: Incrementar en 25% la oferta cultural realizada en los municipios. | AX64: Visitas escolares | AY64: Formación | AZ64: Formación | BC64: 0 | BF64: FALSE | BM64: No | BQ64: Abierta | BR64: =VLOOKUP(BQ64, Cat_Indicadores!B:C, 2, FALSE) -> #N/A | BS64: #ERROR!
... A67: ACT-SCPT13660 | B67: SC-260619-131142 | C67: 46192.55 | D67: 92 | E67: PB3572 | F67: Gestión de programas de exposiciones, actividades formativas y académicas en los Museos de la Secretaría de Cultura y actividades extramuros | G67: Creación y participación en actividades formativas y académicas de los museos adscritos a la Secretaria de Cultura | H67: SUBSECRETARÍA DE DESARROLLO Y PROMOCIÓN ARTÍSTICA Y CULTURAL | I67: DIRECCIÓN GENERAL DE MUSEOS, ARTES VISUALES Y EXPOSICIONES | J67: Número de Actividades realizadas | K67: 800 | L67: Artística | M67: Visita práctica escolar | N67: Recorrido guiado por el museo | O67: Única | P67: 46128 | Q67: 46128 | R67: 1 | S67: Cultura comunitaria | T67: Formación comunitaria | U67: Visitas escolares | V67: Ninguna | W67: Presencial | X67: Espacio a Cargo de la Secretaría | Y67: 6 | AB67: FALSE | AD67: FALSE | AF67: FALSE | AH67: Sin costo | AL67: ccardonav@guanajuato.gob.mx | AM67: Arraigo y empoderamiento cultural de comunidades. | AN67: 2 Igualdad | AO67: 2.1 Protección de derechos humanos | AP67: 2.1.3 Inclusión de personas con discapacidad | AQ67: 2.1.3.2 Coordinar la incorporación progresiva de la accesibilidad universal | AR67: Cooperación | AT67: Fortalecimiento de la participación ciudadana y la mediación cultural | AU67: Impulso a la ampliación de la oferta cultural en los territorios. | AV67: Fortalecer la programación cultural en espacios públicos, espacios alternativos y otros espacios culturales. | AW67: Incrementar en 25% la oferta cultural realizada en los municipios. | AX67: Visitas escolares | AY67: Formación | AZ67: Formación | BC67: 0 | BF67: FALSE | BM67: No | BQ67: Abierta | BR67: =VLOOKUP(BQ67, Cat_Indicadores!B:C, 2, FALSE) -> #N/A | BS67: #ERROR!
A68: ACT-SCJK83217 | B68: SC-260619-141825 | C68: 46192.596 | D68: 92 | E68: PB3572 | F68: Gestión de programas de exposiciones, actividades formativas y académicas en los Museos de la Secretaría de Cultura y actividades extramuros | G68: Creación y participación en actividades formativas y académicas de los museos adscritos a la Secretaria de Cultura | H68: SUBSECRETARÍA DE DESARROLLO Y PROMOCIÓN ARTÍSTICA Y CULTURAL | I68: DIRECCIÓN GENERAL DE MUSEOS, ARTES VISUALES Y EXPOSICIONES | J68: Número de Actividades realizadas | K68: 800 | L68: Artística | M68: Visita práctica escolar | N68: Recorrido guiado por el museo | O68: Única | P68: 46135 | Q68: 46135 | R68: 1 | S68: Cultura comunitaria | T68: Formación comunitaria | U68: Visitas escolares | V68: Ninguna | W68: Presencial | X68: Espacio a Cargo de la Secretaría | Y68: 2 | AB68: FALSE | AD68: FALSE | AF68: FALSE | AH68: Sin costo | AL68: ccardonav@guanajuato.gob.mx | AM68: Arraigo y empoderamiento cultural de comunidades. | AN68: 2 Igualdad | AO68: 2.1 Protección de derechos humanos | AP68: 2.1.3 Inclusión de personas con discapacidad | AQ68: 2.1.3.2 Coordinar la incorporación progresiva de la accesibilidad universal | AR68: Cooperación | AT68: Fortalecimiento de la participación ciudadana y la mediación cultural | AU68: Impulso a la ampliación de la oferta cultural en los territorios. | AV68: Fortalecer la programación cultural en espacios públicos, espacios alternativos y otros espacios culturales. | AW68: Incrementar en 25% la oferta cultural realizada en los municipios. | AX68: Visitas escolares | AY68: Formación | BC68: 0 | BF68: FALSE | BM68: No | BQ68: Abierta | BR68: =VLOOKUP(BQ68, Cat_Indicadores!B:C, 2, FALSE) -> #N/A | BS68: #ERROR!
A69: ACT-SCAP74839 | B69: SC-260619-142402 | C69: 46192.6 | D69: 92 | E69: PB3572 | F69: Gestión de programas de exposiciones, actividades formativas y académicas en los Museos de la Secretaría de Cultura y actividades extramuros | G69: Creación y participación en actividades formativas y académicas de los museos adscritos a la Secretaria de Cultura | H69: SUBSECRETARÍA DE DESARROLLO Y PROMOCIÓN ARTÍSTICA Y CULTURAL | I69: DIRECCIÓN GENERAL DE MUSEOS, ARTES VISUALES Y EXPOSICIONES | J69: Número de Actividades realizadas | K69: 800 | L69: Artística | M69: Joint, Museos+Fanzines | N69: Presentación Editorial de Fanzines y Publicaciones Independientes, resultado del trabajo creativo y técnico de los estudiantes de la Licenciatura en Artes Visuales UG. | O69: Única | P69: 46149 | Q69: 46149 | R69: 1 | S69: Cultura comunitaria | T69: Formación comunitaria | U69: Presentación artística | V69: Ninguna | W69: Presencial | X69: Espacio a Cargo de la Secretaría | Y69: 4 | AB69: FALSE | AD69: FALSE | AF69: FALSE | AH69: Sin costo | AL69: ccardonav@guanajuato.gob.mx | AM69: Arraigo y empoderamiento cultural de comunidades. | AN69: 1 Tranquilidad | AO69: 1.2 Fortalecer prevención del delito | AP69: 1.2.2 Fortalecimiento del tejido social | AQ69: 1.2.3.4 Promover una cultura de paz desde las expresiones artísticas y culturales | AR69: Cooperación | AT69: Fortalecimiento de la participación ciudadana y la mediación cultural | AU69: Impulso a la ampliación de la oferta cultural en los territorios. | AV69: Fortalecer la programación cultural en espacios públicos, espacios alternativos y otros espacios culturales. | AW69: Incrementar en 25% la oferta cultural realizada en los municipios. | AX69: Presentación artística | AY69: Formación | BC69: 0 | BF69: FALSE | BL69: VINCULACIÓN | BM69: Sí | BQ69: Abierta | BR69: =VLOOKUP(BQ69, Cat_Indicadores!B:C, 2, FALSE) -> #N/A | BS69: #ERROR!
A70: ACT-SCZY13401 | B70: SC-260619-145021 | C70: 46192.618 | D70: 92 | E70: PB3572 | F70: Gestión de programas de exposiciones, actividades formativas y académicas en los Museos de la Secretaría de Cultura y actividades extramuros | G70: Creación y participación en actividades formativas y académicas de los museos adscritos a la Secretaria de Cultura | H70: SUBSECRETARÍA DE DESARROLLO Y PROMOCIÓN ARTÍSTICA Y CULTURAL | I70: DIRECCIÓN GENERAL DE MUSEOS, ARTES VISUALES Y EXPOSICIONES | J70: Número de Actividades realizadas | K70: 800 | L70: Artística | M70: Visita escolar Secundaria Benito Juárez | N70: Recorrido guiado por el museo | O70: Única | P70: 46150 | Q70: 46150 | R70: 1 | S70: Cultura comunitaria | T70: Formación comunitaria | U70: Visitas escolares | V70: Ninguna | W70: Presencial | X70: Espacio a Cargo de la Secretaría | Y70: 4 | AB70: FALSE | AD70: FALSE | AF70: FALSE | AH70: Sin costo | AL70: ccardonav@guanajuato.gob.mx | AM70: Arraigo y empoderamiento cultural de comunidades. | AN70: 2 Igualdad | AO70: 2.1 Protección de derechos humanos | AP70: 2.1.3 Inclusión de personas con discapacidad | AQ70: 2.1.3.2 Coordinar la incorporación progresiva de la accesibilidad universal | AR70: Cooperación | AT70: Fortalecimiento de la participación ciudadana y la mediación cultural | AU70: Impulso a la ampliación de la oferta cultural en los territorios. | AV70: Fortalecer la programación cultural en espacios públicos, espacios alternativos y otros espacios culturales. | AW70: Incrementar en 25% la oferta cultural realizada en los municipios. | AX70: Visitas escolares | AY70: Formación | AZ70: Formación | BC70: 0 | BF70: FALSE | BM70: No | BQ70: Abierta | BR70: =VLOOKUP(BQ70, Cat_Indicadores!B:C, 2, FALSE) -> #N/A | BS70: #ERROR!
A71: ACT-SCSH02504 | B71: SC-260619-150004 | C71: 46192.625 | D71: 92 | E71: PB3572 | F71: Gestión de programas de exposiciones, actividades formativas y académicas en los Museos de la Secretaría de Cultura y actividades extramuros | G71: Creación y participación en actividades formativas y académicas de los museos adscritos a la Secretaria de Cultura | H71: SUBSECRETARÍA DE DESARROLLO Y PROMOCIÓN ARTÍSTICA Y CULTURAL | I71: DIRECCIÓN GENERAL DE MUSEOS, ARTES VISUALES Y EXPOSICIONES | J71: Número de Actividades realizadas | K71: 800 | L71: Artística | M71: Taller de lectoescritura: Cada cabeza es un mundo | N71: A partir de la lectura de Persépolis de Marjane Satrapo y Niño Terror: Cómics de miedo para niños punketos a través del cómic y la novela gráfica las y los participantes reconocerán y reflexionarán sobre culturas distintas a las suyas, personajes similares en edades pero con distintos contextos. | O71: Única | P71: 46150 | Q71: 46150 | R71: 1 | S71: Literatura | T71: Fomento a la lectura | U71: Taller | V71: Ninguna | W71: Presencial | X71: Espacio a Cargo de la Secretaría | Y71: 5 | AB71: FALSE | AD71: TRUE | AE71: 1 | AF71: FALSE | AH71: Sin costo | AL71: ccardonav@guanajuato.gob.mx | AM71: Leer para crecer. | AN71: 4 Vocación | AO71: 4.4 Reforzar competencias lectoras y lógico matemáticas | AP71: 4.4.2 Competencias lectoras | AQ71: 4.4.2 Fomentar el hábito lector | AR71: Cooperación | AT71: Fortalecimiento de la participación ciudadana y la mediación cultural | AU71: Impulso a la ampliación de la oferta cultural en los territorios. | AV71: Fortalecer la programación cultural en espacios públicos, espacios alternativos y otros espacios culturales. | AW71: Incrementar en 25% la oferta cultural realizada en los municipios. | AX71: Taller | AY71: Formación | AZ71: Formación | BC71: 0 | BF71: FALSE | BM71: No | BQ71: Abierta | BR71: =VLOOKUP(BQ71, Cat_Indicadores!B:C, 2, FALSE) -> #N/A | BS71: #ERROR!
A72: ACT-SCZG64402 | B72: SC-260619-154616 | C72: 46192.657 | D72: 92 | E72: PB3572 | F72: Gestión de programas de exposiciones, actividades formativas y académicas en los Museos de la Secretaría de Cultura y actividades extramuros | G72: Creación y participación en actividades formativas y académicas de los museos adscritos a la Secretaria de Cultura | H72: SUBSECRETARÍA DE DESARROLLO Y PROMOCIÓN ARTÍSTICA Y CULTURAL | I72: DIRECCIÓN GENERAL DE MUSEOS, ARTES VISUALES Y EXPOSICIONES | J72: Número de Actividades realizadas | K72: 800 | L72: Artística | M72: Visita práctica escolar. Sesión de dibujo UG | N72: Recorrido guiado por el museo | O72: Única | P72: 46156 | Q72: 46156 | R72: 1 | S72: Cultura comunitaria | T72: Formación comunitaria | U72: Visitas escolares | V72: Ninguna | W72: Presencial | X72: Espacio a Cargo de la Secretaría | Y72: 6 | AB72: FALSE | AD72: FALSE | AF72: FALSE | AH72: Sin costo | AL72: ccardonav@guanajuato.gob.mx | AM72: Arraigo y empoderamiento cultural de comunidades. | AN72: 2 Igualdad | AO72: 2.1 Protección de derechos humanos | AP72: 2.1.3 Inclusión de personas con discapacidad | AQ72: 2.1.3.2 Coordinar la incorporación progresiva de la accesibilidad universal | AR72: Cooperación | AT72: Fortalecimiento de la participación ciudadana y la mediación cultural | AU72: Impulso a la ampliación de la oferta cultural en los territorios. | AV72: Fortalecer la programación cultural en espacios públicos, espacios alternativos y otros espacios culturales. | AW72: Incrementar en 25% la oferta cultural realizada en los municipios. | AX72: Visitas escolares | AY72: Formación | AZ72: Formación | BC72: 0 | BF72: FALSE | BM72: No | BQ72: Abierta | BR72: =VLOOKUP(BQ72, Cat_Indicadores!B:C, 2, FALSE) -> #N/A | BS72: #ERROR!
A73: ACT-SCRW57264 | B73: SC-260619-155001 | C73: 46192.66 | D73: 92 | E73: PB3572 | F73: Gestión de programas de exposiciones, actividades formativas y académicas en los Museos de la Secretaría de Cultura y actividades extramuros | G73: Creación y participación en actividades formativas y académicas de los museos adscritos a la Secretaria de Cultura | H73: SUBSECRETARÍA DE DESARROLLO Y PROMOCIÓN ARTÍSTICA Y CULTURAL | I73: DIRECCIÓN GENERAL DE MUSEOS, ARTES VISUALES Y EXPOSICIONES | J73: Número de Actividades realizadas | K73: 800 | L73: Artística | M73: Visita escolar Secundaria Benito Juárez | N73: Recorrido guiado por el museo | O73: Única | P73: 46155 | Q73: 46155 | R73: 1 | S73: Cultura comunitaria | T73: Formación comunitaria | U73: Visitas escolares | V73: Ninguna | W73: Presencial | X73: Espacio a Cargo de la Secretaría | Y73: 6 | AB73: FALSE | AD73: FALSE | AF73: FALSE | AH73: Sin costo | AL73: ccardonav@guanajuato.gob.mx | AM73: Arraigo y empoderamiento cultural de comunidades. | AN73: 2 Igualdad | AO73: 2.1 Protección de derechos humanos | AP73: 2.1.3 Inclusión de personas con discapacidad | AQ73: 2.1.3.2 Coordinar la incorporación progresiva de la accesibilidad universal | AR73: Cooperación | AT73: Fortalecimiento de la participación ciudadana y la mediación cultural | AU73: Impulso a la ampliación de la oferta cultural en los territorios. | AV73: Fortalecer la programación cultural en espacios públicos, espacios alternativos y otros espacios culturales. | AW73: Incrementar en 25% la oferta cultural realizada en los municipios. | AX73: Visitas escolares | AY73: Formación | AZ73: Formación | BC73: 0 | BF73: FALSE | BM73: No | BQ73: Abierta | BR73: =VLOOKUP(BQ73, Cat_Indicadores!B:C, 2, FALSE) -> #N/A | BS73: #ERROR!
A74: ACT-SCRO46689 | B74: SC-260622-100056 | C74: 46195.417 | D74: 92 | E74: PB3572 | F74: Gestión de programas de exposiciones, actividades formativas y académicas en los Museos de la Secretaría de Cultura y actividades extramuros | G74: Creación y participación en actividades formativas y académicas de los museos adscritos a la Secretaria de Cultura | H74: SUBSECRETARÍA DE DESARROLLO Y PROMOCIÓN ARTÍSTICA Y CULTURAL | I74: DIRECCIÓN GENERAL DE MUSEOS, ARTES VISUALES Y EXPOSICIONES | J74: Número de Actividades realizadas | K74: 800 | L74: Cultural | M74: Florilegio de mayo, peregrinaciones a Nuestra Señora de Guanajuato | N74: Conferencia en torno a la tradición en la ciudad de Guanajuato | O74: Única | P74: 46155 | Q74: 46155 | R74: 1 | S74: Patrimonio cultural | T74: Memoria histórica | U74: Conferencia | V74: Ninguna | W74: Presencial | X74: Espacio a Cargo de la Secretaría | Y74: 3 | AB74: FALSE | AD74: FALSE | AF74: FALSE | AH74: Sin costo | AL74: ccardonav@guanajuato.gob.mx | AM74: Arraigo y empoderamiento cultural de comunidades. | AN74: 1 Tranquilidad | AO74: 1.2 Fortalecer prevención del delito | AP74: 1.2.2 Fortalecimiento del tejido social | AQ74: 1.2.3.4 Promover una cultura de paz desde las expresiones artísticas y culturales | AR74: Cooperación | AT74: Fortalecimiento de la participación ciudadana y la mediación cultural | AU74: Impulso a la ampliación de la oferta cultural en los territorios. | AV74: Fortalecer la programación cultural en espacios públicos, espacios alternativos y otros espacios culturales. | AW74: Incrementar en 25% la oferta cultural realizada en los municipios. | AX74: Conferencia | AY74: Formación | AZ74: Formación | BC74: 0 | BF74: FALSE | BM74: No | BQ74: Abierta | BR74: =VLOOKUP(BQ74, Cat_Indicadores!B:C, 2, FALSE) -> #N/A | BS74: #ERROR!
A75: ACT-SCWW16326 | B75: SC-260622-101207 | C75: 46195.425 | D75: 92 | E75: PB3572 | F75: Gestión de programas de exposiciones, actividades formativas y académicas en los Museos de la Secretaría de Cultura y actividades extramuros | G75: Creación y participación en actividades formativas y académicas de los museos adscritos a la Secretaria de Cultura | H75: SUBSECRETARÍA DE DESARROLLO Y PROMOCIÓN ARTÍSTICA Y CULTURAL | I75: DIRECCIÓN GENERAL DE MUSEOS, ARTES VISUALES Y EXPOSICIONES | J75: Número de Actividades realizadas | K75: 800 | L75: Artística | M75: Cuentacuento: La gran campana | N75: Perdido por la lejana y antigua china un chinito me encontró, quien entre risas y canciones un cuentito me contó; la historia de un emperador malicioso quien además de peligroso era muy caprichoso ¡Una gran campana quería! pero nadie se imaginaba lo que para crearla provocaría. | O75: Única | P75: 46159 | Q75: 46159 | R75: 1 | S75: Artes escénicas | T75: Teatro | U75: Presentación artística | V75: Ninguna | W75: Presencial | X75: Espacio a Cargo de la Secretaría | Y75: 4 | AB75: FALSE | AD75: TRUE | AE75: 1 | AF75: FALSE | AH75: Sin costo | AL75: ccardonav@guanajuato.gob.mx | AM75: Arraigo y empoderamiento cultural de comunidades. | AN75: 2 Igualdad | AO75: 2.1 Protección de derechos humanos | AP75: 2.1.3 Inclusión de personas con discapacidad | AQ75: 2.1.3.2 Coordinar la incorporación progresiva de la accesibilidad universal | AR75: Cooperación | AT75: Fortalecimiento de la participación ciudadana y la mediación cultural | AU75: Impulso a la ampliación de la oferta cultural en los territorios. | AV75: Fortalecer la programación cultural en espacios públicos, espacios alternativos y otros espacios culturales. | AW75: Incrementar en 25% la oferta cultural realizada en los municipios. | AX75: Presentación artística | AY75: Formación | AZ75: Formación | BC75: 0 | BF75: FALSE | BM75: No | BQ75: Abierta | BR75: =VLOOKUP(BQ75, Cat_Indicadores!B:C, 2, FALSE) -> #N/A | BS75: #ERROR!
A76: ACT-SCSX44941 | B76: SC-260622-101654 | C76: 46195.428 | D76: 92 | E76: PB3572 | F76: Gestión de programas de exposiciones, actividades formativas y académicas en los Museos de la Secretaría de Cultura y actividades extramuros | G76: Creación y participación en actividades formativas y académicas de los museos adscritos a la Secretaria de Cultura | H76: SUBSECRETARÍA DE DESARROLLO Y PROMOCIÓN ARTÍSTICA Y CULTURAL | I76: DIRECCIÓN GENERAL DE MUSEOS, ARTES VISUALES Y EXPOSICIONES | J76: Número de Actividades realizadas | K76: 800 | L76: Artística | M76: Visita guiada Gerontológico Salamanca | N76: Recorrido guiado por el museo | O76: Única | P76: 46162 | Q76: 46162 | R76: 1 | S76: Cultura comunitaria | T76: Formación comunitaria | U76: Visitas escolares | V76: Ninguna | W76: Presencial | X76: Espacio a Cargo de la Secretaría | Y76: 5 | AB76: FALSE | AD76: FALSE | AF76: FALSE | AH76: Sin costo | AL76: ccardonav@guanajuato.gob.mx | AM76: Arraigo y empoderamiento cultural de comunidades. | AN76: 2 Igualdad | AO76: 2.1 Protección de derechos humanos | AP76: 2.1.3 Inclusión de personas con discapacidad | AQ76: 2.1.3.2 Coordinar la incorporación progresiva de la accesibilidad universal | AR76: Cooperación | AT76: Fortalecimiento de la participación ciudadana y la mediación cultural | AU76: Impulso a la ampliación de la oferta cultural en los territorios. | AV76: Fortalecer la programación cultural en espacios públicos, espacios alternativos y otros espacios culturales. | AW76: Incrementar en 25% la oferta cultural realizada en los municipios. | AX76: Visitas escolares | AY76: Formación | AZ76: Formación | BC76: 0 | BF76: FALSE | BM76: No | BQ76: Abierta | BR76: =VLOOKUP(BQ76, Cat_Indicadores!B:C, 2, FALSE) -> #N/A | BS76: #ERROR!
A77: ACT-SCMS43271 | B77: SC-260622-102102 | C77: 46195.431 | D77: 92 | E77: PB3572 | F77: Gestión de programas de exposiciones, actividades formativas y académicas en los Museos de la Secretaría de Cultura y actividades extramuros | G77: Creación y participación en actividades formativas y académicas de los museos adscritos a la Secretaria de Cultura | H77: SUBSECRETARÍA DE DESARROLLO Y PROMOCIÓN ARTÍSTICA Y CULTURAL | I77: DIRECCIÓN GENERAL DE MUSEOS, ARTES VISUALES Y EXPOSICIONES | J77: Número de Actividades realizadas | K77: 800 | L77: Artística | M77: Rumbo al festival del piano | N77: Presentación musical a cargo de estudiantes de Música de la Universidad de Guanajuato. | O77: Única | P77: 46162 | Q77: 46162 | R77: 1 | S77: Música | T77: Música académica | U77: Presentación artística | V77: Ninguna | W77: Presencial | X77: Espacio a Cargo de la Secretaría | Y77: 5 | AB77: FALSE | AD77: FALSE | AF77: FALSE | AH77: Sin costo | AL77: ccardonav@guanajuato.gob.mx | AM77: Arraigo y empoderamiento cultural de comunidades. | AN77: 1 Tranquilidad | AO77: 1.2 Fortalecer prevención del delito | AP77: 1.2.2 Fortalecimiento del tejido social | AQ77: 1.2.3.4 Promover una cultura de paz desde las expresiones artísticas y culturales | AR77: Cooperación | AT77: Fortalecimiento de la participación ciudadana y la mediación cultural | AU77: Impulso a la ampliación de la oferta cultural en los territorios. | AV77: Fortalecer la programación cultural en espacios públicos, espacios alternativos y otros espacios culturales. | AW77: Incrementar en 25% la oferta cultural realizada en los municipios. | AX77: Presentación artística | AY77: Formación | AZ77: Formación | BC77: 0 | BF77: FALSE | BM77: No | BQ77: Abierta | BR77: =VLOOKUP(BQ77, Cat_Indicadores!B:C, 2, FALSE) -> #N/A | BS77: #ERROR!
A78: ACT-SCPY84321 | B78: SC-260622-103219 | C78: 46195.439 | D78: 92 | E78: PB3572 | F78: Gestión de programas de exposiciones, actividades formativas y académicas en los Museos de la Secretaría de Cultura y actividades extramuros | G78: Creación y participación en actividades formativas y académicas de los museos adscritos a la Secretaria de Cultura | H78: SUBSECRETARÍA DE DESARROLLO Y PROMOCIÓN ARTÍSTICA Y CULTURAL | I78: DIRECCIÓN GENERAL DE MUSEOS, ARTES VISUALES Y EXPOSICIONES | J78: Número de Actividades realizadas | K78: 800 | L78: Cultural | M78: Transmisión Radio UG EL DADO | N78: Transmición de Radio Universidad de Guanajuato en el Museo | O78: Única | P78: 46162 | Q78: 46162 | R78: 1 | S78: Cultura comunitaria | T78: Mediación cultural | U78: Programación cultural en recinto | V78: Ninguna | W78: Presencial | X78: Espacio a Cargo de la Secretaría | Y78: 6 | AB78: FALSE | AD78: FALSE | AF78: FALSE | AH78: Sin costo | AL78: ccardonav@guanajuato.gob.mx | AM78: Arraigo y empoderamiento cultural de comunidades. | AN78: 2 Igualdad | AO78: 2.1 Protección de derechos humanos | AP78: 2.1.3 Inclusión de personas con discapacidad | AQ78: 2.1.3.2 Coordinar la incorporación progresiva de la accesibilidad universal | AR78: Cooperación | AT78: Fortalecimiento de la participación ciudadana y la mediación cultural | AU78: Impulso a la ampliación de la oferta cultural en los territorios. | AV78: Fortalecer la programación cultural en espacios públicos, espacios alternativos y otros espacios culturales. | AW78: Incrementar en 25% la oferta cultural realizada en los municipios. | AX78: Programación cultural en recinto | AY78: Formación | AZ78: Formación | BC78: 0 | BF78: FALSE | BM78: No | BQ78: Abierta | BR78: =VLOOKUP(BQ78, Cat_Indicadores!B:C, 2, FALSE) -> #N/A | BS78: #ERROR!
A79: ACT-SCCK59938 | B79: SC-260622-110744 | C79: 46195.464 | D79: 92 | E79: PB3572 | F79: Gestión de programas de exposiciones, actividades formativas y académicas en los Museos de la Secretaría de Cultura y actividades extramuros | G79: Creación y participación en actividades formativas y académicas de los museos adscritos a la Secretaria de Cultura | H79: SUBSECRETARÍA DE DESARROLLO Y PROMOCIÓN ARTÍSTICA Y CULTURAL | I79: DIRECCIÓN GENERAL DE MUSEOS, ARTES VISUALES Y EXPOSICIONES | J79: Número de Actividades realizadas | K79: 800 | L79: Artística | M79: Los de afuera, presentación musical - visual urbana | N79: Presentación tanto musical como visual de arte urbano en la cual se da introducción a un público no familiarizado con tales disciplinas mientras conocen brevemente las historias de los artistas urbanos invitados. | O79: Única | P79: 46163 | Q79: 46163 | R79: 1 | S79: Artes escénicas | T79: Danza contemporánea | U79: Presentación artística | V79: Ninguna | W79: Presencial | X79: Espacio a Cargo de la Secretaría | Y79: 6 | AB79: FALSE | AD79: FALSE | AF79: FALSE | AH79: Sin costo | AL79: ccardonav@guanajuato.gob.mx | AM79: Arraigo y empoderamiento cultural de comunidades. | AN79: 1 Tranquilidad | AO79: 1.2 Fortalecer prevención del delito | AP79: 1.2.2 Fortalecimiento del tejido social | AQ79: 1.2.3.4 Promover una cultura de paz desde las expresiones artísticas y culturales | AR79: Cooperación | AT79: Fortalecimiento de la participación ciudadana y la mediación cultural | AU79: Impulso a la ampliación de la oferta cultural en los territorios. | AV79: Fortalecer la programación cultural en espacios públicos, espacios alternativos y otros espacios culturales. | AW79: Incrementar en 25% la oferta cultural realizada en los municipios. | AX79: Presentación artística | AY79: Formación | AZ79: Formación | BC79: 0 | BF79: FALSE | BM79: No | BQ79: Abierta | BR79: =VLOOKUP(BQ79, Cat_Indicadores!B:C, 2, FALSE) -> #N/A | BS79: #ERROR!
A80: ACT-SCHE27788 | B80: SC-260622-111214 | C80: 46195.467 | D80: 92 | E80: PB3572 | F80: Gestión de programas de exposiciones, actividades formativas y académicas en los Museos de la Secretaría de Cultura y actividades extramuros | G80: Creación y participación en actividades formativas y académicas de los museos adscritos a la Secretaria de Cultura | H80: SUBSECRETARÍA DE DESARROLLO Y PROMOCIÓN ARTÍSTICA Y CULTURAL | I80: DIRECCIÓN GENERAL DE MUSEOS, ARTES VISUALES Y EXPOSICIONES | J80: Número de Actividades realizadas | K80: 800 | L80: Artística | M80: Inauguración: ¡Moda hoy! Diseño de moda latinoamericanx y latinx | N80: ¡Moda hoy! reúne el talento de diseñadorxs latinxs que han marcado a la industria global con propuestas audaces, identitarias y llenas de historia. | O80: Única | P80: 46163 | Q80: 46163 | R80: 1 | S80: Patrimonio cultural | T80: Patrimonio material | U80: Programación cultural en recinto | V80: Ninguna | W80: Presencial | X80: Espacio a Cargo de la Secretaría | Y80: 2 | AB80: FALSE | AD80: TRUE | AE80: 1 | AF80: FALSE | AH80: Sin costo | AL80: ccardonav@guanajuato.gob.mx | AM80: Creación de la Secretaría de Cultura, con una visión social de la política cultural. | AN80: 1 Tranquilidad | AO80: 1.2 Fortalecer prevención del delito | AP80: 1.2.2 Fortalecimiento del tejido social | AQ80: 1.2.3.4 Promover una cultura de paz desde las expresiones artísticas y culturales | AR80: Cooperación | AT80: Fortalecimiento de la participación ciudadana y la mediación cultural | AU80: Impulso a la ampliación de la oferta cultural en los territorios. | AV80: Fortalecer la programación cultural en espacios públicos, espacios alternativos y otros espacios culturales. | AW80: Incrementar en 25% la oferta cultural realizada en los municipios. | AX80: Programación cultural en recinto | AY80: Formación | AZ80: Formación | BC80: 0 | BF80: FALSE | BM80: No | BQ80: Abierta | BR80: =VLOOKUP(BQ80, Cat_Indicadores!B:C, 2, FALSE) -> #N/A | BS80: #ERROR!
A81: ACT-SCQN89526 | B81: SC-260622-112027 | C81: 46195.473 | D81: 92 | E81: PB3572 | F81: Gestión de programas de exposiciones, actividades formativas y académicas en los Museos de la Secretaría de Cultura y actividades extramuros | G81: Creación y participación en actividades formativas y académicas de los museos adscritos a la Secretaria de Cultura | H81: SUBSECRETARÍA DE DESARROLLO Y PROMOCIÓN ARTÍSTICA Y CULTURAL | I81: DIRECCIÓN GENERAL DE MUSEOS, ARTES VISUALES Y EXPOSICIONES | J81: Número de Actividades realizadas | K81: 800 | L81: Artística | M81: Ecos, Tolula, música y danza. | N81: Ecos Tolula Ensamble presenta una propuesta escénica que muestra el interés por fusionar y enriquecer el contexto armónico, rítmico, visual y de movimiento de estas dos artes. | O81: Única | P81: 46164 | Q81: 46164 | R81: 1 | S81: Música | T81: Música académica | U81: Presentación artística | V81: Ninguna | W81: Presencial | X81: Espacio a Cargo de la Secretaría | Y81: 5 | AB81: FALSE | AD81: FALSE | AF81: FALSE | AH81: Sin costo | AL81: ccardonav@guanajuato.gob.mx | AM81: Arraigo y empoderamiento cultural de comunidades. | AN81: 1 Tranquilidad | AO81: 1.2 Fortalecer prevención del delito | AP81: 1.2.2 Fortalecimiento del tejido social | AQ81: 1.2.3.4 Promover una cultura de paz desde las expresiones artísticas y culturales | AR81: Cooperación | AT81: Fortalecimiento de la participación ciudadana y la mediación cultural | AU81: Impulso a la ampliación de la oferta cultural en los territorios. | AV81: Fortalecer la programación cultural en espacios públicos, espacios alternativos y otros espacios culturales. | AW81: Incrementar en 25% la oferta cultural realizada en los municipios. | AX81: Presentación artística | AY81: Formación | AZ81: Formación | BC81: 0 | BF81: FALSE | BM81: No | BQ81: Abierta | BR81: =VLOOKUP(BQ81, Cat_Indicadores!B:C, 2, FALSE) -> #N/A | BS81: #ERROR!
A82: ACT-SCQZ87444 | B82: SC-260622-112432 | C82: 46195.475 | D82: 92 | E82: PB3572 | F82: Gestión de programas de exposiciones, actividades formativas y académicas en los Museos de la Secretaría de Cultura y actividades extramuros | G82: Creación y participación en actividades formativas y académicas de los museos adscritos a la Secretaria de Cultura | H82: SUBSECRETARÍA DE DESARROLLO Y PROMOCIÓN ARTÍSTICA Y CULTURAL | I82: DIRECCIÓN GENERAL DE MUSEOS, ARTES VISUALES Y EXPOSICIONES | J82: Número de Actividades realizadas | K82: 800 | L82: Artística | M82: Inauguración: ¡Moda hoy! Diseño de moda latinoamericanx y latinx | N82: Conferencia en torno a la exposición¡Moda hoy! Diseño de moda latinoamericanx y latinx A través de piezas emblemáticas y narrativas contemporáneas, descubrirás cómo la creatividad latinoamericana sigue expandiendo sus fronteras. | O82: Única | P82: 46164 | Q82: 46164 | R82: 1 | S82: Cultura comunitaria | T82: Mediación cultural | U82: Charla | V82: Ninguna | W82: Presencial | X82: Espacio a Cargo de la Secretaría | Y82: 2 | AB82: FALSE | AD82: FALSE | AF82: FALSE | AH82: Sin costo | AL82: ccardonav@guanajuato.gob.mx | AM82: Creación de la Secretaría de Cultura, con una visión social de la política cultural. | AN82: 1 Tranquilidad | AO82: 1.2 Fortalecer prevención del delito | AP82: 1.2.2 Fortalecimiento del tejido social | AQ82: 1.2.3.4 Promover una cultura de paz desde las expresiones artísticas y culturales | AR82: Cooperación | AT82: Fortalecimiento de la participación ciudadana y la mediación cultural | AU82: Impulso a la ampliación de la oferta cultural en los territorios. | AV82: Fortalecer la programación cultural en espacios públicos, espacios alternativos y otros espacios culturales. | AW82: Incrementar en 25% la oferta cultural realizada en los municipios. | AX82: Charla | AY82: Formación | AZ82: Formación | BC82: 0 | BF82: FALSE | BM82: No | BQ82: Abierta | BR82: =VLOOKUP(BQ82, Cat_Indicadores!B:C, 2, FALSE) -> #N/A | BS82: #ERROR!
A83: ACT-SCZI86402 | B83: SC-260622-113022 | C83: 46195.479 | D83: 92 | E83: PB3572 | F83: Gestión de programas de exposiciones, actividades formativas y académicas en los Museos de la Secretaría de Cultura y actividades extramuros | G83: Creación y participación en actividades formativas y académicas de los museos adscritos a la Secretaria de Cultura | H83: SUBSECRETARÍA DE DESARROLLO Y PROMOCIÓN ARTÍSTICA Y CULTURAL | I83: DIRECCIÓN GENERAL DE MUSEOS, ARTES VISUALES Y EXPOSICIONES | J83: Número de Actividades realizadas | K83: 800 | L83: Artística | M83: Obra en análisis: observando el poder en El fusilero Marino. | N83: Actividad de mediación artística, en donde a partir de la obra el Fusilero Marino de Diego Rivera realizaremos un análisis de la técnica, la historia, el contexto político y social de la pieza, así como la representación del poder en la misma. El desarrollo de la sesión se llevará a cabo de manera participativa y colectiva, a través del diálogo crítico entre los asistentes. | O83: Única | P83: 46168 | Q83: 46168 | R83: 1 | S83: Cultura comunitaria | T83: Formación comunitaria | U83: Visitas guiadas | V83: Ninguna | W83: Presencial | X83: Espacio a Cargo de la Secretaría | Y83: 6 | AB83: FALSE | AD83: FALSE | AF83: FALSE | AH83: Sin costo | AL83: ccardonav@guanajuato.gob.mx | AM83: Arraigo y empoderamiento cultural de comunidades. | AN83: 1 Tranquilidad | AO83: 1.2 Fortalecer prevención del delito | AP83: 1.2.2 Fortalecimiento del tejido social | AQ83: 1.2.3.4 Promover una cultura de paz desde las expresiones artísticas y culturales | AR83: Cooperación | AT83: Fortalecimiento de la participación ciudadana y la mediación cultural | AU83: Impulso a la ampliación de la oferta cultural en los territorios. | AV83: Fortalecer la programación cultural en espacios públicos, espacios alternativos y otros espacios culturales. | AW83: Incrementar en 25% la oferta cultural realizada en los municipios. | AX83: Visitas guiadas | AY83: Formación | AZ83: Formación | BC83: 0 | BF83: FALSE | BM83: No | BQ83: Abierta | BR83: =VLOOKUP(BQ83, Cat_Indicadores!B:C, 2, FALSE) -> #N/A | BS83: #ERROR!
A84: ACT-SCHH09885 | B84: SC-260622-113516 | C84: 46195.483 | D84: 92 | E84: PB3572 | F84: Gestión de programas de exposiciones, actividades formativas y académicas en los Museos de la Secretaría de Cultura y actividades extramuros | G84: Creación y participación en actividades formativas y académicas de los museos adscritos a la Secretaria de Cultura | H84: SUBSECRETARÍA DE DESARROLLO Y PROMOCIÓN ARTÍSTICA Y CULTURAL | I84: DIRECCIÓN GENERAL DE MUSEOS, ARTES VISUALES Y EXPOSICIONES | J84: Número de Actividades realizadas | K84: 800 | L84: Cultural | M84: Transmisión Radio UG | N84: Transmisión de Radio Universidad de Guanajuato en el Museo | O84: Única | P84: 46168 | Q84: 46168 | R84: 1 | S84: Cultura comunitaria | T84: Activación comunitaria | U84: Vinculación | V84: Ninguna | W84: Presencial | X84: Espacio a Cargo de la Secretaría | Y84: 6 | AB84: FALSE | AD84: FALSE | AF84: FALSE | AH84: Sin costo | AL84: ccardonav@guanajuato.gob.mx | AM84: Arraigo y empoderamiento cultural de comunidades. | AN84: 1 Tranquilidad | AO84: 1.2 Fortalecer prevención del delito | AP84: 1.2.2 Fortalecimiento del tejido social | AQ84: 1.2.3.4 Promover una cultura de paz desde las expresiones artísticas y culturales | AR84: Cooperación | AT84: Fortalecimiento de la participación ciudadana y la mediación cultural | AU84: Impulso a la ampliación de la oferta cultural en los territorios. | AV84: Fortalecer la programación cultural en espacios públicos, espacios alternativos y otros espacios culturales. | AW84: Incrementar en 25% la oferta cultural realizada en los municipios. | AX84: Difusión cultural | AY84: Formación | BC84: 0 | BF84: FALSE | BL84: VINCULACION | BM84: Sí | BQ84: Abierta | BR84: =VLOOKUP(BQ84, Cat_Indicadores!B:C, 2, FALSE) -> #N/A | BS84: #ERROR!
A85: ACT-SCAZ01656 | B85: SC-260622-114448 | C85: 46195.489 | D85: 92 | E85: PB3572 | F85: Gestión de programas de exposiciones, actividades formativas y académicas en los Museos de la Secretaría de Cultura y actividades extramuros | G85: Creación y participación en actividades formativas y académicas de los museos adscritos a la Secretaria de Cultura | H85: SUBSECRETARÍA DE DESARROLLO Y PROMOCIÓN ARTÍSTICA Y CULTURAL | I85: DIRECCIÓN GENERAL DE MUSEOS, ARTES VISUALES Y EXPOSICIONES | J85: Número de Actividades realizadas | K85: 800 | L85: Artística | M85: Visita guiada libre | N85: Recorrido guiado por el museo | O85: Única | P85: 46144 | Q85: 46144 | R85: 1 | S85: Cultura comunitaria | T85: Formación comunitaria | U85: Visitas escolares | V85: Ninguna | W85: Presencial | X85: Espacio a Cargo de la Secretaría | Y85: 1 | AB85: FALSE | AD85: FALSE | AF85: FALSE | AH85: Sin costo | AL85: ccardonav@guanajuato.gob.mx | AM85: Arraigo y empoderamiento cultural de comunidades. | AN85: 2 Igualdad | AO85: 2.1 Protección de derechos humanos | AP85: 2.1.3 Inclusión de personas con discapacidad | AQ85: 2.1.3.2 Coordinar la incorporación progresiva de la accesibilidad universal | AR85: Cooperación | AT85: Fortalecimiento de la participación ciudadana y la mediación cultural | AU85: Impulso a la ampliación de la oferta cultural en los territorios. | AV85: Fortalecer la programación cultural en espacios públicos, espacios alternativos y otros espacios culturales. | AW85: Incrementar en 25% la oferta cultural realizada en los municipios. | AX85: Visitas escolares | AY85: Formación | AZ85: Formación | BC85: 0 | BF85: FALSE | BM85: No | BQ85: Abierta | BR85: =VLOOKUP(BQ85, Cat_Indicadores!B:C, 2, FALSE) -> #N/A | BS85: #ERROR!
A86: ACT-SCKW17009 | B86: SC-260622-114909 | C86: 46195.492 | D86: 92 | E86: PB3572 | F86: Gestión de programas de exposiciones, actividades formativas y académicas en los Museos de la Secretaría de Cultura y actividades extramuros | G86: Creación y participación en actividades formativas y académicas de los museos adscritos a la Secretaria de Cultura | H86: SUBSECRETARÍA DE DESARROLLO Y PROMOCIÓN ARTÍSTICA Y CULTURAL | I86: DIRECCIÓN GENERAL DE MUSEOS, ARTES VISUALES Y EXPOSICIONES | J86: Número de Actividades realizadas | K86: 800 | L86: Artística | M86: Visita guiada libre | N86: Recorrido guiado por el museo | O86: Única | P86: 46145 | Q86: 46145 | R86: 1 | S86: Cultura comunitaria | T86: Formación comunitaria | U86: Visitas escolares | V86: Ninguna | W86: Presencial | X86: Espacio a Cargo de la Secretaría | Y86: 1 | AB86: FALSE | AD86: FALSE | AF86: FALSE | AH86: Sin costo | AL86: ccardonav@guanajuato.gob.mx | AM86: Arraigo y empoderamiento cultural de comunidades. | AN86: 2 Igualdad | AO86: 2.1 Protección de derechos humanos | AP86: 2.1.3 Inclusión de personas con discapacidad | AQ86: 2.1.3.2 Coordinar la incorporación progresiva de la accesibilidad universal | AR86: Cooperación | AT86: Fortalecimiento de la participación ciudadana y la mediación cultural | AU86: Impulso a la ampliación de la oferta cultural en los territorios. | AV86: Fortalecer la programación cultural en espacios públicos, espacios alternativos y otros espacios culturales. | AW86: Incrementar en 25% la oferta cultural realizada en los municipios. | AX86: Visitas escolares | AY86: Formación | AZ86: Formación | BC86: 0 | BF86: FALSE | BM86: No | BQ86: Abierta | BR86: =VLOOKUP(BQ86, Cat_Indicadores!B:C, 2, FALSE) -> #N/A | BS86: #ERROR!
A87: ACT-SCXT69671 | B87: SC-260622-115232 | C87: 46195.495 | D87: 92 | E87: PB3572 | F87: Gestión de programas de exposiciones, actividades formativas y académicas en los Museos de la Secretaría de Cultura y actividades extramuros | G87: Creación y participación en actividades formativas y académicas de los museos adscritos a la Secretaria de Cultura | H87: SUBSECRETARÍA DE DESARROLLO Y PROMOCIÓN ARTÍSTICA Y CULTURAL | I87: DIRECCIÓN GENERAL DE MUSEOS, ARTES VISUALES Y EXPOSICIONES | J87: Número de Actividades realizadas | K87: 800 | L87: Artística | M87: Visita guiada libre | N87: Recorrido guiado por el museo | O87: Única | P87: 46195 | Q87: 46195 | R87: 1 | S87: Cultura comunitaria | T87: Formación comunitaria | U87: Visitas escolares | V87: Ninguna | W87: Presencial | X87: Espacio a Cargo de la Secretaría | Y87: 1 | AB87: FALSE | AD87: FALSE | AF87: FALSE | AH87: Sin costo | AL87: ccardonav@guanajuato.gob.mx | AM87: Arraigo y empoderamiento cultural de comunidades. | AN87: 2 Igualdad | AO87: 2.1 Protección de derechos humanos | AP87: 2.1.3 Inclusión de personas con discapacidad | AQ87: 2.1.3.2 Coordinar la incorporación progresiva de la accesibilidad universal | AR87: Cooperación | AT87: Fortalecimiento de la participación ciudadana y la mediación cultural | AU87: Impulso a la ampliación de la oferta cultural en los territorios. | AV87: Fortalecer la programación cultural en espacios públicos, espacios alternativos y otros espacios culturales. | AW87: Incrementar en 25% la oferta cultural realizada en los municipios. | AX87: Visitas escolares | AY87: Formación | AZ87: Formación | BC87: 0 | BF87: FALSE | BM87: No | BQ87: Abierta | BR87: =VLOOKUP(BQ87, Cat_Indicadores!B:C, 2, FALSE) -> #N/A | BS87: #ERROR!
A88: ACT-SCCB66394 | B88: SC-260622-115601 | C88: 46195.497 | D88: 92 | E88: PB3572 | F88: Gestión de programas de exposiciones, actividades formativas y académicas en los Museos de la Secretaría de Cultura y actividades extramuros | G88: Creación y participación en actividades formativas y académicas de los museos adscritos a la Secretaria de Cultura | H88: SUBSECRETARÍA DE DESARROLLO Y PROMOCIÓN ARTÍSTICA Y CULTURAL | I88: DIRECCIÓN GENERAL DE MUSEOS, ARTES VISUALES Y EXPOSICIONES | J88: Número de Actividades realizadas | K88: 800 | L88: Artística | M88: Visita guiada libre | N88: Recorrido guiado por el museo | O88: Única | P88: 46169 | Q88: 46169 | R88: 1 | S88: Cultura comunitaria | T88: Formación comunitaria | U88: Visitas escolares | V88: Ninguna | W88: Presencial | X88: Espacio a Cargo de la Secretaría | Y88: 1 | AB88: FALSE | AD88: FALSE | AF88: FALSE | AH88: Sin costo | AL88: ccardonav@guanajuato.gob.mx | AM88: Arraigo y empoderamiento cultural de comunidades. | AN88: 2 Igualdad | AO88: 2.1 Protección de derechos humanos | AP88: 2.1.3 Inclusión de personas con discapacidad | AQ88: 2.1.3.2 Coordinar la incorporación progresiva de la accesibilidad universal | AR88: Cooperación | AT88: Fortalecimiento de la participación ciudadana y la mediación cultural | AU88: Impulso a la ampliación de la oferta cultural en los territorios. | AV88: Fortalecer la programación cultural en espacios públicos, espacios alternativos y otros espacios culturales. | AW88: Incrementar en 25% la oferta cultural realizada en los municipios. | AX88: Visitas escolares | AY88: Formación | BC88: 0 | BF88: FALSE | BM88: No | BQ88: Abierta | BR88: =VLOOKUP(BQ88, Cat_Indicadores!B:C, 2, FALSE) -> #N/A | BS88: #ERROR!
A89: ACT-SCVT09644 | B89: SC-260622-115921 | C89: 46195.5 | D89: 92 | E89: PB3572 | F89: Gestión de programas de exposiciones, actividades formativas y académicas en los Museos de la Secretaría de Cultura y actividades extramuros | G89: Creación y participación en actividades formativas y académicas de los museos adscritos a la Secretaria de Cultura | H89: SUBSECRETARÍA DE DESARROLLO Y PROMOCIÓN ARTÍSTICA Y CULTURAL | I89: DIRECCIÓN GENERAL DE MUSEOS, ARTES VISUALES Y EXPOSICIONES | J89: Número de Actividades realizadas | K89: 800 | L89: Artística | M89: Visita guiada libre | N89: Recorrido guiado por el museo | O89: Única | P89: 46172 | Q89: 46172 | R89: 1 | S89: Cultura comunitaria | T89: Formación comunitaria | U89: Visitas escolares | V89: Ninguna | W89: Presencial | X89: Espacio a Cargo de la Secretaría | Y89: 1 | AB89: FALSE | AD89: FALSE | AF89: FALSE | AH89: Sin costo | AL89: ccardonav@guanajuato.gob.mx | AM89: Arraigo y empoderamiento cultural de comunidades. | AN89: 2 Igualdad | AO89: 2.1 Protección de derechos humanos | AP89: 2.1.3 Inclusión de personas con discapacidad | AQ89: 2.1.3.2 Coordinar la incorporación progresiva de la accesibilidad universal | AR89: Cooperación | AT89: Fortalecimiento de la participación ciudadana y la mediación cultural | AU89: Impulso a la ampliación de la oferta cultural en los territorios. | AV89: Fortalecer la programación cultural en espacios públicos, espacios alternativos y otros espacios culturales. | AW89: Incrementar en 25% la oferta cultural realizada en los municipios. | AX89: Visitas escolares | AY89: Formación | AZ89: Formación | BC89: 0 | BF89: FALSE | BM89: No | BQ89: Abierta | BR89: =VLOOKUP(BQ89, Cat_Indicadores!B:C, 2, FALSE) -> #N/A | BS89: #ERROR!
A90: ACT-SCRN21273 | B90: SC-260622-120305 | C90: 46195.502 | D90: 92 | E90: PB3572 | F90: Gestión de programas de exposiciones, actividades formativas y académicas en los Museos de la Secretaría de Cultura y actividades extramuros | G90: Creación y participación en actividades formativas y académicas de los museos adscritos a la Secretaria de Cultura | H90: SUBSECRETARÍA DE DESARROLLO Y PROMOCIÓN ARTÍSTICA Y CULTURAL | I90: DIRECCIÓN GENERAL DE MUSEOS, ARTES VISUALES Y EXPOSICIONES | J90: Número de Actividades realizadas | K90: 800 | L90: Artística | M90: Visita guiada libre | N90: Recorrido guiado por el museo | O90: Única | P90: 46173 | Q90: 46173 | R90: 1 | S90: Cultura comunitaria | T90: Formación comunitaria | U90: Visitas escolares | V90: Ninguna | W90: Presencial | X90: Espacio a Cargo de la Secretaría | Y90: 1 | AB90: FALSE | AD90: FALSE | AF90: FALSE | AH90: Sin costo | AL90: ccardonav@guanajuato.gob.mx | AM90: Arraigo y empoderamiento cultural de comunidades. | AN90: 2 Igualdad | AO90: 2.1 Protección de derechos humanos | AP90: 2.1.3 Inclusión de personas con discapacidad | AQ90: 2.1.3.2 Coordinar la incorporación progresiva de la accesibilidad universal | AR90: Cooperación | AT90: Fortalecimiento de la participación ciudadana y la mediación cultural | AU90: Impulso a la ampliación de la oferta cultural en los territorios. | AV90: Fortalecer la programación cultural en espacios públicos, espacios alternativos y otros espacios culturales. | AW90: Incrementar en 25% la oferta cultural realizada en los municipios. | AX90: Visitas escolares | AY90: Formación | AZ90: Formación | BC90: 0 | BF90: FALSE | BM90: No | BQ90: Abierta | BR90: =VLOOKUP(BQ90, Cat_Indicadores!B:C, 2, FALSE) -> #N/A | BS90: #ERROR!
A91: ACT-SCQL83167 | B91: SC-260622-120810 | C91: 46195.506 | D91: 92 | E91: PB3572 | F91: Gestión de programas de exposiciones, actividades formativas y académicas en los Museos de la Secretaría de Cultura y actividades extramuros | G91: Creación y participación en actividades formativas y académicas de los museos adscritos a la Secretaria de Cultura | H91: SUBSECRETARÍA DE DESARROLLO Y PROMOCIÓN ARTÍSTICA Y CULTURAL | I91: DIRECCIÓN GENERAL DE MUSEOS, ARTES VISUALES Y EXPOSICIONES | J91: Número de Actividades realizadas | K91: 800 | L91: Artística | M91: Visita guiada libre | N91: Recorrido guiado por el museo | O91: Única | P91: 46173 | Q91: 46173 | R91: 1 | S91: Cultura comunitaria | T91: Formación comunitaria | U91: Visitas escolares | V91: Ninguna | W91: Presencial | X91: Espacio a Cargo de la Secretaría | Y91: 1 | AB91: FALSE | AD91: FALSE | AF91: FALSE | AH91: Sin costo | AL91: ccardonav@guanajuato.gob.mx | AM91: Arraigo y empoderamiento cultural de comunidades. | AN91: 2 Igualdad | AO91: 2.1 Protección de derechos humanos | AP91: 2.1.3 Inclusión de personas con discapacidad | AQ91: 2.1.3.2 Coordinar la incorporación progresiva de la accesibilidad universal | AR91: Cooperación | AT91: Fortalecimiento de la participación ciudadana y la mediación cultural | AU91: Impulso a la ampliación de la oferta cultural en los territorios. | AV91: Fortalecer la programación cultural en espacios públicos, espacios alternativos y otros espacios culturales. | AW91: Incrementar en 25% la oferta cultural realizada en los municipios. | AX91: Visitas escolares | AY91: Formación | AZ91: Formación | BC91: 0 | BF91: FALSE | BM91: No | BQ91: Abierta | BR91: =VLOOKUP(BQ91, Cat_Indicadores!B:C, 2, FALSE) -> #N/A | BS91: #ERROR!
A92: ACT-SCMZ54375 | B92: SC-260622-121605 | C92: 46195.511 | D92: 92 | E92: PB3572 | F92: Gestión de programas de exposiciones, actividades formativas y académicas en los Museos de la Secretaría de Cultura y actividades extramuros | G92: Creación y participación en actividades formativas y académicas de los museos adscritos a la Secretaria de Cultura | H92: SUBSECRETARÍA DE DESARROLLO Y PROMOCIÓN ARTÍSTICA Y CULTURAL | I92: DIRECCIÓN GENERAL DE MUSEOS, ARTES VISUALES Y EXPOSICIONES | J92: Número de Actividades realizadas | K92: 800 | L92: Artística | M92: Visita guiada libre | N92: Recorrido guiado por el museo | O92: Única | P92: 46173 | Q92: 46173 | R92: 1 | S92: Cultura comunitaria | T92: Formación comunitaria | U92: Visitas escolares | V92: Ninguna | W92: Presencial | X92: Espacio a Cargo de la Secretaría | Y92: 2 | AB92: FALSE | AD92: FALSE | AF92: FALSE | AH92: Sin costo | AL92: ccardonav@guanajuato.gob.mx | AM92: Arraigo y empoderamiento cultural de comunidades. | AN92: 2 Igualdad | AO92: 2.1 Protección de derechos humanos | AP92: 2.1.3 Inclusión de personas con discapacidad | AQ92: 2.1.3.2 Coordinar la incorporación progresiva de la accesibilidad universal | AR92: Cooperación | AT92: Fortalecimiento de la participación ciudadana y la mediación cultural | AU92: Impulso a la ampliación de la oferta cultural en los territorios. | AV92: Fortalecer la programación cultural en espacios públicos, espacios alternativos y otros espacios culturales. | AW92: Incrementar en 25% la oferta cultural realizada en los municipios. | AX92: Visitas escolares | AY92: Formación | AZ92: Formación | BC92: 0 | BF92: FALSE | BM92: No | BQ92: Abierta | BR92: =VLOOKUP(BQ92, Cat_Indicadores!B:C, 2, FALSE) -> #N/A | BS92: #ERROR!
A93: ACT-SCVP20410 | B93: SC-260622-121932 | C93: 46195.514 | D93: 92 | E93: PB3572 | F93: Gestión de programas de exposiciones, actividades formativas y académicas en los Museos de la Secretaría de Cultura y actividades extramuros | G93: Creación y participación en actividades formativas y académicas de los museos adscritos a la Secretaria de Cultura | H93: SUBSECRETARÍA DE DESARROLLO Y PROMOCIÓN ARTÍSTICA Y CULTURAL | I93: DIRECCIÓN GENERAL DE MUSEOS, ARTES VISUALES Y EXPOSICIONES | J93: Número de Actividades realizadas | K93: 800 | L93: Artística | M93: Visita guiada Esc. TVC Bachillerato Loma de Yerbabuena | N93: Recorrido guiado por el museo | O93: Única | P93: 46164 | Q93: 46164 | R93: 1 | S93: Cultura comunitaria | T93: Formación comunitaria | U93: Visitas escolares | V93: Ninguna | W93: Presencial | X93: Espacio a Cargo de la Secretaría | Y93: 2 | AB93: FALSE | AD93: FALSE | AF93: FALSE | AH93: Sin costo | AL93: ccardonav@guanajuato.gob.mx | AM93: Arraigo y empoderamiento cultural de comunidades. | AN93: 2 Igualdad | AO93: 2.1 Protección de derechos humanos | AP93: 2.1.3 Inclusión de personas con discapacidad | AQ93: 2.1.3.2 Coordinar la incorporación progresiva de la accesibilidad universal | AR93: Cooperación | AT93: Fortalecimiento de la participación ciudadana y la mediación cultural | AU93: Impulso a la ampliación de la oferta cultural en los territorios. | AV93: Fortalecer la programación cultural en espacios públicos, espacios alternativos y otros espacios culturales. | AW93: Incrementar en 25% la oferta cultural realizada en los municipios. | AX93: Visitas escolares | AY93: Formación | BC93: 0 | BF93: FALSE | BM93: No | BQ93: Abierta | BR93: =VLOOKUP(BQ93, Cat_Indicadores!B:C, 2, FALSE) -> #N/A | BS93: #ERROR!
A94: ACT-SCWC72951 | B94: SC-260622-122514 | C94: 46195.518 | D94: 92 | E94: PB3572 | F94: Gestión de programas de exposiciones, actividades formativas y académicas en los Museos de la Secretaría de Cultura y actividades extramuros | G94: Creación y participación en actividades formativas y académicas de los museos adscritos a la Secretaria de Cultura | H94: SUBSECRETARÍA DE DESARROLLO Y PROMOCIÓN ARTÍSTICA Y CULTURAL | I94: DIRECCIÓN GENERAL DE MUSEOS, ARTES VISUALES Y EXPOSICIONES | J94: Número de Actividades realizadas | K94: 800 | L94: Artística | M94: Visita guiada Esc. Pri. Aquiles Serdán | N94: Recorrido guiado por el museo | O94: Única | P94: 46164 | Q94: 46164 | R94: 1 | S94: Cultura comunitaria | T94: Formación comunitaria | U94: Visitas escolares | V94: Ninguna | W94: Presencial | X94: Espacio a Cargo de la Secretaría | Y94: 5 | AB94: FALSE | AD94: FALSE | AF94: FALSE | AH94: Sin costo | AL94: ccardonav@guanajuato.gob.mx | AM94: Arraigo y empoderamiento cultural de comunidades. | AN94: 2 Igualdad | AO94: 2.1 Protección de derechos humanos | AP94: 2.1.3 Inclusión de personas con discapacidad | AQ94: 2.1.3.2 Coordinar la incorporación progresiva de la accesibilidad universal | AR94: Cooperación | AT94: Fortalecimiento de la participación ciudadana y la mediación cultural | AU94: Impulso a la ampliación de la oferta cultural en los territorios. | AV94: Fortalecer la programación cultural en espacios públicos, espacios alternativos y otros espacios culturales. | AW94: Incrementar en 25% la oferta cultural realizada en los municipios. | AX94: Visitas escolares | AY94: Formación | AZ94: Formación | BC94: 0 | BF94: FALSE | BM94: No | BQ94: Abierta | BR94: =VLOOKUP(BQ94, Cat_Indicadores!B:C, 2, FALSE) -> #N/A | BS94: #ERROR!
A95: ACT-SCOJ61319 | B95: SC-260622-122905 | C95: 46195.52 | D95: 92 | E95: PB3572 | F95: Gestión de programas de exposiciones, actividades formativas y académicas en los Museos de la Secretaría de Cultura y actividades extramuros | G95: Creación y participación en actividades formativas y académicas de los museos adscritos a la Secretaria de Cultura | H95: SUBSECRETARÍA DE DESARROLLO Y PROMOCIÓN ARTÍSTICA Y CULTURAL | I95: DIRECCIÓN GENERAL DE MUSEOS, ARTES VISUALES Y EXPOSICIONES | J95: Número de Actividades realizadas | K95: 800 | L95: Artística | M95: Visita práctica escolar. Sesión de dibujo UG | N95: Recorrido guiado por el museo | O95: Única | P95: 46163 | Q95: 46163 | R95: 1 | S95: Cultura comunitaria | T95: Formación comunitaria | U95: Visitas escolares | V95: Ninguna | W95: Presencial | X95: Espacio a Cargo de la Secretaría | Y95: 5 | AB95: FALSE | AD95: FALSE | AF95: FALSE | AH95: Sin costo | AL95: ccardonav@guanajuato.gob.mx | AM95: Arraigo y empoderamiento cultural de comunidades. | AN95: 2 Igualdad | AO95: 2.1 Protección de derechos humanos | AP95: 2.1.3 Inclusión de personas con discapacidad | AQ95: 2.1.3.2 Coordinar la incorporación progresiva de la accesibilidad universal | AR95: Cooperación | AT95: Fortalecimiento de la participación ciudadana y la mediación cultural | AU95: Impulso a la ampliación de la oferta cultural en los territorios. | AV95: Fortalecer la programación cultural en espacios públicos, espacios alternativos y otros espacios culturales. | AW95: Incrementar en 25% la oferta cultural realizada en los municipios. | AX95: Visitas escolares | AY95: Formación | AZ95: Formación | BC95: 0 | BF95: FALSE | BM95: No | BQ95: Abierta | BR95: =VLOOKUP(BQ95, Cat_Indicadores!B:C, 2, FALSE) -> #N/A | BS95: #ERROR!
A96: ACT-SCQS70160 | B96: SC-260622-123746 | C96: 46195.526 | D96: 92 | E96: PB3572 | F96: Gestión de programas de exposiciones, actividades formativas y académicas en los Museos de la Secretaría de Cultura y actividades extramuros | G96: Creación y participación en actividades formativas y académicas de los museos adscritos a la Secretaria de Cultura | H96: SUBSECRETARÍA DE DESARROLLO Y PROMOCIÓN ARTÍSTICA Y CULTURAL | I96: DIRECCIÓN GENERAL DE MUSEOS, ARTES VISUALES Y EXPOSICIONES | J96: Número de Actividades realizadas | K96: 800 | L96: Artística | M96: Concierto de la Orquesta Sinfónica Infantil del Departamento de Música y Artes Escénicas | N96: Espacios incidentales: Concierto de la Orquesta Sinfónica Infantil del Departamento de Música y Artes Escénicas | O96: Única | P96: 46175 | Q96: 46175 | R96: 1 | S96: Música | T96: Música académica | U96: Presentación artística | V96: Ninguna | W96: Presencial | X96: Espacio a Cargo de la Secretaría | Y96: 5 | AB96: FALSE | AD96: FALSE | AF96: FALSE | AH96: Sin costo | AL96: ccardonav@guanajuato.gob.mx | AM96: Arraigo y empoderamiento cultural de comunidades. | AN96: 1 Tranquilidad | AO96: 1.2 Fortalecer prevención del delito | AP96: 1.2.2 Fortalecimiento del tejido social | AQ96: 1.2.3.4 Promover una cultura de paz desde las expresiones artísticas y culturales | AR96: Cooperación | AT96: Fortalecimiento de la participación ciudadana y la mediación cultural | AU96: Impulso a la ampliación de la oferta cultural en los territorios. | AV96: Fortalecer la programación cultural en espacios públicos, espacios alternativos y otros espacios culturales. | AW96: Incrementar en 25% la oferta cultural realizada en los municipios. | AX96: Presentación artística | AY96: Formación | AZ96: Formación | BC96: 0 | BF96: FALSE | BM96: No | BQ96: Abierta | BR96: =VLOOKUP(BQ96, Cat_Indicadores!B:C, 2, FALSE) -> #N/A | BS96: #ERROR!
A97: ACT-SCQP56334 | B97: SC-260622-125313 | C97: 46195.537 | D97: 92 | E97: PB3572 | F97: Gestión de programas de exposiciones, actividades formativas y académicas en los Museos de la Secretaría de Cultura y actividades extramuros | G97: Creación y participación en actividades formativas y académicas de los museos adscritos a la Secretaria de Cultura | H97: SUBSECRETARÍA DE DESARROLLO Y PROMOCIÓN ARTÍSTICA Y CULTURAL | I97: DIRECCIÓN GENERAL DE MUSEOS, ARTES VISUALES Y EXPOSICIONES | J97: Número de Actividades realizadas | K97: 800 | L97: Artística | M97: Jornada: Miguel Cabrera | N97: Jornada de conferencias en torno al cierre de la exposición: Miguel Cabrera, Pintor de la Virgen María | O97: Única | P97: 46176 | Q97: 46176 | R97: 1 | S97: Cultura comunitaria | T97: Formación comunitaria | U97: Conferencia | V97: Ninguna | W97: Presencial | X97: Espacio a Cargo de la Secretaría | Y97: 5 | AB97: FALSE | AD97: FALSE | AF97: FALSE | AH97: Sin costo | AL97: ccardonav@guanajuato.gob.mx | AM97: Arraigo y empoderamiento cultural de comunidades. | AN97: 1 Tranquilidad | AO97: 1.2 Fortalecer prevención del delito | AP97: 1.2.2 Fortalecimiento del tejido social | AQ97: 1.2.3.4 Promover una cultura de paz desde las expresiones artísticas y culturales | AR97: Cooperación | AT97: Fortalecimiento de la participación ciudadana y la mediación cultural | AU97: Impulso a la ampliación de la oferta cultural en los territorios. | AV97: Fortalecer la programación cultural en espacios públicos, espacios alternativos y otros espacios culturales. | AW97: Incrementar en 25% la oferta cultural realizada en los municipios. | AX97: Conferencia | AY97: Formación | AZ97: Formación | BC97: 0 | BF97: FALSE | BM97: No | BQ97: Abierta | BR97: =VLOOKUP(BQ97, Cat_Indicadores!B:C, 2, FALSE) -> #N/A | BS97: #ERROR!
A98: ACT-SCWW65984 | B98: SC-260622-162308 | C98: 46195.683 | D98: 92 | E98: PB3572 | F98: Gestión de programas de exposiciones, actividades formativas y académicas en los Museos de la Secretaría de Cultura y actividades extramuros | G98: Creación y participación en actividades formativas y académicas de los museos adscritos a la Secretaria de Cultura | H98: SUBSECRETARÍA DE DESARROLLO Y PROMOCIÓN ARTÍSTICA Y CULTURAL | I98: DIRECCIÓN GENERAL DE MUSEOS, ARTES VISUALES Y EXPOSICIONES | J98: Número de Actividades realizadas | K98: 800 | L98: Artística | M98: Palabrasumbral, palabrasfilo. Lectura de poesía. | N98: Lectura de poesía. Un tejido verbal hecho con fibras extraídas de 13 poetas latinoamericanos del siglo XX. En torno a la exposición Bajo el signo de saturno del Museo de Arte Historia de Guanajuato. | O98: Única | P98: 46176 | Q98: 46176 | R98: 1 | S98: Literatura | T98: Fomento a la lectura | U98: Charla | V98: Ninguna | W98: Presencial | X98: Espacio a Cargo de la Secretaría | Y98: 2 | AB98: FALSE | AD98: FALSE | AF98: FALSE | AH98: Sin costo | AL98: ccardonav@guanajuato.gob.mx | AM98: Leer para crecer. | AN98: 4 Vocación | AO98: 4.4 Reforzar competencias lectoras y lógico matemáticas | AP98: 4.4.2 Competencias lectoras | AQ98: 4.4.2 Fomentar el hábito lector | AR98: Cooperación | AT98: Fortalecimiento de la participación ciudadana y la mediación cultural | AU98: Impulso a la ampliación de la oferta cultural en los territorios. | AV98: Fortalecer la programación cultural en espacios públicos, espacios alternativos y otros espacios culturales. | AW98: Incrementar en 25% la oferta cultural realizada en los municipios. | AX98: Charla | AY98: Formación | AZ98: Formación | BC98: 0 | BF98: FALSE | BM98: No | BQ98: Abierta | BR98: =VLOOKUP(BQ98, Cat_Indicadores!B:C, 2, FALSE) -> #N/A | BS98: #ERROR!
A99: ACT-SCKC43099 | B99: SC-260623-095522 | C99: 46196.413 | D99: 92 | E99: PB3572 | F99: Gestión de programas de exposiciones, actividades formativas y académicas en los Museos de la Secretaría de Cultura y actividades extramuros | G99: Creación y participación en actividades formativas y académicas de los museos adscritos a la Secretaria de Cultura | H99: SUBSECRETARÍA DE DESARROLLO Y PROMOCIÓN ARTÍSTICA Y CULTURAL | I99: DIRECCIÓN GENERAL DE MUSEOS, ARTES VISUALES Y EXPOSICIONES | J99: Número de Actividades realizadas | K99: 800 | L99: Artística | M99: Reescribir el paisaje. Taller de lectoescritura a partir de la exposición Poética del Paisaje | N99: Taller que promueve el pensamiento y la escritura a partir de la obra de Carlos Pellicer y la aproximación de las obras de la exposición que se fundó a partir del paisaje como un elemento clave en la escritura del autor. | O99: Única | P99: 46177 | Q99: 46177 | R99: 1 | S99: Literatura | T99: Fomento a la lectura | U99: Taller | V99: Ninguna | W99: Presencial | X99: Espacio a Cargo de la Secretaría | Y99: 6 | AB99: FALSE | AD99: FALSE | AF99: FALSE | AH99: Sin costo | AL99: ccardonav@guanajuato.gob.mx | AM99: Leer para crecer. | AN99: 4 Vocación | AO99: 4.4 Reforzar competencias lectoras y lógico matemáticas | AP99: 4.4.2 Competencias lectoras | AQ99: 4.4.2 Fomentar el hábito lector | AR99: Cooperación | AT99: Fortalecimiento de la participación ciudadana y la mediación cultural | AU99: Impulso a la ampliación de la oferta cultural en los territorios. | AV99: Fortalecer la programación cultural en espacios públicos, espacios alternativos y otros espacios culturales. | AW99: Incrementar en 25% la oferta cultural realizada en los municipios. | AX99: Taller | AY99: Formación | AZ99: Formación | BC99: 0 | BF99: FALSE | BM99: No | BQ99: Abierta | BR99: =VLOOKUP(BQ99, Cat_Indicadores!B:C, 2, FALSE) -> #N/A | BS99: #ERROR!
A100: ACT-SCJK78780 | B100: SC-260623-100012 | C100: 46196.417 | D100: 92 | E100: PB3572 | F100: Gestión de programas de exposiciones, actividades formativas y académicas en los Museos de la Secretaría de Cultura y actividades extramuros | G100: Creación y participación en actividades formativas y académicas de los museos adscritos a la Secretaria de Cultura | H100: SUBSECRETARÍA DE DESARROLLO Y PROMOCIÓN ARTÍSTICA Y CULTURAL | I100: DIRECCIÓN GENERAL DE MUSEOS, ARTES VISUALES Y EXPOSICIONES | J100: Número de Actividades realizadas | K100: 800 | L100: Artística | M100: Museum week: Sembrar la paz: taller de creación colectiva a partir de “Sembrador de pájaros" | N100: Actividad dirigida a niñas y niños Posteriormente, los participantes elaborarán pájaros de papel (origami) como símbolo de esperanza, comunidad y construcción colectiva. | O100: Única | P100: 46178 | Q100: 46178 | R100: 1 | S100: Artes visuales | T100: Escultura | U100: Taller | V100: Ninguna | W100: Presencial | X100: Espacio a Cargo de la Secretaría | Y100: 2 | AB100: FALSE | AD100: FALSE | AF100: FALSE | AH100: Sin costo | AL100: ccardonav@guanajuato.gob.mx | AM100: Arraigo y empoderamiento cultural de comunidades. | AN100: 2 Igualdad | AO100: 2.4 Reducir brechas de desigualdad | AP100: 2.4.3 Descentralización de la oferta cultural | AQ100: 2.4.3.1 Impulsar el desarrollo artístico y cultural entre infancias y juventudes | AR100: Cooperación | AT100: Fortalecimiento de la participación ciudadana y la mediación cultural | AU100: Impulso a la ampliación de la oferta cultural en los territorios. | AV100: Fortalecer la programación cultural en espacios públicos, espacios alternativos y otros espacios culturales. | AW100: Incrementar en 25% la oferta cultural realizada en los municipios. | AX100: Taller | AY100: Formación | AZ100: Formación | BC100: 0 | BF100: FALSE | BM100: No | BQ100: Abierta | BR100: =VLOOKUP(BQ100, Cat_Indicadores!B:C, 2, FALSE) -> #N/A | BS100: #ERROR!
A101: ACT-SCTN33043 | B101: SC-260623-100427 | C101: 46196.42 | D101: 92 | E101: PB3572 | F101: Gestión de programas de exposiciones, actividades formativas y académicas en los Museos de la Secretaría de Cultura y actividades extramuros | G101: Creación y participación en actividades formativas y académicas de los museos adscritos a la Secretaria de Cultura | H101: SUBSECRETARÍA DE DESARROLLO Y PROMOCIÓN ARTÍSTICA Y CULTURAL | I101: DIRECCIÓN GENERAL DE MUSEOS, ARTES VISUALES Y EXPOSICIONES | J101: Número de Actividades realizadas | K101: 800 | L101: Artística | M101: Danzón, patrimonio vivo, clases de baile. | N101: Sesiones guiadas de introducción al Danzón dentro del museo a cargo del Mtro. Juan Robles, director de Romance Danzonero. | O101: Única | P101: 46179 | Q101: 46179 | R101: 1 | S101: Artes escénicas | T101: Danza tradicional | U101: Taller | V101: Ninguna | W101: Presencial | X101: Espacio a Cargo de la Secretaría | Y101: 5 | AB101: FALSE | AD101: FALSE | AF101: FALSE | AH101: Sin costo | AL101: ccardonav@guanajuato.gob.mx | AM101: Arraigo y empoderamiento cultural de comunidades. | AN101: 1 Tranquilidad | AO101: 1.2 Fortalecer prevención del delito | AP101: 1.2.2 Fortalecimiento del tejido social | AQ101: 1.2.3.4 Promover una cultura de paz desde las expresiones artísticas y culturales | AR101: Cooperación | AT101: Fortalecimiento de la participación ciudadana y la mediación cultural | AU101: Impulso a la ampliación de la oferta cultural en los territorios. | AV101: Fortalecer la programación cultural en espacios públicos, espacios alternativos y otros espacios culturales. | AW101: Incrementar en 25% la oferta cultural realizada en los municipios. | AX101: Taller | AY101: Formación | AZ101: Formación | BC101: 0 | BF101: FALSE | BM101: No | BQ101: Abierta | BR101: =VLOOKUP(BQ101, Cat_Indicadores!B:C, 2, FALSE) -> #N/A | BS101: #ERROR!
A102: ACT-SCFT66371 | B102: SC-260623-100758 | C102: 46196.422 | D102: 92 | E102: PB3572 | F102: Gestión de programas de exposiciones, actividades formativas y académicas en los Museos de la Secretaría de Cultura y actividades extramuros | G102: Creación y participación en actividades formativas y académicas de los museos adscritos a la Secretaria de Cultura | H102: SUBSECRETARÍA DE DESARROLLO Y PROMOCIÓN ARTÍSTICA Y CULTURAL | I102: DIRECCIÓN GENERAL DE MUSEOS, ARTES VISUALES Y EXPOSICIONES | J102: Número de Actividades realizadas | K102: 800 | L102: Artística | M102: Diversión en los museos: Concierto Postransducción | N102: Concierto de música electroacústica y arte sonoro que concibe el sonido como materia plástica y maleable, esculpida en tiempo real a través del gesto y la tecnología. A partir de texturas densas, capas sostenidas y sonoridades ambientales, la obra constituye un universo acústico inmersivo que envuelve al espectador desde múltiples direcciones, alejándose de toda narrativa lineal o figurativa. | O102: Única | P102: 46179 | Q102: 46179 | R102: 1 | S102: Música | T102: Composición musical | U102: Presentación artística | V102: Ninguna | W102: Presencial | X102: Espacio a Cargo de la Secretaría | Y102: 6 | AB102: FALSE | AD102: FALSE | AF102: FALSE | AH102: Sin costo | AL102: ccardonav@guanajuato.gob.mx | AM102: Arraigo y empoderamiento cultural de comunidades. | AN102: 1 Tranquilidad | AO102: 1.2 Fortalecer prevención del delito | AP102: 1.2.2 Fortalecimiento del tejido social | AQ102: 1.2.3.4 Promover una cultura de paz desde las expresiones artísticas y culturales | AR102: Cooperación | AT102: Fortalecimiento de la participación ciudadana y la mediación cultural | AU102: Impulso a la ampliación de la oferta cultural en los territorios. | AV102: Fortalecer la programación cultural en espacios públicos, espacios alternativos y otros espacios culturales. | AW102: Incrementar en 25% la oferta cultural realizada en los municipios. | AX102: Presentación artística | AY102: Formación | AZ102: Profesionalización | BC102: 0 | BF102: FALSE | BM102: No | BQ102: Abierta | BR102: =VLOOKUP(BQ102, Cat_Indicadores!B:C, 2, FALSE) -> #N/A | BS102: #ERROR!
...

Sheet Registro_Territorio
A1: ID_Territorio | B1: ID_Actividad | C1: Municipio | D1: Tipo_Asentamiento | E1: Comunidad | F1: Nombre_Comunidad | G1: Otra_Comunidad | H1: ZAP_Nuevo_Comienzo | I1: ZAP_SSyP | J1: Cantidad | K1: Cantidad_Participacion | L1: Cantidad_Acceso | M1: Nombre_Comunidad_Final | N1: ZAP_NC_SI_NO | O1: ZAP_SSyP_SI_NO | P1: Tipo_Impacto
A2: 4db1e6e8 | B2: ACT00031 | C2: León | D2: Periurbano | E2: 100 | F2: Las Joyas | H2: Si | I2: No | J2: 11 | K2: 11 | L2: 0 | M2: =IF(F2<>"", F2, G2) -> Las Joyas | N2: =IF(ISNUMBER(FIND("ZP", H2)), "Si", "No") -> No | O2: =IF(I2=TRUE, "Si", "No") -> No
A3: 2d81693b | B3: ACT00032 | C3: León | D3: Periurbano | E3: 115 | F3: El Carmen | H3: Si | I3: No | J3: 8 | L3: 8 | M3: =IF(F3<>"", F3, G3) -> El Carmen | N3: =IF(ISNUMBER(FIND("ZP", H3)), "Si", "No") -> No | O3: =IF(I3=TRUE, "Si", "No") -> No
A4: 635c2bd3 | B4: ACT00033 | C4: Silao de la Victoria | D4: Urbano | E4: 215 | F4: Silao | H4: Si | I4: Si | J4: 15 | K4: 15 | L4: 0 | M4: =IF(F4<>"", F4, G4) -> Silao | N4: =IF(ISNUMBER(FIND("ZP", H4)), "Si", "No") -> No | O4: =IF(I4=TRUE, "Si", "No") -> No
A5: 9803f503 | B5: ACT00034 | C5: Silao de la Victoria | D5: Urbano | E5: 215 | F5: Silao | H5: Si | I5: Si | J5: 12 | K5: 12 | L5: 0 | M5: =IF(F5<>"", F5, G5) -> Silao | N5: =IF(ISNUMBER(FIND("ZP", H5)), "Si", "No") -> No | O5: =IF(I5=TRUE, "Si", "No") -> No
A6: c28cdb33 | B6: ACT00035 | C6: Silao de la Victoria | D6: Urbano | E6: 215 | F6: Silao | H6: Si | I6: Si | J6: 28 | K6: 28 | L6: 0 | M6: =IF(F6<>"", F6, G6) -> Silao | N6: =IF(ISNUMBER(FIND("ZP", H6)), "Si", "No") -> No | O6: =IF(I6=TRUE, "Si", "No") -> No
A7: 88f64665 | B7: ACT00036 | C7: León | D7: Periurbano | E7: 100 | F7: Las Joyas | H7: Si | I7: No | J7: 24 | K7: 24 | L7: 0 | M7: =IF(F7<>"", F7, G7) -> Las Joyas | N7: =IF(ISNUMBER(FIND("ZP", H7)), "Si", "No") -> No | O7: =IF(I7=TRUE, "Si", "No") -> No
A8: 6143a7e4 | B8: ACT00037 | C8: León | D8: Periurbano | E8: 100 | F8: Las Joyas | H8: Si | I8: No | J8: 10 | K8: 10 | L8: 0 | M8: =IF(F8<>"", F8, G8) -> Las Joyas | N8: =IF(ISNUMBER(FIND("ZP", H8)), "Si", "No") -> No | O8: =IF(I8=TRUE, "Si", "No") -> No
A9: bfb569f3 | B9: ACT00038 | C9: Silao de la Victoria | D9: Urbano | E9: 215 | F9: Silao | H9: Si | I9: Si | J9: 101 | K9: 101 | L9: 0 | M9: =IF(F9<>"", F9, G9) -> Silao | N9: =IF(ISNUMBER(FIND("ZP", H9)), "Si", "No") -> No | O9: =IF(I9=TRUE, "Si", "No") -> No
A10: 0229b757 | B10: ACT00039 | C10: Silao de la Victoria | D10: Urbano | E10: 215 | F10: Silao | H10: Si | I10: Si | J10: 101 | K10: 101 | L10: 0 | M10: =IF(F10<>"", F10, G10) -> Silao | N10: =IF(ISNUMBER(FIND("ZP", H10)), "Si", "No") -> No | O10: =IF(I10=TRUE, "Si", "No") -> No
A11: 230eb128 | B11: ACT00040 | C11: Silao de la Victoria | D11: Urbano | E11: 215 | F11: Silao | H11: Si | I11: Si | J11: 101 | L11: 101 | M11: =IF(F11<>"", F11, G11) -> Silao | N11: =IF(ISNUMBER(FIND("ZP", H11)), "Si", "No") -> No | O11: =IF(I11=TRUE, "Si", "No") -> No
A12: 1aadd56c | B12: ACT00041 | C12: Silao de la Victoria | D12: Urbano | E12: 215 | F12: Silao | H12: Si | I12: Si | J12: 101 | K12: 101 | L12: 0 | M12: =IF(F12<>"", F12, G12) -> Silao | N12: =IF(ISNUMBER(FIND("ZP", H12)), "Si", "No") -> No | O12: =IF(I12=TRUE, "Si", "No") -> No
A13: 5d4f3ca5 | B13: ACT00042 | C13: Silao de la Victoria | D13: Urbano | E13: 215 | F13: Silao | H13: Si | I13: Si | J13: 101 | L13: 101 | M13: =IF(F13<>"", F13, G13) -> Silao | N13: =IF(ISNUMBER(FIND("ZP", H13)), "Si", "No") -> No | O13: =IF(I13=TRUE, "Si", "No") -> No
A14: 73fac33e | B14: ACT00043 | C14: Silao de la Victoria | D14: Urbano | E14: 215 | F14: Silao | H14: Si | I14: Si | J14: 101 | L14: 101 | M14: =IF(F14<>"", F14, G14) -> Silao | N14: =IF(ISNUMBER(FIND("ZP", H14)), "Si", "No") -> No | O14: =IF(I14=TRUE, "Si", "No") -> No
A15: 36df9867 | B15: ACT00044 | C15: Silao de la Victoria | D15: Urbano | E15: 215 | F15: Silao | H15: Si | I15: Si | J15: 101 | L15: 101 | M15: =IF(F15<>"", F15, G15) -> Silao | N15: =IF(ISNUMBER(FIND("ZP", H15)), "Si", "No") -> No | O15: =IF(I15=TRUE, "Si", "No") -> No
A16: d41e5cba | B16: ACT00045 | C16: Silao de la Victoria | D16: Urbano | E16: 215 | F16: Silao | H16: Si | I16: Si | J16: 101 | L16: 101 | M16: =IF(F16<>"", F16, G16) -> Silao | N16: =IF(ISNUMBER(FIND("ZP", H16)), "Si", "No") -> No | O16: =IF(I16=TRUE, "Si", "No") -> No
A17: 615b692e | B17: ACT00046 | C17: Silao de la Victoria | D17: Urbano | E17: 215 | F17: Silao | H17: Si | I17: Si | J17: 101 | L17: 101 | M17: =IF(F17<>"", F17, G17) -> Silao | N17: =IF(ISNUMBER(FIND("ZP", H17)), "Si", "No") -> No | O17: =IF(I17=TRUE, "Si", "No") -> No
A18: 8fadd5d8 | B18: ACT00017 | C18: León | D18: Urbano | H18: No | I18: No | J18: 62 | K18: 20 | L18: 42 | M18: =IF(F18<>"", F18, G18) -> 0 | N18: =IF(ISNUMBER(FIND("ZP", H18)), "Si", "No") -> No | O18: =IF(I18=TRUE, "Si", "No") -> No
A19: 6a4f19f2 | B19: ACT00018 | C19: León | D19: Urbano | G19: La Martinica | H19: No | I19: No | J19: 146 | K19: 17 | L19: 129 | M19: =IF(F19<>"", F19, G19) -> La Martinica | N19: =IF(ISNUMBER(FIND("ZP", H19)), "Si", "No") -> No | O19: =IF(I19=TRUE, "Si", "No") -> No
A20: ff181aeb | B20: ACT00019 | C20: León | D20: Urbano | G20: La Martinica | H20: No | I20: No | J20: 26 | K20: 26 | L20: 0 | M20: =IF(F20<>"", F20, G20) -> La Martinica | N20: =IF(ISNUMBER(FIND("ZP", H20)), "Si", "No") -> No | O20: =IF(I20=TRUE, "Si", "No") -> No
A21: ae5f76ef | B21: ACT00020 | C21: León | D21: Urbano | G21: La Martinica | H21: No | I21: No | J21: 16 | K21: 16 | L21: 0 | M21: =IF(F21<>"", F21, G21) -> La Martinica | N21: =IF(ISNUMBER(FIND("ZP", H21)), "Si", "No") -> No | O21: =IF(I21=TRUE, "Si", "No") -> No
A22: 7e8b2e19 | B22: ACT00021 | C22: León | D22: Urbano | G22: La Martinica | H22: No | I22: No | J22: 146 | K22: 17 | L22: 129 | M22: =IF(F22<>"", F22, G22) -> La Martinica | N22: =IF(ISNUMBER(FIND("ZP", H22)), "Si", "No") -> No | O22: =IF(I22=TRUE, "Si", "No") -> No
A23: 3b2905c8 | B23: ACT00023 | C23: León | D23: Urbano | G23: La Martinica | H23: No | I23: No | J23: 352 | L23: 352 | M23: =IF(F23<>"", F23, G23) -> La Martinica | N23: =IF(ISNUMBER(FIND("ZP", H23)), "Si", "No") -> No | O23: =IF(I23=TRUE, "Si", "No") -> No
A24: f64e11ca | B24: ACT00024 | C24: León | D24: Urbano | G24: La Martinica | H24: No | I24: No | J24: 214 | L24: 214 | M24: =IF(F24<>"", F24, G24) -> La Martinica | N24: =IF(ISNUMBER(FIND("ZP", H24)), "Si", "No") -> No | O24: =IF(I24=TRUE, "Si", "No") -> No
A25: 28aa1a2e | B25: ACT00025 | C25: León | D25: Urbano | G25: La Martinica | H25: No | I25: No | J25: 30 | K25: 1 | L25: 29 | M25: =IF(F25<>"", F25, G25) -> La Martinica | N25: =IF(ISNUMBER(FIND("ZP", H25)), "Si", "No") -> No | O25: =IF(I25=TRUE, "Si", "No") -> No
A26: 94c7aafa | B26: ACT00026 | C26: León | D26: Urbano | G26: La Martinica | H26: No | I26: No | J26: 7 | K26: 7 | L26: 0 | M26: =IF(F26<>"", F26, G26) -> La Martinica | N26: =IF(ISNUMBER(FIND("ZP", H26)), "Si", "No") -> No | O26: =IF(I26=TRUE, "Si", "No") -> No
A27: 8e7764b4 | B27: ACT00027 | C27: León | D27: Urbano | G27: La Martinica | H27: No | I27: No | J27: 119 | L27: 119 | M27: =IF(F27<>"", F27, G27) -> La Martinica | N27: =IF(ISNUMBER(FIND("ZP", H27)), "Si", "No") -> No | O27: =IF(I27=TRUE, "Si", "No") -> No
A28: 53fe3fb0 | B28: ACT00028 | C28: León | D28: Urbano | G28: La Martinica | H28: No | I28: No | J28: 67 | K28: 8 | L28: 59 | M28: =IF(F28<>"", F28, G28) -> La Martinica | N28: =IF(ISNUMBER(FIND("ZP", H28)), "Si", "No") -> No | O28: =IF(I28=TRUE, "Si", "No") -> No
A29: 9d52d8b6 | B29: ACT00029 | C29: León | D29: Urbano | G29: La Martinica | H29: No | I29: No | J29: 44 | K29: 1 | L29: 43 | M29: =IF(F29<>"", F29, G29) -> La Martinica | N29: =IF(ISNUMBER(FIND("ZP", H29)), "Si", "No") -> No | O29: =IF(I29=TRUE, "Si", "No") -> No
A30: 45d69317 | B30: ACT00030 | C30: León | D30: Urbano | G30: La Martinica | H30: No | I30: No | J30: 82 | K30: 1 | L30: 81 | M30: =IF(F30<>"", F30, G30) -> La Martinica | N30: =IF(ISNUMBER(FIND("ZP", H30)), "Si", "No") -> No | O30: =IF(I30=TRUE, "Si", "No") -> No
A32: 4c11174b | B32: ACT-SCHP41657 | C32: Guanajuato | D32: Urbano | E32: 49 | F32: Guanajuato | H32: Si | I32: Si | J32: 33 | L32: 33 | M32: =IF(F32<>"", F32, G32) -> Guanajuato | N32: =IF(ISNUMBER(FIND("ZP", H32)), "Si", "No") -> No | O32: =IF(I32=TRUE, "Si", "No") -> No
A33: 9d2da3d8 | B33: ACT-SCXD05649 | C33: Guanajuato | D33: Urbano | E33: 49 | F33: Guanajuato | H33: Si | I33: Si | J33: 11 | K33: 11 | L33: 0 | M33: =IF(F33<>"", F33, G33) -> Guanajuato | N33: =IF(ISNUMBER(FIND("ZP", H33)), "Si", "No") -> No | O33: =IF(I33=TRUE, "Si", "No") -> No
A34: 565f3868 | B34: ACT-SCQF07472 | C34: Guanajuato | D34: Urbano | E34: 49 | F34: Guanajuato | H34: Si | I34: Si | J34: 20 | L34: 20 | M34: =IF(F34<>"", F34, G34) -> Guanajuato | N34: =IF(ISNUMBER(FIND("ZP", H34)), "Si", "No") -> No | O34: =IF(I34=TRUE, "Si", "No") -> No
A35: a2236ecd | B35: ACT-SCNJ91361 | C35: Guanajuato | D35: Urbano | E35: 49 | F35: Guanajuato | H35: Si | I35: Si | J35: 53 | K35: 53 | L35: 0 | M35: =IF(F35<>"", F35, G35) -> Guanajuato | N35: =IF(ISNUMBER(FIND("ZP", H35)), "Si", "No") -> No | O35: =IF(I35=TRUE, "Si", "No") -> No
A36: 80ad4989 | B36: ACT-SCNO77641 | C36: Guanajuato | D36: Urbano | G36: GUANAJUATO CENTRO | H36: No | I36: No | J36: 49 | L36: 49 | M36: =IF(F36<>"", F36, G36) -> GUANAJUATO CENTRO | N36: =IF(ISNUMBER(FIND("ZP", H36)), "Si", "No") -> No | O36: =IF(I36=TRUE, "Si", "No") -> No
